Workbook

Sheet ① Assumptions
A1: AUSTRALIAN CHILD EDUCATION FINANCIAL MODEL
A2: 📋 STEP 1 OF 1: Fill in the blue cells below → then view ② Dashboard for your results → ③ Analysis for detailed breakdowns
A3: LEGEND: | B3: ✎ YOU EDIT THIS COLUMN | C3: ƒx FORMULA | D3: ● FIXED / REFERENCE
A4: SECTION 1: CHILD & GENERAL DETAILS
A5: Child Birth Year | B5: 2024 | D5: ✎ Enter birth year (e.g. 2025)
A6: State | B6: VIC | D6: ✎ VIC or NSW
A7: General Inflation Rate (CPI) | B7: 0.03 | D7: ✎ Annual CPI inflation (e.g. 3%)
A8: Education Inflation Rate | B8: 0.05 | D8: ✎ Education-specific inflation (e.g. 5%)
A10: SECTION 2: SCHOOL PATHWAY
A11: School Type | B11: Public | D11: ✎ Public or Private
A12: Private School Entry Grade | B12: 5 | D12: ✎ Prep, 5, 7, 9, or 12
A13: Selected School (VIC) | B13: Haileybury | D13: ✎ See School Fee Reference tab
A14: Selected School (NSW) | B14: The Scots College | D14: ✎ See School Fee Reference tab
A16: SECTION 3: CHILDCARE (Age 0–4)
A17: Use Childcare? | B17: Yes | D17: ✎ Yes or No
A18: Childcare Start Age | B18: 1 | D18: ✎ Age child starts childcare (0–4)
A19: Childcare End Age | B19: 4 | D19: ✎ Age child ends childcare
A20: Daily Childcare Rate ($) | B20: 169 | D20: ✎ Daily fee (avg $100–$180/day)
A21: Days per Week | B21: 2 | D21: ✎ Days per week (1–5)
A22: CCS Rebate % (Auto from Income) | B22: =IF(B108<=83280,0.9,IF(B108>=533280,0,MAX(0,0.9-((B108-83280)/(533280-83280))*0.9))) -> 0.82656 | D22: ← ƒx Auto-calculated from family income; override below
A23: CCS Override % (Manual) | D23: ✎ Leave blank to use auto-calc; enter 0–0.95 to override
A24: Childcare Weeks per Year | B24: 48 | D24: ✎ Typically 48 weeks (excl. holidays); max 52
A25: Annual Childcare Cost (Gross) | B25: =B20*B21*B24 -> 16224 | D25: ← ƒx Calculated: Daily Rate × Days × Weeks/yr
A26: Annual Childcare Cost (Net of CCS) | B26: =B25*(1-IF(B23<>"",B23,B22)) -> 2813.8906 | D26: ← ƒx Calculated: Gross cost × (1 − effective CCS %)
A28: SECTION 4: BEFORE/AFTER SCHOOL CARE (Age 5–12)
A29: Use Before/After School Care? | B29: Yes | D29: ✎ Yes or No
A30: Daily Rate ($) | B30: 30 | D30: ✎ Per session ($20–$35)
A31: Days per Week | B31: 5 | D31: ✎ Days per week (1–5)
A32: Sessions per Day | B32: 2 | D32: ✎ 1 (before OR after) or 2 (both)
A33: Annual Before/After Care Cost | B33: =B30*B31*B32*40 -> 12000 | D33: ← ƒx Calculated: Rate × Days × Sessions × 40 weeks
A35: SECTION 5: UNIVERSITY
A36: Degree Length (Years) | B36: 3 | D36: ✎ 3 (standard), 4 (Eng/Hons), 5–6 (Med/Law)
A37: School Scholarship % Discount | B37: 0 | D37: ✎ 0% = no scholarship; 10–50% typical bursary
A38: University Scholarship % Discount | B38: 0 | D38: ✎ 0% = no scholarship; 10–50% merit-based
A39: University Type | B39: Domestic | D39: ✎ Domestic or International
A40: HECS Band (if Domestic) | B40: Band 2 | D40: ✎ Band 1 / 2 / 3 / 4 (see Uni Reference)
A41: International Annual Fee ($) | B41: 45000 | D41: ✎ If International ($20k–$50k/yr)
A42: Living Arrangement | B42: At Home | D42: ✎ At Home or Away
A43: Annual Living Cost (if Away) | B43: 22000 | D43: ✎ Rent, food, utilities ($15k–$25k/yr)
A44: Textbooks & Materials (Annual) | B44: 1000 | D44: ✎ Annual ($500–$1,500)
A46: SECTION 6: HEALTH & WELLBEING
A47: Private Health Insurance (Family, Annual) | B47: 4500 | D47: ✎ Family premium ($3k–$6k/yr)
A48: Health Insurance Inflation Rate | B48: 0.06 | D48: ✎ Typically 6–8%/yr (higher than CPI)
A49: Childcare Inflation Rate | B49: 0.05 | D49: ✎ Typically 5–7%/yr (faster than general CPI)
A50: Orthodontics (Total Cost) | B50: 7000 | D50: ✎ Total cost ($5k–$9k over treatment)
A51: Orthodontics Start Age | B51: 12 | D51: ✎ Typically age 10–13
A52: Orthodontics Duration (Years) | B52: 2 | D52: ✎ Usually 1–3 years
A53: Allied Health (Annual, e.g. speech, OT) | B53: 2000 | D53: ✎ Annual cost ($0 if not needed)
A54: Allied Health Ages (Start–End) | B54: 3–8 | D54: ✎ Start age – End age (e.g. 3–8)
A57: SECTION 7: EXTRA-CURRICULARS
A58: Category | B58: Include? | C58: Annual Cost ($) | D58: Start Age | E58: End Age
A59: Sports (club fees, equipment) | B59: Yes | C59: 2500 | D59: 5 | E59: 18
A60: Music / Arts (lessons, instruments) | B60: Yes | C60: 3000 | D60: 6 | E60: 18
A61: Tutoring | B61: Yes | C61: 4000 | D61: 10 | E61: 18
A62: Technology (coding, robotics) | B62: No | C62: 1500 | D62: 8 | E62: 16
A63: Camps / Holiday Programs | B63: Yes | C63: 2000 | D63: 5 | E63: 17
A64: Swimming Lessons | B64: Yes | C64: 1200 | D64: 3 | E64: 10
A66: SECTION 8: TECHNOLOGY & DEVICES
A67: School Laptop Cost ($) | B67: 2000 | D67: ✎ Laptop cost (replaced per frequency below)
A68: Laptop Replacement Frequency (Years) | B68: 3 | D68: ✎ Every 2–4 years
A69: Laptop Start Age | B69: 10 | D69: ✎ Many schools require from Yr 5–7
A70: Phone (First Purchase, Age) | B70: 12 | D70: ✎ Age of first phone
A71: Phone Cost ($) | B71: 1200 | D71: ✎ Phone cost (replaced per frequency below)
A72: Phone Replacement Frequency (Years) | B72: 3 | D72: ✎ Every 2–3 years
A74: SECTION 9: DRIVING & TRANSPORT (Age 16–18)
A75: Include Driving Costs? | B75: Yes | D75: ✎ Yes or No
A76: Driving Lessons (Total) | B76: 1500 | D76: ✎ Total cost (~$60/hr × 20–25 lessons)
A77: Driving Lesson Age | B77: 16 | D77: ✎ Learner permit age (typically 16)
A78: First Car Cost ($) | B78: 15000 | D78: ✎ $0 if not purchasing a car
A79: First Car Purchase Age | B79: 18 | D79: ✎ Age of first car purchase
A80: Car Insurance & Rego (Annual) | B80: 3000 | D80: ✎ Annual cost from purchase age
A82: SECTION 10: GAP YEAR & OTHER
A83: Include Gap Year? | B83: No | D83: ✎ Yes or No (between school & uni)
A84: Gap Year Budget ($) | B84: 15000 | D84: ✎ Travel & living costs ($5k–$20k)
A85: School Uniforms (Annual) | B85: 1500 | D85: ✎ Private $1k–$2k; Public $300–$500
A86: School Camps & Excursions (Annual) | B86: 1000 | D86: ✎ Annual ($200–$2,000/yr)
A89: SECTION 11: FUNDING & INVESTMENT
A90: Initial Lump Sum ($) | B90: 50000 | D90: ✎ One-time deposit at Year 0
A91: Regular Contribution ($) | B91: 1000 | D91: ✎ Periodic contribution amount
A92: Contribution Frequency | B92: Monthly | D92: ✎ Monthly, Quarterly, or Annually
A93: Annual Contribution | B93: =IF(B92="Monthly",B91*12,IF(B92="Quarterly",B91*4,B91)) -> 12000 | D93: ← ƒx Calculated: from contribution amount & frequency
A94: Contribution Growth Rate (Annual) | B94: =B99 -> 0.035 | D94: ✎ Annual increase in contributions
A95: Assumed Rate of Return | B95: 0.06 | D95: ✎ Expected investment return (e.g. 6%)
A96: Marginal Tax Rate | B96: 0.325 | D96: ✎ Your marginal tax rate (e.g. 32.5%, 37%, 45%)
A97: Effective Net Return | B97: =IF(B100="Yes",B95,B95*(1-B96)) -> 0.0405 | D97: ← ƒx If Ed Bond: gross return; else: return × (1 − tax rate)
A98: Contingency Buffer % | B98: 0.05 | D98: ✎ 5–10% buffer for unexpected costs
A99: Wage Growth Rate | B99: 0.035 | D99: ✎ Link contribution growth to salary increases (~3–4%)
A100: Use Education Bond? | B100: No | D100: ✎ Yes or No (tax-advantaged after 10yr)
A101: Education Bond Initial Amount ($) | B101: 0 | D101: ✎ If using education bond
A102: Life Insurance (Annual Premium) | B102: 1500 | D102: ✎ Protecting education funding
A103: Risk-Free Rate (Opportunity Cost) | B103: 0.0425 | D103: ✎ Risk-free rate for opportunity cost (e.g. 10yr AU govt bond ~4.25%)
A104: Borrowing Rate (Debt Funding) | B104: 0.065 | D104: ✎ Rate charged when fund balance is negative (e.g. personal loan ~6.5%)
A105: Effective Borrowing Rate (After Tax) | B105: =B104*(1-B96) -> 0.043875 | D105: ← ƒx Borrowing rate × (1 − tax rate) — interest may be deductible
A106: SECTION 12: GOVERNMENT BENEFITS
A107: Include Government Benefits? | B107: Yes | D107: ✎ Yes or No
A108: Family Taxable Income ($) | B108: 120000 | D108: ✎ Affects FTB & CCS eligibility
A109: FTB Part A (Annual, Age 0–12) | B109: 5903 | D109: ✎ Max ~$227/fn (~$5,903/yr per child)
A110: FTB Part A (Annual, Age 13–19) | B110: 7187 | D110: ✎ Max ~$276/fn (~$7,187/yr per child)
A111: FTB Part B (Annual) | B111: 4550 | D111: ✎ Max ~$175/fn; income-tested
A112: FTB Part A Supplement (Annual) | B112: 916 | D112: ✎ End-of-year supplement
...

Sheet ② Dashboard
B1: 📊 YOUR CHILD EDUCATION COST SUMMARY | H1: Year | I1: Fund Balance ($)
B2: All figures update automatically | ← Change inputs on tab ① Assumptions | → Deep analysis on tab ③ Analysis | H2: =0 -> 0 | I2: ='④ Cash Flow Model'!D35 -> 52369
H3: =1 -> 1 | I3: ='④ Cash Flow Model'!E35 -> 53745.95
B4: PLAN STATUS | E4: YOUR CHOICES | H4: =2 -> 2 | I4: ='④ Cash Flow Model'!F35 -> 55006.146
B5: Total Cost (Birth to Age 21) | C5: ='③ Analysis'!B5 -> 1233062.9 | E5: School | F5: =IF('① Assumptions'!B11="Public","Public School",'① Assumptions'!B13) -> Public School | H5: =3 -> 3 | I5: ='④ Cash Flow Model'!G35 -> 52458.176
B6: That's roughly per year: | C6: =C5/22 -> 56048.313 | E6: School Type | F6: ='① Assumptions'!B11 -> Public | H6: =4 -> 4 | I6: ='④ Cash Flow Model'!H35 -> 53038.384
E7: Private School Entry | F7: =IF('① Assumptions'!B11="Public","N/A",'① Assumptions'!B12) -> N/A | H7: =5 -> 5 | I7: ='④ Cash Flow Model'!I35 -> 31912.853
B8: Your Savings Plan | C8: ='① Assumptions'!B90 -> 50000 | E8: University | F8: ='① Assumptions'!B39&" ("&'① Assumptions'!B40&")" -> Domestic (Band 2) | H8: =6 -> 6 | I8: ='④ Cash Flow Model'!J35 -> 5018.8083
B9: (initial lump sum investment) | E9: Uni Living | F9: ='① Assumptions'!B42 -> At Home | H9: =7 -> 7 | I9: ='④ Cash Flow Model'!K35 -> -24289.135
B10: You also save monthly: | C10: ='① Assumptions'!B91 -> 1000 | E10: Childcare | F10: ='① Assumptions'!B17 -> Yes | H10: =8 -> 8 | I10: ='④ Cash Flow Model'!L35 -> -56257.529
E11: State | F11: ='① Assumptions'!B6 -> VIC | H11: =9 -> 9 | I11: ='④ Cash Flow Model'!M35 -> -88350.345
B12: Funding Gap at Age 21 | C12: ='③ Analysis'!B9 -> -660504.36 | E12: Birth Year | F12: ='① Assumptions'!B5 -> 2024 | H12: =10 -> 10 | I12: ='④ Cash Flow Model'!N35 -> -131771.58
H13: =11 -> 11 | I13: ='④ Cash Flow Model'!O35 -> -174230.03
B14: 💰 WHERE DOES THE MONEY GO? | E14: 🎓 COST BY LIFE STAGE | H14: =12 -> 12 | I14: ='④ Cash Flow Model'!P35 -> -227883.94
B15: Category | C15: 21-Year Total | E15: Life Stage | F15: Total Cost | H15: =13 -> 13 | I15: ='④ Cash Flow Model'!Q35 -> -261538.28
B16: =INDEX('③ Analysis'!A22:A38,MATCH(LARGE('③ Analysis'!B22:B38,1),'③ Analysis'!B22:B38,0)) -> Extra-Curriculars | C16: =LARGE('③ Analysis'!B22:B38,1) -> 207947.54 | E16: 👶 Baby & Toddler (Age 0–4) | F16: =SUM('④ Cash Flow Model'!D31:H31) -> 130320.73 | H16: =14 -> 14 | I16: ='④ Cash Flow Model'!R35 -> -288883.87
B17: =INDEX('③ Analysis'!A22:A38,MATCH(LARGE('③ Analysis'!B22:B38,2),'③ Analysis'!B22:B38,0)) -> Health Insurance | C17: =LARGE('③ Analysis'!B22:B38,2) -> 195265.31 | E17: 🏠 Primary School (Age 5–11) | F17: =SUM('④ Cash Flow Model'!I31:O31) -> 429583.94 | H17: =15 -> 15 | I17: ='④ Cash Flow Model'!S35 -> -320125.02
B18: =INDEX('③ Analysis'!A22:A38,MATCH(LARGE('③ Analysis'!B22:B38,3),'③ Analysis'!B22:B38,0)) -> Before/After School Care | C18: =LARGE('③ Analysis'!B22:B38,3) -> 146248.22 | E18: 📚 Secondary School (Age 12–17) | F18: =SUM('④ Cash Flow Model'!P31:U31) -> 379198.03 | H18: =16 -> 16 | I18: ='④ Cash Flow Model'!T35 -> -357443.35
B19: =INDEX('③ Analysis'!A22:A38,MATCH(LARGE('③ Analysis'!B22:B38,4),'③ Analysis'!B22:B38,0)) -> University Fees | C19: =LARGE('③ Analysis'!B22:B38,4) -> 60854.261 | E19: 🎓 University (Age 18–20) | F19: =SUM('④ Cash Flow Model'!V31:X31) -> 247620.94 | H19: =17 -> 17 | I19: ='④ Cash Flow Model'!U35 -> -398836.18
B20: =INDEX('③ Analysis'!A22:A38,MATCH(LARGE('③ Analysis'!B22:B38,5),'③ Analysis'!B22:B38,0)) -> Car Costs | C20: =LARGE('③ Analysis'!B22:B38,5) -> 46903.531 | E20: 🌟 Post-Uni (Age 21) | F20: ='④ Cash Flow Model'!Y31 -> 46339.232 | H20: =18 -> 18 | I20: ='④ Cash Flow Model'!V35 -> -489440.66
B21: Everything Else | C21: ='③ Analysis'!B41-SUM(C16:C20) -> 575844.02 | E21: TOTAL | F21: =SUM(F16:F20) -> 1233062.9 | H21: =19 -> 19 | I21: ='④ Cash Flow Model'!W35 -> -543276.11
H22: =20 -> 20 | I22: ='④ Cash Flow Model'!X35 -> -612025.68
B23: 💡 WHAT YOU SHOULD KNOW | E23: ✅ QUICK TIPS TO SAVE MONEY | H23: =21 -> 21 | I23: ='④ Cash Flow Model'!Y35 -> -660504.36
B24: =IF(C12<0,"⚠️ Your plan has a funding gap of "&TEXT(-C12,"$#,##0")&". You'll need to save more, invest better, or reduce costs.","✅ Great news! Your plan is fully funded with "&TEXT(C12,"$#,##0")&" to spare.") -> ⚠️ Your plan has a funding gap of $660,504. You'll need to save more, invest better, or reduce costs. | E24: ="1️⃣ Living Costs & Extra-Curriculars are the biggest drivers ("&TEXT(('③ Analysis'!B39+'③ Analysis'!B27)/'③ Analysis'!B41,"0%")&" of total). Review Section 7 & 14 on ① Assumptions." -> 1️⃣ Living Costs & Extra-Curriculars are the biggest drivers (45% of total). Review Section 7 & 14 on ① Assumptions.
B25: =IF('③ Analysis'!B9>=0,"✅ Your plan is on track — the fund is projected to be fully funded at Age 21.","💵 Even at your current "&TEXT('① Assumptions'!B93,"$#,##0")&"/year contribution, the plan has a "&TEXT(ABS('③ Analysis'!B9),"$#,##0")&" shortfall. The gap is driven by costs compounding faster than investment returns — try increasing contributions or reducing costs on tab ① Assumptions.") -> 💵 Even at your current $12,000/year contribution, the plan has a $660,504 shortfall. The gap is driven by costs compounding faster than investment returns — try increasing contributions or reducing costs on tab ① Assumptions. | E25: 2️⃣ Switch to Public school or delay Private entry to Year 7/9 — saves years of compounding school fees. Change on ① Assumptions (Section 2).
B26: ="🏦 Your $"&TEXT('① Assumptions'!B90,"#,##0")&" lump sum grows to ~$"&TEXT('① Assumptions'!B90*(1+'① Assumptions'!B97)^21,"#,##0")&" over 21 years at "&TEXT('① Assumptions'!B97,"0.0%")&" net return ("&TEXT('① Assumptions'!B95,"0%")&" gross, "&TEXT('① Assumptions'!B96,"0%")&" tax)." -> 🏦 Your $50,000 lump sum grows to ~$115,094 over 21 years at 4.1% net return (6% gross, 33% tax). | E26: 3️⃣ Increase your monthly contribution by even $200 — it compounds significantly over 21 years. Update on ① Assumptions (Section 11). | H26: Year | I26: Total Costs ($) | J26: Total Income ($)
B27: ="📈 Your most expensive life stage is "&INDEX(E16:E20,MATCH(MAX(F16:F20),F16:F20,0))&" at "&TEXT(MAX(F16:F20),"$#,##0")&" — "&TEXT(MAX(F16:F20)/C5,"0%")&" of your total 21-year spend." -> 📈 Your most expensive life stage is 🏠 Primary School (Age 5–11) at $429,584 — 35% of your total 21-year spend. | E27: 4️⃣ Check your CCS rebate % on ① Assumptions (B22) — many families under-claim the Child Care Subsidy. | H27: =0 -> 0 | I27: ='④ Cash Flow Model'!D26 -> 0 | J27: ='④ Cash Flow Model'!D31 -> 21000
B28: ="👨‍👩‍👧 Government benefits cover $"&TEXT('③ Analysis'!B7,"#,##0")&" of your costs over 21 years (FTB + CCS)." -> 👨‍👩‍👧 Government benefits cover $296,693 of your costs over 21 years (FTB + CCS). | E28: 5️⃣ Use HECS-HELP for uni (Band 1–2) — it’s interest-free and indexed to CPI only, not education inflation. Update on ① Assumptions (Section 5). | H28: =1 -> 1 | I28: ='④ Cash Flow Model'!E26 -> 0 | J28: ='④ Cash Flow Model'!E31 -> 24874.064
B29: ="📊 "&INDEX('③ Analysis'!A22:A40,MATCH(MAX('③ Analysis'!B22:B40),'③ Analysis'!B22:B40,0))&" is your biggest cost at "&TEXT(MAX('③ Analysis'!B22:B40),"$#,##0")&" ("&TEXT(MAX('③ Analysis'!C22:C40),"0%")&" of total) — review this category on tab ① Assumptions." -> 📊 Living Costs is your biggest cost at $348,455 (28% of total) — review this category on tab ① Assumptions. | H29: =2 -> 2 | I29: ='④ Cash Flow Model'!F26 -> 0 | J29: ='④ Cash Flow Model'!F31 -> 25832.588
B30: ="⭐ Education inflation ("&TEXT('① Assumptions'!B8,"0%")&"/yr) is higher than general CPI ("&TEXT('① Assumptions'!B7,"0%")&"/yr) — costs rise faster than everything else." -> ⭐ Education inflation (5%/yr) is higher than general CPI (3%/yr) — costs rise faster than everything else. | H30: =3 -> 3 | I30: ='④ Cash Flow Model'!G26 -> 0 | J30: ='④ Cash Flow Model'!G31 -> 30503.547
H31: =4 -> 4 | I31: ='④ Cash Flow Model'!H26 -> 0 | J31: ='④ Cash Flow Model'!H31 -> 28110.533
B32: 📖 HOW TO USE THIS MODEL | H32: =5 -> 5 | I32: ='④ Cash Flow Model'!I26 -> 0 | J32: ='④ Cash Flow Model'!I31 -> 50705.609
B33: 1. Go to the Assumptions tab — all the blue cells are things you can change. | E33: 3. This dashboard updates instantly when you change anything. | H33: =6 -> 6 | I33: ='④ Cash Flow Model'!J26 -> 0 | J33: ='④ Cash Flow Model'!J31 -> 56512.759
B34: 2. Key choices: Public vs Private school, which school, university type. | E34: 4. For deeper analysis, see the ③ Analysis tab (IRR, sensitivity, break-even) and ④ Cash Flow Model (year-by-year detail). | H34: =7 -> 7 | I34: ='④ Cash Flow Model'!K26 -> 0 | J34: ='④ Cash Flow Model'!K31 -> 58760.992
B35: Use the dropdown menus — just click the cells and pick from the list. | E35: They have more detail: year-by-year costs, sensitivity tables, break-even analysis. | H35: =8 -> 8 | I35: ='④ Cash Flow Model'!L26 -> 0 | J35: ='④ Cash Flow Model'!L31 -> 61106.325
H36: =9 -> 9 | I36: ='④ Cash Flow Model'!M26 -> 0 | J36: ='④ Cash Flow Model'!M31 -> 60813.252
H37: =10 -> 10 | I37: ='④ Cash Flow Model'!N26 -> 0 | J37: ='④ Cash Flow Model'!N31 -> 71751.03
H38: =11 -> 11 | I38: ='④ Cash Flow Model'!O26 -> 0 | J38: ='④ Cash Flow Model'!O31 -> 69933.972
H39: =12 -> 12 | I39: ='④ Cash Flow Model'!P26 -> 0 | J39: ='④ Cash Flow Model'!P31 -> 80351.864
H40: =13 -> 13 | I40: ='④ Cash Flow Model'!Q26 -> 0 | J40: ='④ Cash Flow Model'!Q31 -> 61004.764
H41: =14 -> 14 | I41: ='④ Cash Flow Model'!R26 -> 0 | J41: ='④ Cash Flow Model'!R31 -> 54433.723
H42: =15 -> 15 | I42: ='④ Cash Flow Model'!S26 -> 0 | J42: ='④ Cash Flow Model'!S31 -> 58383.519
H43: =16 -> 16 | I43: ='④ Cash Flow Model'!T26 -> 0 | J43: ='④ Cash Flow Model'!T31 -> 64385.029
H44: =17 -> 17 | I44: ='④ Cash Flow Model'!U26 -> 0 | J44: ='④ Cash Flow Model'!U31 -> 60639.132
H45: =18 -> 18 | I45: ='④ Cash Flow Model'!V26 -> 0 | J45: ='④ Cash Flow Model'!V31 -> 109190.23
H46: =19 -> 19 | I46: ='④ Cash Flow Model'!W26 -> 0 | J46: ='④ Cash Flow Model'!W31 -> 69639.914
H47: =20 -> 20 | I47: ='④ Cash Flow Model'!X26 -> 0 | J47: ='④ Cash Flow Model'!X31 -> 68790.798
H48: =21 -> 21 | I48: ='④ Cash Flow Model'!Y26 -> 0 | J48: ='④ Cash Flow Model'!Y31 -> 46339.232
H51: Life Stage | I51: Total Cost ($)
H52: Baby & Toddler (0–4) | I52: ='② Dashboard'!F16 -> 130320.73
H53: Primary School (5–11) | I53: ='② Dashboard'!F17 -> 429583.94
H54: Secondary School (12–17) | I54: ='② Dashboard'!F18 -> 379198.03
H55: University (18–20) | I55: ='② Dashboard'!F19 -> 247620.94
H56: Post-Uni (21) | I56: ='② Dashboard'!F20 -> 46339.232
H59: Category | I59: 21-Year Total ($)
H60: Living Costs | I60: ='③ Analysis'!B39 -> 348455.46
H61: Extra-Curriculars | I61: ='③ Analysis'!B27 -> 207947.54
H62: Health Insurance | I62: ='③ Analysis'!B29 -> 195265.31
H63: Before/After Care | I63: ='③ Analysis'!B23 -> 146248.22
H64: University Fees | I64: ='③ Analysis'!B35 -> 60854.261
H65: Car Costs | I65: ='③ Analysis'!B34 -> 0
H66: Life Insurance | I66: ='③ Analysis'!B38 -> 45805.17
H67: School Fees | I67: ='③ Analysis'!B24 -> 14967.954
H68: Uniforms | I68: ='③ Analysis'!B25 -> 27157.949
H69: Camps & Excursions | I69: ='③ Analysis'!B26 -> 18105.3
H70: Technology | I70: ='③ Analysis'!B28 -> 17964.719
H71: Allied Health | I71: ='③ Analysis'!B32 -> 2407.0597
H72: Contingency Buffer | I72: ='③ Analysis'!B40 -> 58717.28

Sheet ③ Analysis
A1: IRR & DASHBOARD
A2: All outputs are formula-driven | ← Change inputs on tab ① Assumptions | View summary on tab ② Dashboard
A4: KEY METRICS
A5: Total 21-Year Costs | B5: =SUM('④ Cash Flow Model'!D31:Y31) -> 1233062.9 | E5: The rate of return needed to fully fund the plan (Fund Balance = 0 at Year 21)
A6: Total Contributions + Govt Benefits (Lump Sum + Regular + Benefits) | B6: =SUM('④ Cash Flow Model'!D8:Y8)+SUM('④ Cash Flow Model'!D7:Y7) -> 734639.45
A7: Total Government Benefits | B7: =SUM('④ Cash Flow Model'!D7:Y7) -> 296692.63 | E7: Year | F7: Net Cash Flow (excl. returns) | G7: Description
A8: Total Investment Returns | B8: =SUM('④ Cash Flow Model'!D9:Y9) -> -162080.93 | E8: 0 | F8: ='④ Cash Flow Model'!D8+'④ Cash Flow Model'!D7-'④ Cash Flow Model'!D31 -> 52369 | G8: Initial investment + Year 0 net
A9: Final Fund Balance (Year 21) | B9: ='④ Cash Flow Model'!Y35 -> -660504.36 | E9: 1 | F9: ='④ Cash Flow Model'!E8+'④ Cash Flow Model'!E7-'④ Cash Flow Model'!E31 -> -743.99434 | G9: Year 1 net (excl. returns)
A10: Total Costs in Today's Dollars (PV) | B10: {=SUMPRODUCT('④ Cash Flow Model'!D31:Y31/(1+'① Assumptions'!B7)^'④ Cash Flow Model'!D3:Y3)} -> 875013.23 | E10: 2 | F10: ='④ Cash Flow Model'!F8+'④ Cash Flow Model'!F7-'④ Cash Flow Model'!F31 -> -916.51546
A11: Effective Net Return (after tax) | B11: ='① Assumptions'!B97 -> 0.0405 | E11: 3 | F11: ='④ Cash Flow Model'!G8+'④ Cash Flow Model'!G7-'④ Cash Flow Model'!G31 -> -4775.719
E12: 2 | F12: ='④ Cash Flow Model'!H8+'④ Cash Flow Model'!H7-'④ Cash Flow Model'!H31 -> -1544.3473 | G12: Year 4 net (excl. returns)
A13: Initial Lump Sum | B13: ='① Assumptions'!B90 -> 50000 | E13: 3 | F13: ='④ Cash Flow Model'!I8+'④ Cash Flow Model'!I7-'④ Cash Flow Model'!I31 -> -23273.586 | G13: Year 5 net (excl. returns)
A14: Annual Contribution (Year 0) | B14: ='① Assumptions'!B93 -> 12000 | E14: 4 | F14: ='④ Cash Flow Model'!J8+'④ Cash Flow Model'!J7-'④ Cash Flow Model'!J31 -> -28186.515 | G14: Year 6 net (excl. returns)
A15: Assumed Rate of Return | B15: ='① Assumptions'!B95 -> 0.06 | E15: 5 | F15: ='④ Cash Flow Model'!K8+'④ Cash Flow Model'!K7-'④ Cash Flow Model'!K31 -> -29511.205 | G15: Year 7 net (excl. returns)
A16: General Inflation (CPI) | B16: ='① Assumptions'!B7 -> 0.03 | E16: 6 | F16: ='④ Cash Flow Model'!L8+'④ Cash Flow Model'!L7-'④ Cash Flow Model'!L31 -> -30902.708 | G16: Year 8 net (excl. returns)
A17: Education Inflation | B17: ='① Assumptions'!B8 -> 0.05 | E17: 7 | F17: ='④ Cash Flow Model'!M8+'④ Cash Flow Model'!M7-'④ Cash Flow Model'!M31 -> -29624.517 | G17: Year 9 net (excl. returns)
A18: ="⚡ KEY INSIGHT: With current assumptions ("&'① Assumptions'!B13&" private from Grade "&TEXT('① Assumptions'!B12,"0")&", $"&TEXT('① Assumptions'!B90/1000,"0")&"k lump + $"&TEXT('① Assumptions'!B93/1000,"0")&"k/yr contributions, "&TEXT('① Assumptions'!B95,"0%")&" gross / "&TEXT('① Assumptions'!B97,"0.0%")&" net return)," -> ⚡ KEY INSIGHT: With current assumptions (Haileybury private from Grade 5, $50k lump + $12k/yr contributions, 6% gross / 4.1% net return), | E18: 8 | F18: ='④ Cash Flow Model'!N8+'④ Cash Flow Model'!N7-'④ Cash Flow Model'!N31 -> -39544.859 | G18: Year 10 net (excl. returns)
A19: =" the plan has a $"&TEXT(ABS('④ Cash Flow Model'!Y35)/1000000,"0.0")&"M "&IF('④ Cash Flow Model'!Y35<0,"shortfall","surplus")&". Try adjusting school type, entry grade, or contributions." -> the plan has a $0.7M shortfall. Try adjusting school type, entry grade, or contributions. | E19: 9 | F19: ='④ Cash Flow Model'!O8+'④ Cash Flow Model'!O7-'④ Cash Flow Model'!O31 -> -36676.981 | G19: Year 11 net (excl. returns)
A20: COST BREAKDOWN BY CATEGORY | F20: ='④ Cash Flow Model'!P8+'④ Cash Flow Model'!P7-'④ Cash Flow Model'!P31 -> -46009.565 | G20: Year 12 net (excl. returns)
A21: Category | B21: 21-Year Total | C21: % of Total | E21: 11 | F21: ='④ Cash Flow Model'!Q8+'④ Cash Flow Model'!Q7-'④ Cash Flow Model'!Q31 -> -23655.934 | G21: Year 13 net (excl. returns)
A22: Childcare | B22: =SUM('④ Cash Flow Model'!D12:Y12) -> 12734.631 | C22: =IF(B$41=0,0,B22/B$41) -> 0.010327641 | E22: 12 | F22: ='④ Cash Flow Model'!R8+'④ Cash Flow Model'!R7-'④ Cash Flow Model'!R31 -> -15870.591 | G22: Year 14 net (excl. returns)
A23: Before/After School Care | B23: =SUM('④ Cash Flow Model'!D13:Y13) -> 146248.22 | C23: =IF(B$41=0,0,B23/B$41) -> 0.11860565 | E23: 13 | F23: ='④ Cash Flow Model'!S8+'④ Cash Flow Model'!S7-'④ Cash Flow Model'!S31 -> -18566.372 | G23: Year 15 net (excl. returns)
A24: School Fees | B24: =SUM('④ Cash Flow Model'!D14:Y14) -> 14967.954 | C24: =IF(B$41=0,0,B24/B$41) -> 0.012138841 | E24: 14 | F24: ='④ Cash Flow Model'!T8+'④ Cash Flow Model'!T7-'④ Cash Flow Model'!T31 -> -23272.846 | G24: Year 16 net (excl. returns)
A25: Uniforms | B25: =SUM('④ Cash Flow Model'!D15:Y15) -> 27157.949 | C25: =IF(B$41=0,0,B25/B$41) -> 0.022024789 | E25: 15 | F25: ='④ Cash Flow Model'!U8+'④ Cash Flow Model'!U7-'④ Cash Flow Model'!U31 -> -25710.001 | G25: Year 17 net (excl. returns)
A26: Camps & Excursions | B26: =SUM('④ Cash Flow Model'!D16:Y16) -> 18105.3 | C26: =IF(B$41=0,0,B26/B$41) -> 0.014683192 | E26: 16 | F26: ='④ Cash Flow Model'!V8+'④ Cash Flow Model'!V7-'④ Cash Flow Model'!V31 -> -73105.544 | G26: Year 18 net (excl. returns)
A27: Extra-Curriculars | B27: =SUM('④ Cash Flow Model'!D17:Y17) -> 207947.54 | C27: =IF(B$41=0,0,B27/B$41) -> 0.16864309 | E27: 17 | F27: ='④ Cash Flow Model'!W8+'④ Cash Flow Model'!W7-'④ Cash Flow Model'!W31 -> -32361.238 | G27: Year 19 net (excl. returns)
A28: Technology | B28: =SUM('④ Cash Flow Model'!D18:Y18) -> 17964.719 | C28: =IF(B$41=0,0,B28/B$41) -> 0.014569183 | E28: 18 | F28: ='④ Cash Flow Model'!X8+'④ Cash Flow Model'!X7-'④ Cash Flow Model'!X31 -> -44913.332 | G28: Year 20 net (excl. returns)
A29: Health Insurance | B29: =SUM('④ Cash Flow Model'!D19:Y19) -> 195265.31 | C29: =IF(B$41=0,0,B29/B$41) -> 0.15835795 | E29: 19 | F29: ='④ Cash Flow Model'!Y8+'④ Cash Flow Model'!Y7-'④ Cash Flow Model'!Y31 -> -21626.054 | G29: Year 21 net (excl. returns)
A30: Orthodontics | B30: =SUM('④ Cash Flow Model'!D20:Y20) -> 10130.031 | C30: =IF(B$41=0,0,B30/B$41) -> 0.0082153403 | E30: 20
A31: Allied Health | B31: =SUM('④ Cash Flow Model'!D21:Y21) -> 14136.412 | C31: =IF(B$41=0,0,B31/B$41) -> 0.01146447 | E31: 21
A32: Driving Lessons | B32: =SUM('④ Cash Flow Model'!D22:Y22) -> 2407.0597 | C32: =IF(B$41=0,0,B32/B$41) -> 0.0019520981
A33: Car Costs | B33: =SUM('④ Cash Flow Model'!D23:Y23) -> 46903.531 | C33: =IF(B$41=0,0,B33/B$41) -> 0.038038231 | E33: REQUIRED RATE OF RETURN (IRR) | F33: =IFERROR(IRR(F8:F29),"N/A — Costs exceed all funding") -> 0.24771804
A34: Gap Year | B34: =SUM('④ Cash Flow Model'!D24:Y24) -> 0 | C34: =IF(B$41=0,0,B34/B$41) -> 0 | E34: Interpretation: | F34: This is the annual investment return needed to make Fund Balance = $0 at Year 21
A35: University Fees | B35: =SUM('④ Cash Flow Model'!D25:Y25) -> 60854.261 | C35: =IF(B$41=0,0,B35/B$41) -> 0.049352115
A36: University Living Costs | B36: =SUM('④ Cash Flow Model'!D26:Y26) -> 0 | C36: =IF(B$41=0,0,B36/B$41) -> 0
A37: Textbooks & Materials | B37: =SUM('④ Cash Flow Model'!D27:Y27) -> 5262.0503 | C37: =IF(B$41=0,0,B37/B$41) -> 0.0042674631
A38: Life Insurance | B38: =SUM('④ Cash Flow Model'!D28:Y28) -> 45805.17 | C38: =IF(B$41=0,0,B38/B$41) -> 0.037147473
A39: Living Costs | B39: =SUM('④ Cash Flow Model'!D29:Y29) -> 348455.46 | C39: =IF(B$41=0,0,B39/B$41) -> 0.28259343
A40: Contingency Buffer | B40: =SUM('④ Cash Flow Model'!D30:Y30) -> 58717.28 | C40: =IF(B$41=0,0,B40/B$41) -> 0.047619048
A41: TOTAL COSTS | B41: =SUM(B22:B40) -> 1233062.9 | C41: =SUM(C22:C40) -> 1
A44: SENSITIVITY ANALYSIS
A45: Final Fund Balance at Year 21 — varying Annual Contribution vs. Rate of Return
A47: Annual Contribution \ Rate of Return → | B47: 0.02 | C47: 0.04 | D47: 0.06 | E47: 0.08 | F47: 0.1 | G47: 0.12 | H47: 0.14
A48: 3000 | B48: {='① Assumptions'!$B$90*(1+0.02)^21+SUMPRODUCT((3000*(1+'① Assumptions'!$B$94)^'④ Cash Flow Model'!$D$3:$Y$3+'④ Cash Flow Model'!D7:Y7-'④ Cash Flow Model'!D31:Y31)*(1+0.02)^(21-'④ Cash Flow Model'!$D$3:$Y$3))} -> -917671.15 | C48: {='① Assumptions'!$B$90*(1+0.04)^21+SUMPRODUCT((3000*(1+'① Assumptions'!$B$94)^'④ Cash Flow Model'!$D$3:$Y$3+'④ Cash Flow Model'!D7:Y7-'④ Cash Flow Model'!D31:Y31)*(1+0.04)^(21-'④ Cash Flow Model'!$D$3:$Y$3))} -> -1071752.3 | D48: {='① Assumptions'!$B$90*(1+0.06)^21+SUMPRODUCT((3000*(1+'① Assumptions'!$B$94)^'④ Cash Flow Model'!$D$3:$Y$3+'④ Cash Flow Model'!D7:Y7-'④ Cash Flow Model'!D31:Y31)*(1+0.06)^(21-'④ Cash Flow Model'!$D$3:$Y$3))} -> -1256421.1 | E48: {='① Assumptions'!$B$90*(1+0.08)^21+SUMPRODUCT((3000*(1+'① Assumptions'!$B$94)^'④ Cash Flow Model'!$D$3:$Y$3+'④ Cash Flow Model'!D7:Y7-'④ Cash Flow Model'!D31:Y31)*(1+0.08)^(21-'④ Cash Flow Model'!$D$3:$Y$3))} -> -1477031.9 | F48: {='① Assumptions'!$B$90*(1+0.1)^21+SUMPRODUCT((3000*(1+'① Assumptions'!$B$94)^'④ Cash Flow Model'!$D$3:$Y$3+'④ Cash Flow Model'!D7:Y7-'④ Cash Flow Model'!D31:Y31)*(1+0.1)^(21-'④ Cash Flow Model'!$D$3:$Y$3))} -> -1739405.9 | G48: {='① Assumptions'!$B$90*(1+0.12)^21+SUMPRODUCT((3000*(1+'① Assumptions'!$B$94)^'④ Cash Flow Model'!$D$3:$Y$3+'④ Cash Flow Model'!D7:Y7-'④ Cash Flow Model'!D31:Y31)*(1+0.12)^(21-'④ Cash Flow Model'!$D$3:$Y$3))} -> -2049637.7 | H48: {='① Assumptions'!$B$90*(1+0.14)^21+SUMPRODUCT((3000*(1+'① Assumptions'!$B$94)^'④ Cash Flow Model'!$D$3:$Y$3+'④ Cash Flow Model'!D7:Y7-'④ Cash Flow Model'!D31:Y31)*(1+0.14)^(21-'④ Cash Flow Model'!$D$3:$Y$3))} -> -2413757.3
A49: 5000 | B49: {='① Assumptions'!$B$90*(1+0.02)^21+SUMPRODUCT((5000*(1+'① Assumptions'!$B$94)^'④ Cash Flow Model'!$D$3:$Y$3+'④ Cash Flow Model'!D7:Y7-'④ Cash Flow Model'!D31:Y31)*(1+0.02)^(21-'④ Cash Flow Model'!$D$3:$Y$3))} -> -839600.23 | C49: {='① Assumptions'!$B$90*(1+0.04)^21+SUMPRODUCT((5000*(1+'① Assumptions'!$B$94)^'④ Cash Flow Model'!$D$3:$Y$3+'④ Cash Flow Model'!D7:Y7-'④ Cash Flow Model'!D31:Y31)*(1+0.04)^(21-'④ Cash Flow Model'!$D$3:$Y$3))} -> -976389.45 | D49: {='① Assumptions'!$B$90*(1+0.06)^21+SUMPRODUCT((5000*(1+'① Assumptions'!$B$94)^'④ Cash Flow Model'!$D$3:$Y$3+'④ Cash Flow Model'!D7:Y7-'④ Cash Flow Model'!D31:Y31)*(1+0.06)^(21-'④ Cash Flow Model'!$D$3:$Y$3))} -> -1138659 | E49: {='① Assumptions'!$B$90*(1+0.08)^21+SUMPRODUCT((5000*(1+'① Assumptions'!$B$94)^'④ Cash Flow Model'!$D$3:$Y$3+'④ Cash Flow Model'!D7:Y7-'④ Cash Flow Model'!D31:Y31)*(1+0.08)^(21-'④ Cash Flow Model'!$D$3:$Y$3))} -> -1330141.7 | F49: {='① Assumptions'!$B$90*(1+0.1)^21+SUMPRODUCT((5000*(1+'① Assumptions'!$B$94)^'④ Cash Flow Model'!$D$3:$Y$3+'④ Cash Flow Model'!D7:Y7-'④ Cash Flow Model'!D31:Y31)*(1+0.1)^(21-'④ Cash Flow Model'!$D$3:$Y$3))} -> -1554520.9 | G49: {='① Assumptions'!$B$90*(1+0.12)^21+SUMPRODUCT((5000*(1+'① Assumptions'!$B$94)^'④ Cash Flow Model'!$D$3:$Y$3+'④ Cash Flow Model'!D7:Y7-'④ Cash Flow Model'!D31:Y31)*(1+0.12)^(21-'④ Cash Flow Model'!$D$3:$Y$3))} -> -1815077.7 | H49: {='① Assumptions'!$B$90*(1+0.14)^21+SUMPRODUCT((5000*(1+'① Assumptions'!$B$94)^'④ Cash Flow Model'!$D$3:$Y$3+'④ Cash Flow Model'!D7:Y7-'④ Cash Flow Model'!D31:Y31)*(1+0.14)^(21-'④ Cash Flow Model'!$D$3:$Y$3))} -> -2114147.2
A50: 6000 | B50: {='① Assumptions'!$B$90*(1+0.02)^21+SUMPRODUCT((6000*(1+'① Assumptions'!$B$94)^'④ Cash Flow Model'!$D$3:$Y$3+'④ Cash Flow Model'!D7:Y7-'④ Cash Flow Model'!D31:Y31)*(1+0.02)^(21-'④ Cash Flow Model'!$D$3:$Y$3))} -> -800564.77 | C50: {='① Assumptions'!$B$90*(1+0.04)^21+SUMPRODUCT((6000*(1+'① Assumptions'!$B$94)^'④ Cash Flow Model'!$D$3:$Y$3+'④ Cash Flow Model'!D7:Y7-'④ Cash Flow Model'!D31:Y31)*(1+0.04)^(21-'④ Cash Flow Model'!$D$3:$Y$3))} -> -928708.01 | D50: {='① Assumptions'!$B$90*(1+0.06)^21+SUMPRODUCT((6000*(1+'① Assumptions'!$B$94)^'④ Cash Flow Model'!$D$3:$Y$3+'④ Cash Flow Model'!D7:Y7-'④ Cash Flow Model'!D31:Y31)*(1+0.06)^(21-'④ Cash Flow Model'!$D$3:$Y$3))} -> -1079778 | E50: {='① Assumptions'!$B$90*(1+0.08)^21+SUMPRODUCT((6000*(1+'① Assumptions'!$B$94)^'④ Cash Flow Model'!$D$3:$Y$3+'④ Cash Flow Model'!D7:Y7-'④ Cash Flow Model'!D31:Y31)*(1+0.08)^(21-'④ Cash Flow Model'!$D$3:$Y$3))} -> -1256696.6 | F50: {='① Assumptions'!$B$90*(1+0.1)^21+SUMPRODUCT((6000*(1+'① Assumptions'!$B$94)^'④ Cash Flow Model'!$D$3:$Y$3+'④ Cash Flow Model'!D7:Y7-'④ Cash Flow Model'!D31:Y31)*(1+0.1)^(21-'④ Cash Flow Model'!$D$3:$Y$3))} -> -1462078.4 | G50: {='① Assumptions'!$B$90*(1+0.12)^21+SUMPRODUCT((6000*(1+'① Assumptions'!$B$94)^'④ Cash Flow Model'!$D$3:$Y$3+'④ Cash Flow Model'!D7:Y7-'④ Cash Flow Model'!D31:Y31)*(1+0.12)^(21-'④ Cash Flow Model'!$D$3:$Y$3))} -> -1697797.7 | H50: {='① Assumptions'!$B$90*(1+0.14)^21+SUMPRODUCT((6000*(1+'① Assumptions'!$B$94)^'④ Cash Flow Model'!$D$3:$Y$3+'④ Cash Flow Model'!D7:Y7-'④ Cash Flow Model'!D31:Y31)*(1+0.14)^(21-'④ Cash Flow Model'!$D$3:$Y$3))} -> -1964342.2
A51: 8000 | B51: {='① Assumptions'!$B$90*(1+0.02)^21+SUMPRODUCT((8000*(1+'① Assumptions'!$B$94)^'④ Cash Flow Model'!$D$3:$Y$3+'④ Cash Flow Model'!D7:Y7-'④ Cash Flow Model'!D31:Y31)*(1+0.02)^(21-'④ Cash Flow Model'!$D$3:$Y$3))} -> -722493.85 | C51: {='① Assumptions'!$B$90*(1+0.04)^21+SUMPRODUCT((8000*(1+'① Assumptions'!$B$94)^'④ Cash Flow Model'!$D$3:$Y$3+'④ Cash Flow Model'!D7:Y7-'④ Cash Flow Model'!D31:Y31)*(1+0.04)^(21-'④ Cash Flow Model'!$D$3:$Y$3))} -> -833345.12 | D51: {='① Assumptions'!$B$90*(1+0.06)^21+SUMPRODUCT((8000*(1+'① Assumptions'!$B$94)^'④ Cash Flow Model'!$D$3:$Y$3+'④ Cash Flow Model'!D7:Y7-'④ Cash Flow Model'!D31:Y31)*(1+0.06)^(21-'④ Cash Flow Model'!$D$3:$Y$3))} -> -962015.91 | E51: {='① Assumptions'!$B$90*(1+0.08)^21+SUMPRODUCT((8000*(1+'① Assumptions'!$B$94)^'④ Cash Flow Model'!$D$3:$Y$3+'④ Cash Flow Model'!D7:Y7-'④ Cash Flow Model'!D31:Y31)*(1+0.08)^(21-'④ Cash Flow Model'!$D$3:$Y$3))} -> -1109806.5 | F51: {='① Assumptions'!$B$90*(1+0.1)^21+SUMPRODUCT((8000*(1+'① Assumptions'!$B$94)^'④ Cash Flow Model'!$D$3:$Y$3+'④ Cash Flow Model'!D7:Y7-'④ Cash Flow Model'!D31:Y31)*(1+0.1)^(21-'④ Cash Flow Model'!$D$3:$Y$3))} -> -1277193.3 | G51: {='① Assumptions'!$B$90*(1+0.12)^21+SUMPRODUCT((8000*(1+'① Assumptions'!$B$94)^'④ Cash Flow Model'!$D$3:$Y$3+'④ Cash Flow Model'!D7:Y7-'④ Cash Flow Model'!D31:Y31)*(1+0.12)^(21-'④ Cash Flow Model'!$D$3:$Y$3))} -> -1463237.8 | H51: {='① Assumptions'!$B$90*(1+0.14)^21+SUMPRODUCT((8000*(1+'① Assumptions'!$B$94)^'④ Cash Flow Model'!$D$3:$Y$3+'④ Cash Flow Model'!D7:Y7-'④ Cash Flow Model'!D31:Y31)*(1+0.14)^(21-'④ Cash Flow Model'!$D$3:$Y$3))} -> -1664732.1
A52: 10000 | B52: {='① Assumptions'!$B$90*(1+0.02)^21+SUMPRODUCT((10000*(1+'① Assumptions'!$B$94)^'④ Cash Flow Model'!$D$3:$Y$3+'④ Cash Flow Model'!D7:Y7-'④ Cash Flow Model'!D31:Y31)*(1+0.02)^(21-'④ Cash Flow Model'!$D$3:$Y$3))} -> -644422.93 | C52: {='① Assumptions'!$B$90*(1+0.04)^21+SUMPRODUCT((10000*(1+'① Assumptions'!$B$94)^'④ Cash Flow Model'!$D$3:$Y$3+'④ Cash Flow Model'!D7:Y7-'④ Cash Flow Model'!D31:Y31)*(1+0.04)^(21-'④ Cash Flow Model'!$D$3:$Y$3))} -> -737982.24 | D52: {='① Assumptions'!$B$90*(1+0.06)^21+SUMPRODUCT((10000*(1+'① Assumptions'!$B$94)^'④ Cash Flow Model'!$D$3:$Y$3+'④ Cash Flow Model'!D7:Y7-'④ Cash Flow Model'!D31:Y31)*(1+0.06)^(21-'④ Cash Flow Model'!$D$3:$Y$3))} -> -844253.84 | E52: {='① Assumptions'!$B$90*(1+0.08)^21+SUMPRODUCT((10000*(1+'① Assumptions'!$B$94)^'④ Cash Flow Model'!$D$3:$Y$3+'④ Cash Flow Model'!D7:Y7-'④ Cash Flow Model'!D31:Y31)*(1+0.08)^(21-'④ Cash Flow Model'!$D$3:$Y$3))} -> -962916.3 | F52: {='① Assumptions'!$B$90*(1+0.1)^21+SUMPRODUCT((10000*(1+'① Assumptions'!$B$94)^'④ Cash Flow Model'!$D$3:$Y$3+'④ Cash Flow Model'!D7:Y7-'④ Cash Flow Model'!D31:Y31)*(1+0.1)^(21-'④ Cash Flow Model'!$D$3:$Y$3))} -> -1092308.3 | G52: {='① Assumptions'!$B$90*(1+0.12)^21+SUMPRODUCT((10000*(1+'① Assumptions'!$B$94)^'④ Cash Flow Model'!$D$3:$Y$3+'④ Cash Flow Model'!D7:Y7-'④ Cash Flow Model'!D31:Y31)*(1+0.12)^(21-'④ Cash Flow Model'!$D$3:$Y$3))} -> -1228677.8 | H52: {='① Assumptions'!$B$90*(1+0.14)^21+SUMPRODUCT((10000*(1+'① Assumptions'!$B$94)^'④ Cash Flow Model'!$D$3:$Y$3+'④ Cash Flow Model'!D7:Y7-'④ Cash Flow Model'!D31:Y31)*(1+0.14)^(21-'④ Cash Flow Model'!$D$3:$Y$3))} -> -1365122.1
A53: 12000 | B53: {='① Assumptions'!$B$90*(1+0.02)^21+SUMPRODUCT((12000*(1+'① Assumptions'!$B$94)^'④ Cash Flow Model'!$D$3:$Y$3+'④ Cash Flow Model'!D7:Y7-'④ Cash Flow Model'!D31:Y31)*(1+0.02)^(21-'④ Cash Flow Model'!$D$3:$Y$3))} -> -566352.01 | C53: {='① Assumptions'!$B$90*(1+0.04)^21+SUMPRODUCT((12000*(1+'① Assumptions'!$B$94)^'④ Cash Flow Model'!$D$3:$Y$3+'④ Cash Flow Model'!D7:Y7-'④ Cash Flow Model'!D31:Y31)*(1+0.04)^(21-'④ Cash Flow Model'!$D$3:$Y$3))} -> -642619.35 | D53: {='① Assumptions'!$B$90*(1+0.06)^21+SUMPRODUCT((12000*(1+'① Assumptions'!$B$94)^'④ Cash Flow Model'!$D$3:$Y$3+'④ Cash Flow Model'!D7:Y7-'④ Cash Flow Model'!D31:Y31)*(1+0.06)^(21-'④ Cash Flow Model'!$D$3:$Y$3))} -> -726491.77 | E53: {='① Assumptions'!$B$90*(1+0.08)^21+SUMPRODUCT((12000*(1+'① Assumptions'!$B$94)^'④ Cash Flow Model'!$D$3:$Y$3+'④ Cash Flow Model'!D7:Y7-'④ Cash Flow Model'!D31:Y31)*(1+0.08)^(21-'④ Cash Flow Model'!$D$3:$Y$3))} -> -816026.13 | F53: {='① Assumptions'!$B$90*(1+0.1)^21+SUMPRODUCT((12000*(1+'① Assumptions'!$B$94)^'④ Cash Flow Model'!$D$3:$Y$3+'④ Cash Flow Model'!D7:Y7-'④ Cash Flow Model'!D31:Y31)*(1+0.1)^(21-'④ Cash Flow Model'!$D$3:$Y$3))} -> -907423.29 | G53: {='① Assumptions'!$B$90*(1+0.12)^21+SUMPRODUCT((12000*(1+'① Assumptions'!$B$94)^'④ Cash Flow Model'!$D$3:$Y$3+'④ Cash Flow Model'!D7:Y7-'④ Cash Flow Model'!D31:Y31)*(1+0.12)^(21-'④ Cash Flow Model'!$D$3:$Y$3))} -> -994117.84 | H53: {='① Assumptions'!$B$90*(1+0.14)^21+SUMPRODUCT((12000*(1+'① Assumptions'!$B$94)^'④ Cash Flow Model'!$D$3:$Y$3+'④ Cash Flow Model'!D7:Y7-'④ Cash Flow Model'!D31:Y31)*(1+0.14)^(21-'④ Cash Flow Model'!$D$3:$Y$3))} -> -1065512
A54: 15000 | B54: {='① Assumptions'!$B$90*(1+0.02)^21+SUMPRODUCT((15000*(1+'① Assumptions'!$B$94)^'④ Cash Flow Model'!$D$3:$Y$3+'④ Cash Flow Model'!D7:Y7-'④ Cash Flow Model'!D31:Y31)*(1+0.02)^(21-'④ Cash Flow Model'!$D$3:$Y$3))} -> -449245.63 | C54: {='① Assumptions'!$B$90*(1+0.04)^21+SUMPRODUCT((15000*(1+'① Assumptions'!$B$94)^'④ Cash Flow Model'!$D$3:$Y$3+'④ Cash Flow Model'!D7:Y7-'④ Cash Flow Model'!D31:Y31)*(1+0.04)^(21-'④ Cash Flow Model'!$D$3:$Y$3))} -> -499575.02 | D54: {='① Assumptions'!$B$90*(1+0.06)^21+SUMPRODUCT((15000*(1+'① Assumptions'!$B$94)^'④ Cash Flow Model'!$D$3:$Y$3+'④ Cash Flow Model'!D7:Y7-'④ Cash Flow Model'!D31:Y31)*(1+0.06)^(21-'④ Cash Flow Model'!$D$3:$Y$3))} -> -549848.67 | E54: {='① Assumptions'!$B$90*(1+0.08)^21+SUMPRODUCT((15000*(1+'① Assumptions'!$B$94)^'④ Cash Flow Model'!$D$3:$Y$3+'④ Cash Flow Model'!D7:Y7-'④ Cash Flow Model'!D31:Y31)*(1+0.08)^(21-'④ Cash Flow Model'!$D$3:$Y$3))} -> -595690.87 | F54: {='① Assumptions'!$B$90*(1+0.1)^21+SUMPRODUCT((15000*(1+'① Assumptions'!$B$94)^'④ Cash Flow Model'!$D$3:$Y$3+'④ Cash Flow Model'!D7:Y7-'④ Cash Flow Model'!D31:Y31)*(1+0.1)^(21-'④ Cash Flow Model'!$D$3:$Y$3))} -> -630095.75 | G54: {='① Assumptions'!$B$90*(1+0.12)^21+SUMPRODUCT((15000*(1+'① Assumptions'!$B$94)^'④ Cash Flow Model'!$D$3:$Y$3+'④ Cash Flow Model'!D7:Y7-'④ Cash Flow Model'!D31:Y31)*(1+0.12)^(21-'④ Cash Flow Model'!$D$3:$Y$3))} -> -642277.89 | H54: {='① Assumptions'!$B$90*(1+0.14)^21+SUMPRODUCT((15000*(1+'① Assumptions'!$B$94)^'④ Cash Flow Model'!$D$3:$Y$3+'④ Cash Flow Model'!D7:Y7-'④ Cash Flow Model'!D31:Y31)*(1+0.14)^(21-'④ Cash Flow Model'!$D$3:$Y$3))} -> -616096.93
A56: Yellow cell = base case assumptions
A57: Green = surplus (plan is fully funded), Red = deficit (need more funding)
A58: ⚠️ Note: This table uses a simplified single compound rate for all years. The actual model applies a lower net return (4.05%) when the fund is positive and a higher borrowing rate (4.39%) when negative — so these figures are approximate estimates, not exact model outputs.
A59: SENSITIVITY: Impact of Education Inflation on Total School + University Fees
A61: Education Inflation Rate | B61: Total School Fees | C61: Total Uni Fees | D61: Combined Total | E61: Δ vs Base Case | F61: Fund Balance Impact | G61: Est. Fund Balance
A62: 0.03 | B62: {=SUMPRODUCT('④ Cash Flow Model'!D14:Y14*((1+A62)/(1+'① Assumptions'!$B$8))^'④ Cash Flow Model'!D3:Y3)} -> 11819.372 | C62: {=SUMPRODUCT('④ Cash Flow Model'!D25:Y25*((1+A62)/(1+'① Assumptions'!$B$8))^'④ Cash Flow Model'!D3:Y3)} -> 42206.906 | D62: =B62+C62 -> 54026.277 | E62: =D62-D$64 -> -21795.938 | F62: =-(D62-D$64) -> 21795.938 | G62: ='④ Cash Flow Model'!Y35+F62 -> -638708.42
A63: 0.04 | B63: {=SUMPRODUCT('④ Cash Flow Model'!D14:Y14*((1+A63)/(1+'① Assumptions'!$B$8))^'④ Cash Flow Model'!D3:Y3)} -> 13300.427 | C63: {=SUMPRODUCT('④ Cash Flow Model'!D25:Y25*((1+A63)/(1+'① Assumptions'!$B$8))^'④ Cash Flow Model'!D3:Y3)} -> 50723.11 | D63: =B63+C63 -> 64023.538 | E63: =D63-D$64 -> -11798.678 | F63: =-(D63-D$64) -> 11798.678 | G63: ='④ Cash Flow Model'!Y35+F63 -> -648705.68
A64: 0.05 | B64: {=SUMPRODUCT('④ Cash Flow Model'!D14:Y14*((1+A64)/(1+'① Assumptions'!$B$8))^'④ Cash Flow Model'!D3:Y3)} -> 14967.954 | C64: {=SUMPRODUCT('④ Cash Flow Model'!D25:Y25*((1+A64)/(1+'① Assumptions'!$B$8))^'④ Cash Flow Model'!D3:Y3)} -> 60854.261 | D64: =B64+C64 -> 75822.215 | E64: =D64-D$64 -> 0 | F64: =-(D64-D$64) -> 0 | G64: ='④ Cash Flow Model'!Y35+F64 -> -660504.36
A65: 0.06 | B65: {=SUMPRODUCT('④ Cash Flow Model'!D14:Y14*((1+A65)/(1+'① Assumptions'!$B$8))^'④ Cash Flow Model'!D3:Y3)} -> 16844.993 | C65: {=SUMPRODUCT('④ Cash Flow Model'!D25:Y25*((1+A65)/(1+'① Assumptions'!$B$8))^'④ Cash Flow Model'!D3:Y3)} -> 72887.422 | D65: =B65+C65 -> 89732.415 | E65: =D65-D$64 -> 13910.199 | F65: =-(D65-D$64) -> -13910.199 | G65: ='④ Cash Flow Model'!Y35+F65 -> -674414.56
A66: 0.07 | B66: {=SUMPRODUCT('④ Cash Flow Model'!D14:Y14*((1+A66)/(1+'① Assumptions'!$B$8))^'④ Cash Flow Model'!D3:Y3)} -> 18957.321 | C66: {=SUMPRODUCT('④ Cash Flow Model'!D25:Y25*((1+A66)/(1+'① Assumptions'!$B$8))^'④ Cash Flow Model'!D3:Y3)} -> 87157.343 | D66: =B66+C66 -> 106114.66 | E66: =D66-D$64 -> 30292.449 | F66: =-(D66-D$64) -> -30292.449 | G66: ='④ Cash Flow Model'!Y35+F66 -> -690796.81
A67: 0.08 | B67: {=SUMPRODUCT('④ Cash Flow Model'!D14:Y14*((1+A67)/(1+'① Assumptions'!$B$8))^'④ Cash Flow Model'!D3:Y3)} -> 21333.757 | C67: {=SUMPRODUCT('④ Cash Flow Model'!D25:Y25*((1+A67)/(1+'① Assumptions'!$B$8))^'④ Cash Flow Model'!D3:Y3)} -> 104053.85 | D67: =B67+C67 -> 125387.6 | E67: =D67-D$64 -> 49565.389 | F67: =-(D67-D$64) -> -49565.389 | G67: ='④ Cash Flow Model'!Y35+F67 -> -710069.75
A68: 0.09 | B68: {=SUMPRODUCT('④ Cash Flow Model'!D14:Y14*((1+A68)/(1+'① Assumptions'!$B$8))^'④ Cash Flow Model'!D3:Y3)} -> 24006.499 | C68: {=SUMPRODUCT('④ Cash Flow Model'!D25:Y25*((1+A68)/(1+'① Assumptions'!$B$8))^'④ Cash Flow Model'!D3:Y3)} -> 124030.27 | D68: =B68+C68 -> 148036.77 | E68: =D68-D$64 -> 72214.55 | F68: =-(D68-D$64) -> -72214.55 | G68: ='④ Cash Flow Model'!Y35+F68 -> -732718.91
A73: CHART DATA (for reference)
A74: Year | B74: Fund Balance | C74: Cumulative Costs | D74: Cumulative Contributions
A75: 0 | B75: ='④ Cash Flow Model'!D35 -> 52369 | C75: =SUM('④ Cash Flow Model'!D31:'④ Cash Flow Model'!D31) -> 21000 | D75: =SUM('④ Cash Flow Model'!D8:'④ Cash Flow Model'!D8)+SUM('④ Cash Flow Model'!D7:'④ Cash Flow Model'!D7) -> 73369
A76: 1 | B76: ='④ Cash Flow Model'!E35 -> 53745.95 | C76: =SUM('④ Cash Flow Model'!D31:'④ Cash Flow Model'!E31) -> 45874.064 | D76: =SUM('④ Cash Flow Model'!D8:'④ Cash Flow Model'!E8)+SUM('④ Cash Flow Model'!D7:'④ Cash Flow Model'!E7) -> 97499.07
A77: 2 | B77: ='④ Cash Flow Model'!F35 -> 55006.146 | C77: =SUM('④ Cash Flow Model'!D31:'④ Cash Flow Model'!F31) -> 71706.652 | D77: =SUM('④ Cash Flow Model'!D8:'④ Cash Flow Model'!F8)+SUM('④ Cash Flow Model'!D7:'④ Cash Flow Model'!F7) -> 122415.14
A78: 3 | B78: ='④ Cash Flow Model'!G35 -> 52458.176 | C78: =SUM('④ Cash Flow Model'!D31:'④ Cash Flow Model'!G31) -> 102210.2 | D78: =SUM('④ Cash Flow Model'!D8:'④ Cash Flow Model'!G8)+SUM('④ Cash Flow Model'!D7:'④ Cash Flow Model'!G7) -> 148142.97
A79: 4 | B79: ='④ Cash Flow Model'!H35 -> 53038.384 | C79: =SUM('④ Cash Flow Model'!D31:'④ Cash Flow Model'!H31) -> 130320.73 | D79: =SUM('④ Cash Flow Model'!D8:'④ Cash Flow Model'!H8)+SUM('④ Cash Flow Model'!D7:'④ Cash Flow Model'!H7) -> 174709.16
A80: 5 | B80: ='④ Cash Flow Model'!I35 -> 31912.853 | C80: =SUM('④ Cash Flow Model'!D31:'④ Cash Flow Model'!I31) -> 181026.34 | D80: =SUM('④ Cash Flow Model'!D8:'④ Cash Flow Model'!I8)+SUM('④ Cash Flow Model'!D7:'④ Cash Flow Model'!I7) -> 202141.18
A81: 6 | B81: ='④ Cash Flow Model'!J35 -> 5018.8083 | C81: =SUM('④ Cash Flow Model'!D31:'④ Cash Flow Model'!J31) -> 237539.1 | D81: =SUM('④ Cash Flow Model'!D8:'④ Cash Flow Model'!J8)+SUM('④ Cash Flow Model'!D7:'④ Cash Flow Model'!J7) -> 230467.42
A82: 7 | B82: ='④ Cash Flow Model'!K35 -> -24289.135 | C82: =SUM('④ Cash Flow Model'!D31:'④ Cash Flow Model'!K31) -> 296300.09 | D82: =SUM('④ Cash Flow Model'!D8:'④ Cash Flow Model'!K8)+SUM('④ Cash Flow Model'!D7:'④ Cash Flow Model'!K7) -> 259717.21
A83: 8 | B83: ='④ Cash Flow Model'!L35 -> -56257.529 | C83: =SUM('④ Cash Flow Model'!D31:'④ Cash Flow Model'!L31) -> 357406.42 | D83: =SUM('④ Cash Flow Model'!D8:'④ Cash Flow Model'!L8)+SUM('④ Cash Flow Model'!D7:'④ Cash Flow Model'!L7) -> 289920.83
A84: 9 | B84: ='④ Cash Flow Model'!M35 -> -88350.345 | C84: =SUM('④ Cash Flow Model'!D31:'④ Cash Flow Model'!M31) -> 418219.67 | D84: =SUM('④ Cash Flow Model'!D8:'④ Cash Flow Model'!M8)+SUM('④ Cash Flow Model'!D7:'④ Cash Flow Model'!M7) -> 321109.56
A85: 10 | B85: ='④ Cash Flow Model'!N35 -> -131771.58 | C85: =SUM('④ Cash Flow Model'!D31:'④ Cash Flow Model'!N31) -> 489970.7 | D85: =SUM('④ Cash Flow Model'!D8:'④ Cash Flow Model'!N8)+SUM('④ Cash Flow Model'!D7:'④ Cash Flow Model'!N7) -> 353315.73
A86: 11 | B86: ='④ Cash Flow Model'!O35 -> -174230.03 | C86: =SUM('④ Cash Flow Model'!D31:'④ Cash Flow Model'!O31) -> 559904.67 | D86: =SUM('④ Cash Flow Model'!D8:'④ Cash Flow Model'!O8)+SUM('④ Cash Flow Model'!D7:'④ Cash Flow Model'!O7) -> 386572.72
A87: 12 | B87: ='④ Cash Flow Model'!P35 -> -227883.94 | C87: =SUM('④ Cash Flow Model'!D31:'④ Cash Flow Model'!P31) -> 640256.54 | D87: =SUM('④ Cash Flow Model'!D8:'④ Cash Flow Model'!P8)+SUM('④ Cash Flow Model'!D7:'④ Cash Flow Model'!P7) -> 420915.02
A88: 13 | B88: ='④ Cash Flow Model'!Q35 -> -261538.28 | C88: =SUM('④ Cash Flow Model'!D31:'④ Cash Flow Model'!Q31) -> 701261.3 | D88: =SUM('④ Cash Flow Model'!D8:'④ Cash Flow Model'!Q8)+SUM('④ Cash Flow Model'!D7:'④ Cash Flow Model'!Q7) -> 458263.85
A89: 14 | B89: ='④ Cash Flow Model'!R35 -> -288883.87 | C89: =SUM('④ Cash Flow Model'!D31:'④ Cash Flow Model'!R31) -> 755695.02 | D89: =SUM('④ Cash Flow Model'!D8:'④ Cash Flow Model'!R8)+SUM('④ Cash Flow Model'!D7:'④ Cash Flow Model'!R7) -> 496826.99
A90: 15 | B90: ='④ Cash Flow Model'!S35 -> -320125.02 | C90: =SUM('④ Cash Flow Model'!D31:'④ Cash Flow Model'!S31) -> 814078.54 | D90: =SUM('④ Cash Flow Model'!D8:'④ Cash Flow Model'!S8)+SUM('④ Cash Flow Model'!D7:'④ Cash Flow Model'!S7) -> 536644.13
A91: 16 | B91: ='④ Cash Flow Model'!T35 -> -357443.35 | C91: =SUM('④ Cash Flow Model'!D31:'④ Cash Flow Model'!T31) -> 878463.57 | D91: =SUM('④ Cash Flow Model'!D8:'④ Cash Flow Model'!T8)+SUM('④ Cash Flow Model'!D7:'④ Cash Flow Model'!T7) -> 577756.32
A92: 17 | B92: ='④ Cash Flow Model'!U35 -> -398836.18 | C92: =SUM('④ Cash Flow Model'!D31:'④ Cash Flow Model'!U31) -> 939102.7 | D92: =SUM('④ Cash Flow Model'!D8:'④ Cash Flow Model'!U8)+SUM('④ Cash Flow Model'!D7:'④ Cash Flow Model'!U7) -> 612685.45
A93: 18 | B93: ='④ Cash Flow Model'!V35 -> -489440.66 | C93: =SUM('④ Cash Flow Model'!D31:'④ Cash Flow Model'!V31) -> 1048292.9 | D93: =SUM('④ Cash Flow Model'!D8:'④ Cash Flow Model'!V8)+SUM('④ Cash Flow Model'!D7:'④ Cash Flow Model'!V7) -> 648770.13
A94: 19 | B94: ='④ Cash Flow Model'!W35 -> -543276.11 | C94: =SUM('④ Cash Flow Model'!D31:'④ Cash Flow Model'!W31) -> 1117932.8 | D94: =SUM('④ Cash Flow Model'!D8:'④ Cash Flow Model'!W8)+SUM('④ Cash Flow Model'!D7:'④ Cash Flow Model'!W7) -> 686048.81
A95: 20 | B95: ='④ Cash Flow Model'!X35 -> -612025.68 | C95: =SUM('④ Cash Flow Model'!D31:'④ Cash Flow Model'!X31) -> 1186723.6 | D95: =SUM('④ Cash Flow Model'!D8:'④ Cash Flow Model'!X8)+SUM('④ Cash Flow Model'!D7:'④ Cash Flow Model'!X7) -> 709926.27
A96: 21 | B96: ='④ Cash Flow Model'!Y35 -> -660504.36 | C96: =SUM('④ Cash Flow Model'!D31:'④ Cash Flow Model'!Y31) -> 1233062.9 | D96: =SUM('④ Cash Flow Model'!D8:'④ Cash Flow Model'!Y8)+SUM('④ Cash Flow Model'!D7:'④ Cash Flow Model'!Y7) -> 734639.45
A99: ADDITIONAL ANALYSIS
A101: BREAK-EVEN ANALYSIS
A102: At the assumed rate of return, what annual contribution breaks even?
A104: Total Costs (Future Value at Year 21) | B104: {=SUMPRODUCT('④ Cash Flow Model'!D31:Y31*(1+'① Assumptions'!B97)^(21-'④ Cash Flow Model'!D3:Y3))} -> 1802404.3
A105: Total Benefits + Regular Contributions (Future Value at Year 21) | B105: {=SUMPRODUCT(('④ Cash Flow Model'!D7:Y7)*(1+'① Assumptions'!B97)^(21-'④ Cash Flow Model'!D3:Y3))+SUMPRODUCT(('① Assumptions'!B93*(1+'① Assumptions'!B94)^'④ Cash Flow Model'!D3:Y3)*(1+'① Assumptions'!B97)^(21-'④ Cash Flow Model'!D3:Y3))} -> 1042681.4
A106: Lump Sum (Future Value at Year 21) | B106: ='① Assumptions'!B90*(1+'① Assumptions'!B97)^21 -> 115094.29
A107: Funding Gap | B107: =B104-B105-B106 -> 644628.63
A108: Contribution Growth Factor Sum | B108: {=SUMPRODUCT((1+'① Assumptions'!B94)^'④ Cash Flow Model'!D3:Y3*(1+'① Assumptions'!B97)^(21-'④ Cash Flow Model'!D3:Y3))} -> 47.927383
A109: Required Annual Contribution | B109: =IF(B108=0,0,B107/B108) -> 13450.111
A111: This is the annual starting contribution needed (growing at the contribution growth rate) to fully fund the plan, in addition to the initial lump sum.
A113: OPPORTUNITY COST ANALYSIS
A114: What would your child-related spending be worth if invested at the risk-free rate instead?
A116: Metric | B116: Value | C116: Notes
A117: Risk-Free Rate | B117: ='① Assumptions'!B103 -> 0.0425 | C117: Australian 10yr government bond rate (input on Assumptions tab)
...

Sheet ④ Cash Flow Model
A1: COST OF CHILD — 21-YEAR CASH FLOW PROJECTION
A2: ="All values are formula-driven from ① Assumptions | Total Costs: "&TEXT('④ Cash Flow Model'!Z31,"$#,##0")&" | Total Income: "&TEXT('④ Cash Flow Model'!Z10,"$#,##0")&" | Net Position: "&TEXT('④ Cash Flow Model'!Z33,"$#,##0") -> All values are formula-driven from ① Assumptions | Total Costs: $1,233,063 | Total Income: $572,559 | Net Position: -$660,504
A3: Category | B3: Section | C3: Line Item | D3: 0 | E3: 1 | F3: 2 | G3: 3 | H3: 4 | I3: 5 | J3: 6 | K3: 7 | L3: 8 | M3: 9 | N3: 10 | O3: 11 | P3: 12 | Q3: 13 | R3: 14 | S3: 15 | T3: 16 | U3: 17 | V3: 18 | W3: 19 | X3: 20 | Y3: 21 | Z3: TOTALS
C4: Child Age | D4: 0 | E4: 1 | F4: 2 | G4: 3 | H4: 4 | I4: 5 | J4: 6 | K4: 7 | L4: 8 | M4: 9 | N4: 10 | O4: 11 | P4: 12 | Q4: 13 | R4: 14 | S4: 15 | T4: 16 | U4: 17 | V4: 18 | W4: 19 | X4: 20 | Y4: 21
C5: School Grade | D5: Pre-School | E5: Pre-School | F5: Pre-School | G5: Pre-School | H5: Pre-School | I5: Prep | J5: Grade 1 | K5: Grade 2 | L5: Grade 3 | M5: Grade 4 | N5: Grade 5 | O5: Grade 6 | P5: Year 7 | Q5: Year 8 | R5: Year 9 | S5: Year 10 | T5: Year 11 | U5: Year 12 | V5: Uni Year 1 | W5: Uni Year 2 | X5: Uni Year 3 | Y5: Post-Uni
A6: INCOME
A7: 🏛️ Govt Benefits | B7: Income | C7: Govt Benefits | D7: =IF('① Assumptions'!$B$107="Yes",(IF(D$4<=12,IF(D$4<='① Assumptions'!$B$113,'① Assumptions'!$B$109,0),IF(D$4<='① Assumptions'!$B$113,'① Assumptions'!$B$110,0))+IF(D$4<='① Assumptions'!$B$113,'① Assumptions'!$B$112,0)+IF(D$4<='① Assumptions'!$B$114,'① Assumptions'!$B$111,0))*(1+'① Assumptions'!$B$7)^D$3,0) -> 11369 | E7: =IF('① Assumptions'!$B$107="Yes",(IF(E$4<=12,IF(E$4<='① Assumptions'!$B$113,'① Assumptions'!$B$109,0),IF(E$4<='① Assumptions'!$B$113,'① Assumptions'!$B$110,0))+IF(E$4<='① Assumptions'!$B$113,'① Assumptions'!$B$112,0)+IF(E$4<='① Assumptions'!$B$114,'① Assumptions'!$B$111,0))*(1+'① Assumptions'!$B$7)^E$3,0) -> 11710.07 | F7: =IF('① Assumptions'!$B$107="Yes",(IF(F$4<=12,IF(F$4<='① Assumptions'!$B$113,'① Assumptions'!$B$109,0),IF(F$4<='① Assumptions'!$B$113,'① Assumptions'!$B$110,0))+IF(F$4<='① Assumptions'!$B$113,'① Assumptions'!$B$112,0)+IF(F$4<='① Assumptions'!$B$114,'① Assumptions'!$B$111,0))*(1+'① Assumptions'!$B$7)^F$3,0) -> 12061.372 | G7: =IF('① Assumptions'!$B$107="Yes",(IF(G$4<=12,IF(G$4<='① Assumptions'!$B$113,'① Assumptions'!$B$109,0),IF(G$4<='① Assumptions'!$B$113,'① Assumptions'!$B$110,0))+IF(G$4<='① Assumptions'!$B$113,'① Assumptions'!$B$112,0)+IF(G$4<='① Assumptions'!$B$114,'① Assumptions'!$B$111,0))*(1+'① Assumptions'!$B$7)^G$3,0) -> 12423.213 | H7: =IF('① Assumptions'!$B$107="Yes",(IF(H$4<=12,IF(H$4<='① Assumptions'!$B$113,'① Assumptions'!$B$109,0),IF(H$4<='① Assumptions'!$B$113,'① Assumptions'!$B$110,0))+IF(H$4<='① Assumptions'!$B$113,'① Assumptions'!$B$112,0)+IF(H$4<='① Assumptions'!$B$114,'① Assumptions'!$B$111,0))*(1+'① Assumptions'!$B$7)^H$3,0) -> 12795.91 | I7: =IF('① Assumptions'!$B$107="Yes",(IF(I$4<=12,IF(I$4<='① Assumptions'!$B$113,'① Assumptions'!$B$109,0),IF(I$4<='① Assumptions'!$B$113,'① Assumptions'!$B$110,0))+IF(I$4<='① Assumptions'!$B$113,'① Assumptions'!$B$112,0)+IF(I$4<='① Assumptions'!$B$114,'① Assumptions'!$B$111,0))*(1+'① Assumptions'!$B$7)^I$3,0) -> 13179.787 | J7: =IF('① Assumptions'!$B$107="Yes",(IF(J$4<=12,IF(J$4<='① Assumptions'!$B$113,'① Assumptions'!$B$109,0),IF(J$4<='① Assumptions'!$B$113,'① Assumptions'!$B$110,0))+IF(J$4<='① Assumptions'!$B$113,'① Assumptions'!$B$112,0)+IF(J$4<='① Assumptions'!$B$114,'① Assumptions'!$B$111,0))*(1+'① Assumptions'!$B$7)^J$3,0) -> 13575.181 | K7: =IF('① Assumptions'!$B$107="Yes",(IF(K$4<=12,IF(K$4<='① Assumptions'!$B$113,'① Assumptions'!$B$109,0),IF(K$4<='① Assumptions'!$B$113,'① Assumptions'!$B$110,0))+IF(K$4<='① Assumptions'!$B$113,'① Assumptions'!$B$112,0)+IF(K$4<='① Assumptions'!$B$114,'① Assumptions'!$B$111,0))*(1+'① Assumptions'!$B$7)^K$3,0) -> 13982.436 | ... Y7: =IF('① Assumptions'!$B$107="Yes",(IF(Y$4<=12,IF(Y$4<='① Assumptions'!$B$113,'① Assumptions'!$B$109,0),IF(Y$4<='① Assumptions'!$B$113,'① Assumptions'!$B$110,0))+IF(Y$4<='① Assumptions'!$B$113,'① Assumptions'!$B$112,0)+IF(Y$4<='① Assumptions'!$B$114,'① Assumptions'!$B$111,0))*(1+'① Assumptions'!$B$7)^Y$3,0) -> 0 | Z7: =SUM(D7:Y7) -> 296692.63
A8: 💰 Contributions | B8: Income | C8: Contributions | D8: ='① Assumptions'!$B$90+'① Assumptions'!$B$93 -> 62000 | E8: ='① Assumptions'!$B$93*(1+'① Assumptions'!$B$94)^E$3 -> 12420 | F8: ='① Assumptions'!$B$93*(1+'① Assumptions'!$B$94)^F$3 -> 12854.7 | G8: ='① Assumptions'!$B$93*(1+'① Assumptions'!$B$94)^G$3 -> 13304.614 | H8: ='① Assumptions'!$B$93*(1+'① Assumptions'!$B$94)^H$3 -> 13770.276 | I8: ='① Assumptions'!$B$93*(1+'① Assumptions'!$B$94)^I$3 -> 14252.236 | J8: ='① Assumptions'!$B$93*(1+'① Assumptions'!$B$94)^J$3 -> 14751.064 | K8: ='① Assumptions'!$B$93*(1+'① Assumptions'!$B$94)^K$3 -> 15267.351 | L8: ='① Assumptions'!$B$93*(1+'① Assumptions'!$B$94)^L$3 -> 15801.708 | ... Y8: ='① Assumptions'!$B$93*(1+'① Assumptions'!$B$94)^Y$3 -> 24713.178 | Z8: =SUM(D8:Y8) -> 437946.83
A9: 📈 Investment Return | B9: Income | C9: Investment Return | D9: 0 | E9: =IF(D$35>=0,D$35*'① Assumptions'!$B$97,D$35*'① Assumptions'!$B$105) -> 2120.9445 | F9: =IF(E$35>=0,E$35*'① Assumptions'!$B$97,E$35*'① Assumptions'!$B$105) -> 2176.711 | G9: =IF(F$35>=0,F$35*'① Assumptions'!$B$97,F$35*'① Assumptions'!$B$105) -> 2227.7489 | H9: =IF(G$35>=0,G$35*'① Assumptions'!$B$97,G$35*'① Assumptions'!$B$105) -> 2124.5561 | I9: =IF(H$35>=0,H$35*'① Assumptions'!$B$97,H$35*'① Assumptions'!$B$105) -> 2148.0546 | J9: =IF(I$35>=0,I$35*'① Assumptions'!$B$97,I$35*'① Assumptions'!$B$105) -> 1292.4705 | K9: =IF(J$35>=0,J$35*'① Assumptions'!$B$97,J$35*'① Assumptions'!$B$105) -> 203.26173 | L9: =IF(K$35>=0,K$35*'① Assumptions'!$B$97,K$35*'① Assumptions'!$B$105) -> -1065.6858 | ... Y9: =IF(X$35>=0,X$35*'① Assumptions'!$B$97,X$35*'① Assumptions'!$B$105) -> -26852.627 | Z9: =SUM(D9:Y9) -> -162080.93
A10: ∑ TOTAL INCOME | B10: Income | C10: TOTAL INCOME | D10: =D$7+D$8+D$9 -> 73369 | E10: =E$7+E$8+E$9 -> 26251.015 | F10: =F$7+F$8+F$9 -> 27092.783 | G10: =G$7+G$8+G$9 -> 27955.577 | H10: =H$7+H$8+H$9 -> 28690.742 | I10: =I$7+I$8+I$9 -> 29580.077 | J10: =J$7+J$8+J$9 -> 29618.715 | K10: =K$7+K$8+K$9 -> 29453.049 | ... Y10: =Y$7+Y$8+Y$9 -> -2139.4489 | Z10: =SUM(D10:Y10) -> 572558.52
A11: COSTS
A12: 👶 Childcare | B12: Costs | C12: Childcare | D12: =IF(AND('① Assumptions'!$B$17="Yes",D$4>='① Assumptions'!$B$18,D$4<='① Assumptions'!$B$19),'① Assumptions'!$B$26*(1+'① Assumptions'!$B$49)^D$3,0) -> 0 | E12: =IF(AND('① Assumptions'!$B$17="Yes",E$4>='① Assumptions'!$B$18,E$4<='① Assumptions'!$B$19),'① Assumptions'!$B$26*(1+'① Assumptions'!$B$49)^E$3,0) -> 2954.5851 | F12: =IF(AND('① Assumptions'!$B$17="Yes",F$4>='① Assumptions'!$B$18,F$4<='① Assumptions'!$B$19),'① Assumptions'!$B$26*(1+'① Assumptions'!$B$49)^F$3,0) -> 3102.3143 | G12: =IF(AND('① Assumptions'!$B$17="Yes",G$4>='① Assumptions'!$B$18,G$4<='① Assumptions'!$B$19),'① Assumptions'!$B$26*(1+'① Assumptions'!$B$49)^G$3,0) -> 3257.4301 | H12: =IF(AND('① Assumptions'!$B$17="Yes",H$4>='① Assumptions'!$B$18,H$4<='① Assumptions'!$B$19),'① Assumptions'!$B$26*(1+'① Assumptions'!$B$49)^H$3,0) -> 3420.3016 | I12: =IF(AND('① Assumptions'!$B$17="Yes",I$4>='① Assumptions'!$B$18,I$4<='① Assumptions'!$B$19),'① Assumptions'!$B$26*(1+'① Assumptions'!$B$49)^I$3,0) -> 0 | J12: =IF(AND('① Assumptions'!$B$17="Yes",J$4>='① Assumptions'!$B$18,J$4<='① Assumptions'!$B$19),'① Assumptions'!$B$26*(1+'① Assumptions'!$B$49)^J$3,0) -> 0 | K12: =IF(AND('① Assumptions'!$B$17="Yes",K$4>='① Assumptions'!$B$18,K$4<='① Assumptions'!$B$19),'① Assumptions'!$B$26*(1+'① Assumptions'!$B$49)^K$3,0) -> 0 | ... Y12: =IF(AND('① Assumptions'!$B$17="Yes",Y$4>='① Assumptions'!$B$18,Y$4<='① Assumptions'!$B$19),'① Assumptions'!$B$26*(1+'① Assumptions'!$B$49)^Y$3,0) -> 0 | Z12: =SUM(D12:Y12) -> 12734.631
A13: 🏫 Before / After Care | B13: Costs | C13: Before/After Care | D13: =IF(AND('① Assumptions'!$B$29="Yes",D$4>=5,D$4<=12),'① Assumptions'!$B$33*(1+'① Assumptions'!$B$49)^D$3,0) -> 0 | E13: =IF(AND('① Assumptions'!$B$29="Yes",E$4>=5,E$4<=12),'① Assumptions'!$B$33*(1+'① Assumptions'!$B$49)^E$3,0) -> 0 | F13: =IF(AND('① Assumptions'!$B$29="Yes",F$4>=5,F$4<=12),'① Assumptions'!$B$33*(1+'① Assumptions'!$B$49)^F$3,0) -> 0 | G13: =IF(AND('① Assumptions'!$B$29="Yes",G$4>=5,G$4<=12),'① Assumptions'!$B$33*(1+'① Assumptions'!$B$49)^G$3,0) -> 0 | H13: =IF(AND('① Assumptions'!$B$29="Yes",H$4>=5,H$4<=12),'① Assumptions'!$B$33*(1+'① Assumptions'!$B$49)^H$3,0) -> 0 | I13: =IF(AND('① Assumptions'!$B$29="Yes",I$4>=5,I$4<=12),'① Assumptions'!$B$33*(1+'① Assumptions'!$B$49)^I$3,0) -> 15315.379 | J13: =IF(AND('① Assumptions'!$B$29="Yes",J$4>=5,J$4<=12),'① Assumptions'!$B$33*(1+'① Assumptions'!$B$49)^J$3,0) -> 16081.148 | K13: =IF(AND('① Assumptions'!$B$29="Yes",K$4>=5,K$4<=12),'① Assumptions'!$B$33*(1+'① Assumptions'!$B$49)^K$3,0) -> 16885.205 | ... Y13: =IF(AND('① Assumptions'!$B$29="Yes",Y$4>=5,Y$4<=12),'① Assumptions'!$B$33*(1+'① Assumptions'!$B$49)^Y$3,0) -> 0 | Z13: =SUM(D13:Y13) -> 146248.22
A14: 🏫 School Fees | B14: Costs | C14: School Fees | D14: =IF(OR(D$4<5,D$4>17),0,IF('① Assumptions'!$B$11="Public",IF(D$4<=11,'⑤ School Fees'!$B$18,'⑤ School Fees'!$C$18)*(1+'① Assumptions'!$B$8)^D$3,IF(D$4<IF('① Assumptions'!$B$12="Prep",5,IF('① Assumptions'!$B$12=5,10,IF('① Assumptions'!$B$12=7,12,IF('① Assumptions'!$B$12=9,14,17)))),IF(D$4<=11,'⑤ School Fees'!$B$18,'⑤ School Fees'!$C$18)*(1+'① Assumptions'!$B$8)^D$3,IF('① Assumptions'!$B$6="VIC",IF(D$4<=11,VLOOKUP('① Assumptions'!$B$13,'⑤ School Fees'!$A$6:$C$15,2,FALSE),VLOOKUP('① Assumptions'!$B$13,'⑤ School Fees'!$A$6:$C$15,3,FALSE)),IF(D$4<=11,VLOOKUP('① Assumptions'!$B$14,'⑤ School Fees'!$A$22:$C$31,2,FALSE),VLOOKUP('① Assumptions'!$B$14,'⑤ School Fees'!$A$22:$C$31,3,FALSE)))*(1-'① Assumptions'!$B$37)*(1+'① Assumptions'!$B$8)^D$3))) -> 0 | E14: =IF(OR(E$4<5,E$4>17),0,IF('① Assumptions'!$B$11="Public",IF(E$4<=11,'⑤ School Fees'!$B$18,'⑤ School Fees'!$C$18)*(1+'① Assumptions'!$B$8)^E$3,IF(E$4<IF('① Assumptions'!$B$12="Prep",5,IF('① Assumptions'!$B$12=5,10,IF('① Assumptions'!$B$12=7,12,IF('① Assumptions'!$B$12=9,14,17)))),IF(E$4<=11,'⑤ School Fees'!$B$18,'⑤ School Fees'!$C$18)*(1+'① Assumptions'!$B$8)^E$3,IF('① Assumptions'!$B$6="VIC",IF(E$4<=11,VLOOKUP('① Assumptions'!$B$13,'⑤ School Fees'!$A$6:$C$15,2,FALSE),VLOOKUP('① Assumptions'!$B$13,'⑤ School Fees'!$A$6:$C$15,3,FALSE)),IF(E$4<=11,VLOOKUP('① Assumptions'!$B$14,'⑤ School Fees'!$A$22:$C$31,2,FALSE),VLOOKUP('① Assumptions'!$B$14,'⑤ School Fees'!$A$22:$C$31,3,FALSE)))*(1-'① Assumptions'!$B$37)*(1+'① Assumptions'!$B$8)^E$3))) -> 0 | F14: =IF(OR(F$4<5,F$4>17),0,IF('① Assumptions'!$B$11="Public",IF(F$4<=11,'⑤ School Fees'!$B$18,'⑤ School Fees'!$C$18)*(1+'① Assumptions'!$B$8)^F$3,IF(F$4<IF('① Assumptions'!$B$12="Prep",5,IF('① Assumptions'!$B$12=5,10,IF('① Assumptions'!$B$12=7,12,IF('① Assumptions'!$B$12=9,14,17)))),IF(F$4<=11,'⑤ School Fees'!$B$18,'⑤ School Fees'!$C$18)*(1+'① Assumptions'!$B$8)^F$3,IF('① Assumptions'!$B$6="VIC",IF(F$4<=11,VLOOKUP('① Assumptions'!$B$13,'⑤ School Fees'!$A$6:$C$15,2,FALSE),VLOOKUP('① Assumptions'!$B$13,'⑤ School Fees'!$A$6:$C$15,3,FALSE)),IF(F$4<=11,VLOOKUP('① Assumptions'!$B$14,'⑤ School Fees'!$A$22:$C$31,2,FALSE),VLOOKUP('① Assumptions'!$B$14,'⑤ School Fees'!$A$22:$C$31,3,FALSE)))*(1-'① Assumptions'!$B$37)*(1+'① Assumptions'!$B$8)^F$3))) -> 0 | G14: =IF(OR(G$4<5,G$4>17),0,IF('① Assumptions'!$B$11="Public",IF(G$4<=11,'⑤ School Fees'!$B$18,'⑤ School Fees'!$C$18)*(1+'① Assumptions'!$B$8)^G$3,IF(G$4<IF('① Assumptions'!$B$12="Prep",5,IF('① Assumptions'!$B$12=5,10,IF('① Assumptions'!$B$12=7,12,IF('① Assumptions'!$B$12=9,14,17)))),IF(G$4<=11,'⑤ School Fees'!$B$18,'⑤ School Fees'!$C$18)*(1+'① Assumptions'!$B$8)^G$3,IF('① Assumptions'!$B$6="VIC",IF(G$4<=11,VLOOKUP('① Assumptions'!$B$13,'⑤ School Fees'!$A$6:$C$15,2,FALSE),VLOOKUP('① Assumptions'!$B$13,'⑤ School Fees'!$A$6:$C$15,3,FALSE)),IF(G$4<=11,VLOOKUP('① Assumptions'!$B$14,'⑤ School Fees'!$A$22:$C$31,2,FALSE),VLOOKUP('① Assumptions'!$B$14,'⑤ School Fees'!$A$22:$C$31,3,FALSE)))*(1-'① Assumptions'!$B$37)*(1+'① Assumptions'!$B$8)^G$3))) -> 0 | H14: =IF(OR(H$4<5,H$4>17),0,IF('① Assumptions'!$B$11="Public",IF(H$4<=11,'⑤ School Fees'!$B$18,'⑤ School Fees'!$C$18)*(1+'① Assumptions'!$B$8)^H$3,IF(H$4<IF('① Assumptions'!$B$12="Prep",5,IF('① Assumptions'!$B$12=5,10,IF('① Assumptions'!$B$12=7,12,IF('① Assumptions'!$B$12=9,14,17)))),IF(H$4<=11,'⑤ School Fees'!$B$18,'⑤ School Fees'!$C$18)*(1+'① Assumptions'!$B$8)^H$3,IF('① Assumptions'!$B$6="VIC",IF(H$4<=11,VLOOKUP('① Assumptions'!$B$13,'⑤ School Fees'!$A$6:$C$15,2,FALSE),VLOOKUP('① Assumptions'!$B$13,'⑤ School Fees'!$A$6:$C$15,3,FALSE)),IF(H$4<=11,VLOOKUP('① Assumptions'!$B$14,'⑤ School Fees'!$A$22:$C$31,2,FALSE),VLOOKUP('① Assumptions'!$B$14,'⑤ School Fees'!$A$22:$C$31,3,FALSE)))*(1-'① Assumptions'!$B$37)*(1+'① Assumptions'!$B$8)^H$3))) -> 0 | I14: =IF(OR(I$4<5,I$4>17),0,IF('① Assumptions'!$B$11="Public",IF(I$4<=11,'⑤ School Fees'!$B$18,'⑤ School Fees'!$C$18)*(1+'① Assumptions'!$B$8)^I$3,IF(I$4<IF('① Assumptions'!$B$12="Prep",5,IF('① Assumptions'!$B$12=5,10,IF('① Assumptions'!$B$12=7,12,IF('① Assumptions'!$B$12=9,14,17)))),IF(I$4<=11,'⑤ School Fees'!$B$18,'⑤ School Fees'!$C$18)*(1+'① Assumptions'!$B$8)^I$3,IF('① Assumptions'!$B$6="VIC",IF(I$4<=11,VLOOKUP('① Assumptions'!$B$13,'⑤ School Fees'!$A$6:$C$15,2,FALSE),VLOOKUP('① Assumptions'!$B$13,'⑤ School Fees'!$A$6:$C$15,3,FALSE)),IF(I$4<=11,VLOOKUP('① Assumptions'!$B$14,'⑤ School Fees'!$A$22:$C$31,2,FALSE),VLOOKUP('① Assumptions'!$B$14,'⑤ School Fees'!$A$22:$C$31,3,FALSE)))*(1-'① Assumptions'!$B$37)*(1+'① Assumptions'!$B$8)^I$3))) -> 638.14078 | J14: =IF(OR(J$4<5,J$4>17),0,IF('① Assumptions'!$B$11="Public",IF(J$4<=11,'⑤ School Fees'!$B$18,'⑤ School Fees'!$C$18)*(1+'① Assumptions'!$B$8)^J$3,IF(J$4<IF('① Assumptions'!$B$12="Prep",5,IF('① Assumptions'!$B$12=5,10,IF('① Assumptions'!$B$12=7,12,IF('① Assumptions'!$B$12=9,14,17)))),IF(J$4<=11,'⑤ School Fees'!$B$18,'⑤ School Fees'!$C$18)*(1+'① Assumptions'!$B$8)^J$3,IF('① Assumptions'!$B$6="VIC",IF(J$4<=11,VLOOKUP('① Assumptions'!$B$13,'⑤ School Fees'!$A$6:$C$15,2,FALSE),VLOOKUP('① Assumptions'!$B$13,'⑤ School Fees'!$A$6:$C$15,3,FALSE)),IF(J$4<=11,VLOOKUP('① Assumptions'!$B$14,'⑤ School Fees'!$A$22:$C$31,2,FALSE),VLOOKUP('① Assumptions'!$B$14,'⑤ School Fees'!$A$22:$C$31,3,FALSE)))*(1-'① Assumptions'!$B$37)*(1+'① Assumptions'!$B$8)^J$3))) -> 670.04782 | K14: =IF(OR(K$4<5,K$4>17),0,IF('① Assumptions'!$B$11="Public",IF(K$4<=11,'⑤ School Fees'!$B$18,'⑤ School Fees'!$C$18)*(1+'① Assumptions'!$B$8)^K$3,IF(K$4<IF('① Assumptions'!$B$12="Prep",5,IF('① Assumptions'!$B$12=5,10,IF('① Assumptions'!$B$12=7,12,IF('① Assumptions'!$B$12=9,14,17)))),IF(K$4<=11,'⑤ School Fees'!$B$18,'⑤ School Fees'!$C$18)*(1+'① Assumptions'!$B$8)^K$3,IF('① Assumptions'!$B$6="VIC",IF(K$4<=11,VLOOKUP('① Assumptions'!$B$13,'⑤ School Fees'!$A$6:$C$15,2,FALSE),VLOOKUP('① Assumptions'!$B$13,'⑤ School Fees'!$A$6:$C$15,3,FALSE)),IF(K$4<=11,VLOOKUP('① Assumptions'!$B$14,'⑤ School Fees'!$A$22:$C$31,2,FALSE),VLOOKUP('① Assumptions'!$B$14,'⑤ School Fees'!$A$22:$C$31,3,FALSE)))*(1-'① Assumptions'!$B$37)*(1+'① Assumptions'!$B$8)^K$3))) -> 703.55021 | ... Y14: =IF(OR(Y$4<5,Y$4>17),0,IF('① Assumptions'!$B$11="Public",IF(Y$4<=11,'⑤ School Fees'!$B$18,'⑤ School Fees'!$C$18)*(1+'① Assumptions'!$B$8)^Y$3,IF(Y$4<IF('① Assumptions'!$B$12="Prep",5,IF('① Assumptions'!$B$12=5,10,IF('① Assumptions'!$B$12=7,12,IF('① Assumptions'!$B$12=9,14,17)))),IF(Y$4<=11,'⑤ School Fees'!$B$18,'⑤ School Fees'!$C$18)*(1+'① Assumptions'!$B$8)^Y$3,IF('① Assumptions'!$B$6="VIC",IF(Y$4<=11,VLOOKUP('① Assumptions'!$B$13,'⑤ School Fees'!$A$6:$C$15,2,FALSE),VLOOKUP('① Assumptions'!$B$13,'⑤ School Fees'!$A$6:$C$15,3,FALSE)),IF(Y$4<=11,VLOOKUP('① Assumptions'!$B$14,'⑤ School Fees'!$A$22:$C$31,2,FALSE),VLOOKUP('① Assumptions'!$B$14,'⑤ School Fees'!$A$22:$C$31,3,FALSE)))*(1-'① Assumptions'!$B$37)*(1+'① Assumptions'!$B$8)^Y$3))) -> 0 | Z14: =SUM(D14:Y14) -> 14967.954
A15: 👕 Uniforms | B15: Costs | C15: Uniforms | D15: =IF(AND(D$4>=5,D$4<=17),'① Assumptions'!$B$85*(1+'① Assumptions'!$B$7)^D$3,0) -> 0 | E15: =IF(AND(E$4>=5,E$4<=17),'① Assumptions'!$B$85*(1+'① Assumptions'!$B$7)^E$3,0) -> 0 | F15: =IF(AND(F$4>=5,F$4<=17),'① Assumptions'!$B$85*(1+'① Assumptions'!$B$7)^F$3,0) -> 0 | G15: =IF(AND(G$4>=5,G$4<=17),'① Assumptions'!$B$85*(1+'① Assumptions'!$B$7)^G$3,0) -> 0 | H15: =IF(AND(H$4>=5,H$4<=17),'① Assumptions'!$B$85*(1+'① Assumptions'!$B$7)^H$3,0) -> 0 | I15: =IF(AND(I$4>=5,I$4<=17),'① Assumptions'!$B$85*(1+'① Assumptions'!$B$7)^I$3,0) -> 1738.9111 | J15: =IF(AND(J$4>=5,J$4<=17),'① Assumptions'!$B$85*(1+'① Assumptions'!$B$7)^J$3,0) -> 1791.0784 | K15: =IF(AND(K$4>=5,K$4<=17),'① Assumptions'!$B$85*(1+'① Assumptions'!$B$7)^K$3,0) -> 1844.8108 | ... Y15: =IF(AND(Y$4>=5,Y$4<=17),'① Assumptions'!$B$85*(1+'① Assumptions'!$B$7)^Y$3,0) -> 0 | Z15: =SUM(D15:Y15) -> 27157.949
A16: ⛺ Camps & Excursions | B16: Costs | C16: Camps & Excursions | D16: =IF(AND(D$4>=5,D$4<=17),'① Assumptions'!$B$86*(1+'① Assumptions'!$B$7)^D$3,0) -> 0 | E16: =IF(AND(E$4>=5,E$4<=17),'① Assumptions'!$B$86*(1+'① Assumptions'!$B$7)^E$3,0) -> 0 | F16: =IF(AND(F$4>=5,F$4<=17),'① Assumptions'!$B$86*(1+'① Assumptions'!$B$7)^F$3,0) -> 0 | G16: =IF(AND(G$4>=5,G$4<=17),'① Assumptions'!$B$86*(1+'① Assumptions'!$B$7)^G$3,0) -> 0 | H16: =IF(AND(H$4>=5,H$4<=17),'① Assumptions'!$B$86*(1+'① Assumptions'!$B$7)^H$3,0) -> 0 | I16: =IF(AND(I$4>=5,I$4<=17),'① Assumptions'!$B$86*(1+'① Assumptions'!$B$7)^I$3,0) -> 1159.2741 | J16: =IF(AND(J$4>=5,J$4<=17),'① Assumptions'!$B$86*(1+'① Assumptions'!$B$7)^J$3,0) -> 1194.0523 | K16: =IF(AND(K$4>=5,K$4<=17),'① Assumptions'!$B$86*(1+'① Assumptions'!$B$7)^K$3,0) -> 1229.8739 | ... Y16: =IF(AND(Y$4>=5,Y$4<=17),'① Assumptions'!$B$86*(1+'① Assumptions'!$B$7)^Y$3,0) -> 0 | Z16: =SUM(D16:Y16) -> 18105.3
A17: ⚽ Extra-Curriculars | B17: Costs | C17: Extra-Curriculars | D17: {=SUMPRODUCT(('① Assumptions'!$B$59:$B$64="Yes")*1,(D$4>='① Assumptions'!$D$59:$D$64)*1,(D$4<='① Assumptions'!$E$59:$E$64)*1,'① Assumptions'!$C$59:$C$64)*(1+'① Assumptions'!$B$7)^D$3} -> 0 | E17: {=SUMPRODUCT(('① Assumptions'!$B$59:$B$64="Yes")*1,(E$4>='① Assumptions'!$D$59:$D$64)*1,(E$4<='① Assumptions'!$E$59:$E$64)*1,'① Assumptions'!$C$59:$C$64)*(1+'① Assumptions'!$B$7)^E$3} -> 0 | F17: {=SUMPRODUCT(('① Assumptions'!$B$59:$B$64="Yes")*1,(F$4>='① Assumptions'!$D$59:$D$64)*1,(F$4<='① Assumptions'!$E$59:$E$64)*1,'① Assumptions'!$C$59:$C$64)*(1+'① Assumptions'!$B$7)^F$3} -> 0 | G17: {=SUMPRODUCT(('① Assumptions'!$B$59:$B$64="Yes")*1,(G$4>='① Assumptions'!$D$59:$D$64)*1,(G$4<='① Assumptions'!$E$59:$E$64)*1,'① Assumptions'!$C$59:$C$64)*(1+'① Assumptions'!$B$7)^G$3} -> 1311.2724 | H17: {=SUMPRODUCT(('① Assumptions'!$B$59:$B$64="Yes")*1,(H$4>='① Assumptions'!$D$59:$D$64)*1,(H$4<='① Assumptions'!$E$59:$E$64)*1,'① Assumptions'!$C$59:$C$64)*(1+'① Assumptions'!$B$7)^H$3} -> 1350.6106 | I17: {=SUMPRODUCT(('① Assumptions'!$B$59:$B$64="Yes")*1,(I$4>='① Assumptions'!$D$59:$D$64)*1,(I$4<='① Assumptions'!$E$59:$E$64)*1,'① Assumptions'!$C$59:$C$64)*(1+'① Assumptions'!$B$7)^I$3} -> 6607.8622 | J17: {=SUMPRODUCT(('① Assumptions'!$B$59:$B$64="Yes")*1,(J$4>='① Assumptions'!$D$59:$D$64)*1,(J$4<='① Assumptions'!$E$59:$E$64)*1,'① Assumptions'!$C$59:$C$64)*(1+'① Assumptions'!$B$7)^J$3} -> 10388.255 | K17: {=SUMPRODUCT(('① Assumptions'!$B$59:$B$64="Yes")*1,(K$4>='① Assumptions'!$D$59:$D$64)*1,(K$4<='① Assumptions'!$E$59:$E$64)*1,'① Assumptions'!$C$59:$C$64)*(1+'① Assumptions'!$B$7)^K$3} -> 10699.903 | ... Y17: {=SUMPRODUCT(('① Assumptions'!$B$59:$B$64="Yes")*1,(Y$4>='① Assumptions'!$D$59:$D$64)*1,(Y$4<='① Assumptions'!$E$59:$E$64)*1,'① Assumptions'!$C$59:$C$64)*(1+'① Assumptions'!$B$7)^Y$3} -> 0 | Z17: =SUM(D17:Y17) -> 207947.54
A18: 💻 Technology | B18: Costs | C18: Technology | D18: =(IF(AND(D$4>='① Assumptions'!$B$69,D$4<=20,MOD(D$4-'① Assumptions'!$B$69,'① Assumptions'!$B$68)=0),'① Assumptions'!$B$67,0)+IF(AND(D$4>='① Assumptions'!$B$70,D$4<=20,MOD(D$4-'① Assumptions'!$B$70,'① Assumptions'!$B$72)=0),'① Assumptions'!$B$71,0))*(1+'① Assumptions'!$B$7)^D$3 -> 0 | E18: =(IF(AND(E$4>='① Assumptions'!$B$69,E$4<=20,MOD(E$4-'① Assumptions'!$B$69,'① Assumptions'!$B$68)=0),'① Assumptions'!$B$67,0)+IF(AND(E$4>='① Assumptions'!$B$70,E$4<=20,MOD(E$4-'① Assumptions'!$B$70,'① Assumptions'!$B$72)=0),'① Assumptions'!$B$71,0))*(1+'① Assumptions'!$B$7)^E$3 -> 0 | F18: =(IF(AND(F$4>='① Assumptions'!$B$69,F$4<=20,MOD(F$4-'① Assumptions'!$B$69,'① Assumptions'!$B$68)=0),'① Assumptions'!$B$67,0)+IF(AND(F$4>='① Assumptions'!$B$70,F$4<=20,MOD(F$4-'① Assumptions'!$B$70,'① Assumptions'!$B$72)=0),'① Assumptions'!$B$71,0))*(1+'① Assumptions'!$B$7)^F$3 -> 0 | G18: =(IF(AND(G$4>='① Assumptions'!$B$69,G$4<=20,MOD(G$4-'① Assumptions'!$B$69,'① Assumptions'!$B$68)=0),'① Assumptions'!$B$67,0)+IF(AND(G$4>='① Assumptions'!$B$70,G$4<=20,MOD(G$4-'① Assumptions'!$B$70,'① Assumptions'!$B$72)=0),'① Assumptions'!$B$71,0))*(1+'① Assumptions'!$B$7)^G$3 -> 0 | H18: =(IF(AND(H$4>='① Assumptions'!$B$69,H$4<=20,MOD(H$4-'① Assumptions'!$B$69,'① Assumptions'!$B$68)=0),'① Assumptions'!$B$67,0)+IF(AND(H$4>='① Assumptions'!$B$70,H$4<=20,MOD(H$4-'① Assumptions'!$B$70,'① Assumptions'!$B$72)=0),'① Assumptions'!$B$71,0))*(1+'① Assumptions'!$B$7)^H$3 -> 0 | I18: =(IF(AND(I$4>='① Assumptions'!$B$69,I$4<=20,MOD(I$4-'① Assumptions'!$B$69,'① Assumptions'!$B$68)=0),'① Assumptions'!$B$67,0)+IF(AND(I$4>='① Assumptions'!$B$70,I$4<=20,MOD(I$4-'① Assumptions'!$B$70,'① Assumptions'!$B$72)=0),'① Assumptions'!$B$71,0))*(1+'① Assumptions'!$B$7)^I$3 -> 0 | J18: =(IF(AND(J$4>='① Assumptions'!$B$69,J$4<=20,MOD(J$4-'① Assumptions'!$B$69,'① Assumptions'!$B$68)=0),'① Assumptions'!$B$67,0)+IF(AND(J$4>='① Assumptions'!$B$70,J$4<=20,MOD(J$4-'① Assumptions'!$B$70,'① Assumptions'!$B$72)=0),'① Assumptions'!$B$71,0))*(1+'① Assumptions'!$B$7)^J$3 -> 0 | K18: =(IF(AND(K$4>='① Assumptions'!$B$69,K$4<=20,MOD(K$4-'① Assumptions'!$B$69,'① Assumptions'!$B$68)=0),'① Assumptions'!$B$67,0)+IF(AND(K$4>='① Assumptions'!$B$70,K$4<=20,MOD(K$4-'① Assumptions'!$B$70,'① Assumptions'!$B$72)=0),'① Assumptions'!$B$71,0))*(1+'① Assumptions'!$B$7)^K$3 -> 0 | ... Y18: =(IF(AND(Y$4>='① Assumptions'!$B$69,Y$4<=20,MOD(Y$4-'① Assumptions'!$B$69,'① Assumptions'!$B$68)=0),'① Assumptions'!$B$67,0)+IF(AND(Y$4>='① Assumptions'!$B$70,Y$4<=20,MOD(Y$4-'① Assumptions'!$B$70,'① Assumptions'!$B$72)=0),'① Assumptions'!$B$71,0))*(1+'① Assumptions'!$B$7)^Y$3 -> 0 | Z18: =SUM(D18:Y18) -> 17964.719
A19: 🏥 Health Insurance | B19: Costs | C19: Health Insurance | D19: ='① Assumptions'!$B$47*(1+'① Assumptions'!$B$48)^D$3 -> 4500 | E19: ='① Assumptions'!$B$47*(1+'① Assumptions'!$B$48)^E$3 -> 4770 | F19: ='① Assumptions'!$B$47*(1+'① Assumptions'!$B$48)^F$3 -> 5056.2 | G19: ='① Assumptions'!$B$47*(1+'① Assumptions'!$B$48)^G$3 -> 5359.572 | H19: ='① Assumptions'!$B$47*(1+'① Assumptions'!$B$48)^H$3 -> 5681.1463 | I19: ='① Assumptions'!$B$47*(1+'① Assumptions'!$B$48)^I$3 -> 6022.0151 | J19: ='① Assumptions'!$B$47*(1+'① Assumptions'!$B$48)^J$3 -> 6383.336 | K19: ='① Assumptions'!$B$47*(1+'① Assumptions'!$B$48)^K$3 -> 6766.3362 | ... Y19: ='① Assumptions'!$B$47*(1+'① Assumptions'!$B$48)^Y$3 -> 15298.036 | Z19: =SUM(D19:Y19) -> 195265.31
A20: 🦷 Orthodontics | B20: Costs | C20: Orthodontics | D20: =IF(AND(D$4>='① Assumptions'!$B$51,D$4<'① Assumptions'!$B$51+'① Assumptions'!$B$52),('① Assumptions'!$B$50/'① Assumptions'!$B$52)*(1+'① Assumptions'!$B$7)^D$3,0) -> 0 | E20: =IF(AND(E$4>='① Assumptions'!$B$51,E$4<'① Assumptions'!$B$51+'① Assumptions'!$B$52),('① Assumptions'!$B$50/'① Assumptions'!$B$52)*(1+'① Assumptions'!$B$7)^E$3,0) -> 0 | F20: =IF(AND(F$4>='① Assumptions'!$B$51,F$4<'① Assumptions'!$B$51+'① Assumptions'!$B$52),('① Assumptions'!$B$50/'① Assumptions'!$B$52)*(1+'① Assumptions'!$B$7)^F$3,0) -> 0 | G20: =IF(AND(G$4>='① Assumptions'!$B$51,G$4<'① Assumptions'!$B$51+'① Assumptions'!$B$52),('① Assumptions'!$B$50/'① Assumptions'!$B$52)*(1+'① Assumptions'!$B$7)^G$3,0) -> 0 | H20: =IF(AND(H$4>='① Assumptions'!$B$51,H$4<'① Assumptions'!$B$51+'① Assumptions'!$B$52),('① Assumptions'!$B$50/'① Assumptions'!$B$52)*(1+'① Assumptions'!$B$7)^H$3,0) -> 0 | I20: =IF(AND(I$4>='① Assumptions'!$B$51,I$4<'① Assumptions'!$B$51+'① Assumptions'!$B$52),('① Assumptions'!$B$50/'① Assumptions'!$B$52)*(1+'① Assumptions'!$B$7)^I$3,0) -> 0 | J20: =IF(AND(J$4>='① Assumptions'!$B$51,J$4<'① Assumptions'!$B$51+'① Assumptions'!$B$52),('① Assumptions'!$B$50/'① Assumptions'!$B$52)*(1+'① Assumptions'!$B$7)^J$3,0) -> 0 | K20: =IF(AND(K$4>='① Assumptions'!$B$51,K$4<'① Assumptions'!$B$51+'① Assumptions'!$B$52),('① Assumptions'!$B$50/'① Assumptions'!$B$52)*(1+'① Assumptions'!$B$7)^K$3,0) -> 0 | ... Y20: =IF(AND(Y$4>='① Assumptions'!$B$51,Y$4<'① Assumptions'!$B$51+'① Assumptions'!$B$52),('① Assumptions'!$B$50/'① Assumptions'!$B$52)*(1+'① Assumptions'!$B$7)^Y$3,0) -> 0 | Z20: =SUM(D20:Y20) -> 10130.031
A21: ⚕️ Allied Health | B21: Costs | C21: Allied Health | D21: =IF(AND(D$4>=VALUE(LEFT('① Assumptions'!$B$54,FIND("–",'① Assumptions'!$B$54)-1)),D$4<=VALUE(MID('① Assumptions'!$B$54,FIND("–",'① Assumptions'!$B$54)+1,10))),'① Assumptions'!$B$53*(1+'① Assumptions'!$B$7)^D$3,0) -> 0 | E21: =IF(AND(E$4>=VALUE(LEFT('① Assumptions'!$B$54,FIND("–",'① Assumptions'!$B$54)-1)),E$4<=VALUE(MID('① Assumptions'!$B$54,FIND("–",'① Assumptions'!$B$54)+1,10))),'① Assumptions'!$B$53*(1+'① Assumptions'!$B$7)^E$3,0) -> 0 | F21: =IF(AND(F$4>=VALUE(LEFT('① Assumptions'!$B$54,FIND("–",'① Assumptions'!$B$54)-1)),F$4<=VALUE(MID('① Assumptions'!$B$54,FIND("–",'① Assumptions'!$B$54)+1,10))),'① Assumptions'!$B$53*(1+'① Assumptions'!$B$7)^F$3,0) -> 0 | G21: =IF(AND(G$4>=VALUE(LEFT('① Assumptions'!$B$54,FIND("–",'① Assumptions'!$B$54)-1)),G$4<=VALUE(MID('① Assumptions'!$B$54,FIND("–",'① Assumptions'!$B$54)+1,10))),'① Assumptions'!$B$53*(1+'① Assumptions'!$B$7)^G$3,0) -> 2185.454 | H21: =IF(AND(H$4>=VALUE(LEFT('① Assumptions'!$B$54,FIND("–",'① Assumptions'!$B$54)-1)),H$4<=VALUE(MID('① Assumptions'!$B$54,FIND("–",'① Assumptions'!$B$54)+1,10))),'① Assumptions'!$B$53*(1+'① Assumptions'!$B$7)^H$3,0) -> 2251.0176 | I21: =IF(AND(I$4>=VALUE(LEFT('① Assumptions'!$B$54,FIND("–",'① Assumptions'!$B$54)-1)),I$4<=VALUE(MID('① Assumptions'!$B$54,FIND("–",'① Assumptions'!$B$54)+1,10))),'① Assumptions'!$B$53*(1+'① Assumptions'!$B$7)^I$3,0) -> 2318.5481 | J21: =IF(AND(J$4>=VALUE(LEFT('① Assumptions'!$B$54,FIND("–",'① Assumptions'!$B$54)-1)),J$4<=VALUE(MID('① Assumptions'!$B$54,FIND("–",'① Assumptions'!$B$54)+1,10))),'① Assumptions'!$B$53*(1+'① Assumptions'!$B$7)^J$3,0) -> 2388.1046 | K21: =IF(AND(K$4>=VALUE(LEFT('① Assumptions'!$B$54,FIND("–",'① Assumptions'!$B$54)-1)),K$4<=VALUE(MID('① Assumptions'!$B$54,FIND("–",'① Assumptions'!$B$54)+1,10))),'① Assumptions'!$B$53*(1+'① Assumptions'!$B$7)^K$3,0) -> 2459.7477 | ... Y21: =IF(AND(Y$4>=VALUE(LEFT('① Assumptions'!$B$54,FIND("–",'① Assumptions'!$B$54)-1)),Y$4<=VALUE(MID('① Assumptions'!$B$54,FIND("–",'① Assumptions'!$B$54)+1,10))),'① Assumptions'!$B$53*(1+'① Assumptions'!$B$7)^Y$3,0) -> 0 | Z21: =SUM(D21:Y21) -> 14136.412
A22: 🚗 Driving Lessons | B22: Costs | C22: Driving | D22: =IF(AND('① Assumptions'!$B$75="Yes",D$4='① Assumptions'!$B$77),'① Assumptions'!$B$76*(1+'① Assumptions'!$B$7)^D$3,0) -> 0 | E22: =IF(AND('① Assumptions'!$B$75="Yes",E$4='① Assumptions'!$B$77),'① Assumptions'!$B$76*(1+'① Assumptions'!$B$7)^E$3,0) -> 0 | F22: =IF(AND('① Assumptions'!$B$75="Yes",F$4='① Assumptions'!$B$77),'① Assumptions'!$B$76*(1+'① Assumptions'!$B$7)^F$3,0) -> 0 | G22: =IF(AND('① Assumptions'!$B$75="Yes",G$4='① Assumptions'!$B$77),'① Assumptions'!$B$76*(1+'① Assumptions'!$B$7)^G$3,0) -> 0 | H22: =IF(AND('① Assumptions'!$B$75="Yes",H$4='① Assumptions'!$B$77),'① Assumptions'!$B$76*(1+'① Assumptions'!$B$7)^H$3,0) -> 0 | I22: =IF(AND('① Assumptions'!$B$75="Yes",I$4='① Assumptions'!$B$77),'① Assumptions'!$B$76*(1+'① Assumptions'!$B$7)^I$3,0) -> 0 | J22: =IF(AND('① Assumptions'!$B$75="Yes",J$4='① Assumptions'!$B$77),'① Assumptions'!$B$76*(1+'① Assumptions'!$B$7)^J$3,0) -> 0 | K22: =IF(AND('① Assumptions'!$B$75="Yes",K$4='① Assumptions'!$B$77),'① Assumptions'!$B$76*(1+'① Assumptions'!$B$7)^K$3,0) -> 0 | ... Y22: =IF(AND('① Assumptions'!$B$75="Yes",Y$4='① Assumptions'!$B$77),'① Assumptions'!$B$76*(1+'① Assumptions'!$B$7)^Y$3,0) -> 0 | Z22: =SUM(D22:Y22) -> 2407.0597
A23: 🚙 Car Costs | B23: Costs | C23: Car Costs | D23: =IF('① Assumptions'!$B$75="Yes",IF(D$4='① Assumptions'!$B$79,'① Assumptions'!$B$78*(1+'① Assumptions'!$B$7)^D$3,0)+IF(AND(D$4>='① Assumptions'!$B$79,D$4<=21),'① Assumptions'!$B$80*(1+'① Assumptions'!$B$7)^D$3,0),0) -> 0 | E23: =IF('① Assumptions'!$B$75="Yes",IF(E$4='① Assumptions'!$B$79,'① Assumptions'!$B$78*(1+'① Assumptions'!$B$7)^E$3,0)+IF(AND(E$4>='① Assumptions'!$B$79,E$4<=21),'① Assumptions'!$B$80*(1+'① Assumptions'!$B$7)^E$3,0),0) -> 0 | F23: =IF('① Assumptions'!$B$75="Yes",IF(F$4='① Assumptions'!$B$79,'① Assumptions'!$B$78*(1+'① Assumptions'!$B$7)^F$3,0)+IF(AND(F$4>='① Assumptions'!$B$79,F$4<=21),'① Assumptions'!$B$80*(1+'① Assumptions'!$B$7)^F$3,0),0) -> 0 | G23: =IF('① Assumptions'!$B$75="Yes",IF(G$4='① Assumptions'!$B$79,'① Assumptions'!$B$78*(1+'① Assumptions'!$B$7)^G$3,0)+IF(AND(G$4>='① Assumptions'!$B$79,G$4<=21),'① Assumptions'!$B$80*(1+'① Assumptions'!$B$7)^G$3,0),0) -> 0 | H23: =IF('① Assumptions'!$B$75="Yes",IF(H$4='① Assumptions'!$B$79,'① Assumptions'!$B$78*(1+'① Assumptions'!$B$7)^H$3,0)+IF(AND(H$4>='① Assumptions'!$B$79,H$4<=21),'① Assumptions'!$B$80*(1+'① Assumptions'!$B$7)^H$3,0),0) -> 0 | I23: =IF('① Assumptions'!$B$75="Yes",IF(I$4='① Assumptions'!$B$79,'① Assumptions'!$B$78*(1+'① Assumptions'!$B$7)^I$3,0)+IF(AND(I$4>='① Assumptions'!$B$79,I$4<=21),'① Assumptions'!$B$80*(1+'① Assumptions'!$B$7)^I$3,0),0) -> 0 | J23: =IF('① Assumptions'!$B$75="Yes",IF(J$4='① Assumptions'!$B$79,'① Assumptions'!$B$78*(1+'① Assumptions'!$B$7)^J$3,0)+IF(AND(J$4>='① Assumptions'!$B$79,J$4<=21),'① Assumptions'!$B$80*(1+'① Assumptions'!$B$7)^J$3,0),0) -> 0 | K23: =IF('① Assumptions'!$B$75="Yes",IF(K$4='① Assumptions'!$B$79,'① Assumptions'!$B$78*(1+'① Assumptions'!$B$7)^K$3,0)+IF(AND(K$4>='① Assumptions'!$B$79,K$4<=21),'① Assumptions'!$B$80*(1+'① Assumptions'!$B$7)^K$3,0),0) -> 0 | ... Y23: =IF('① Assumptions'!$B$75="Yes",IF(Y$4='① Assumptions'!$B$79,'① Assumptions'!$B$78*(1+'① Assumptions'!$B$7)^Y$3,0)+IF(AND(Y$4>='① Assumptions'!$B$79,Y$4<=21),'① Assumptions'!$B$80*(1+'① Assumptions'!$B$7)^Y$3,0),0) -> 5580.8837 | Z23: =SUM(D23:Y23) -> 46903.531
A24: 🌍 Gap Year | B24: Costs | C24: Gap Year | D24: =IF(AND('① Assumptions'!$B$83="Yes",D$4=18),'① Assumptions'!$B$84*(1+'① Assumptions'!$B$7)^D$3,0) -> 0 | E24: =IF(AND('① Assumptions'!$B$83="Yes",E$4=18),'① Assumptions'!$B$84*(1+'① Assumptions'!$B$7)^E$3,0) -> 0 | F24: =IF(AND('① Assumptions'!$B$83="Yes",F$4=18),'① Assumptions'!$B$84*(1+'① Assumptions'!$B$7)^F$3,0) -> 0 | G24: =IF(AND('① Assumptions'!$B$83="Yes",G$4=18),'① Assumptions'!$B$84*(1+'① Assumptions'!$B$7)^G$3,0) -> 0 | H24: =IF(AND('① Assumptions'!$B$83="Yes",H$4=18),'① Assumptions'!$B$84*(1+'① Assumptions'!$B$7)^H$3,0) -> 0 | I24: =IF(AND('① Assumptions'!$B$83="Yes",I$4=18),'① Assumptions'!$B$84*(1+'① Assumptions'!$B$7)^I$3,0) -> 0 | J24: =IF(AND('① Assumptions'!$B$83="Yes",J$4=18),'① Assumptions'!$B$84*(1+'① Assumptions'!$B$7)^J$3,0) -> 0 | K24: =IF(AND('① Assumptions'!$B$83="Yes",K$4=18),'① Assumptions'!$B$84*(1+'① Assumptions'!$B$7)^K$3,0) -> 0 | ... Y24: =IF(AND('① Assumptions'!$B$83="Yes",Y$4=18),'① Assumptions'!$B$84*(1+'① Assumptions'!$B$7)^Y$3,0) -> 0 | Z24: =SUM(D24:Y24) -> 0
A25: 🎓 University Fees | B25: Costs | C25: University Fees | D25: =IF('① Assumptions'!$B$83="Yes",IF(AND(D$4>=19,D$4<=18+'① Assumptions'!$B$36),(IF('① Assumptions'!$B$39="Domestic",IF('① Assumptions'!$B$40="Band 1",'⑥ University'!$B$6,IF('① Assumptions'!$B$40="Band 2",'⑥ University'!$B$7,IF('① Assumptions'!$B$40="Band 3",'⑥ University'!$B$8,'⑥ University'!$B$9))),'① Assumptions'!$B$41)*(1-'① Assumptions'!$B$38))*(1+'① Assumptions'!$B$8)^D$3,0),IF(AND(D$4>=18,D$4<=17+'① Assumptions'!$B$36),(IF('① Assumptions'!$B$39="Domestic",IF('① Assumptions'!$B$40="Band 1",'⑥ University'!$B$6,IF('① Assumptions'!$B$40="Band 2",'⑥ University'!$B$7,IF('① Assumptions'!$B$40="Band 3",'⑥ University'!$B$8,'⑥ University'!$B$9))),'① Assumptions'!$B$41)*(1-'① Assumptions'!$B$38))*(1+'① Assumptions'!$B$8)^D$3,0)) -> 0 | E25: =IF('① Assumptions'!$B$83="Yes",IF(AND(E$4>=19,E$4<=18+'① Assumptions'!$B$36),(IF('① Assumptions'!$B$39="Domestic",IF('① Assumptions'!$B$40="Band 1",'⑥ University'!$B$6,IF('① Assumptions'!$B$40="Band 2",'⑥ University'!$B$7,IF('① Assumptions'!$B$40="Band 3",'⑥ University'!$B$8,'⑥ University'!$B$9))),'① Assumptions'!$B$41)*(1-'① Assumptions'!$B$38))*(1+'① Assumptions'!$B$8)^E$3,0),IF(AND(E$4>=18,E$4<=17+'① Assumptions'!$B$36),(IF('① Assumptions'!$B$39="Domestic",IF('① Assumptions'!$B$40="Band 1",'⑥ University'!$B$6,IF('① Assumptions'!$B$40="Band 2",'⑥ University'!$B$7,IF('① Assumptions'!$B$40="Band 3",'⑥ University'!$B$8,'⑥ University'!$B$9))),'① Assumptions'!$B$41)*(1-'① Assumptions'!$B$38))*(1+'① Assumptions'!$B$8)^E$3,0)) -> 0 | F25: =IF('① Assumptions'!$B$83="Yes",IF(AND(F$4>=19,F$4<=18+'① Assumptions'!$B$36),(IF('① Assumptions'!$B$39="Domestic",IF('① Assumptions'!$B$40="Band 1",'⑥ University'!$B$6,IF('① Assumptions'!$B$40="Band 2",'⑥ University'!$B$7,IF('① Assumptions'!$B$40="Band 3",'⑥ University'!$B$8,'⑥ University'!$B$9))),'① Assumptions'!$B$41)*(1-'① Assumptions'!$B$38))*(1+'① Assumptions'!$B$8)^F$3,0),IF(AND(F$4>=18,F$4<=17+'① Assumptions'!$B$36),(IF('① Assumptions'!$B$39="Domestic",IF('① Assumptions'!$B$40="Band 1",'⑥ University'!$B$6,IF('① Assumptions'!$B$40="Band 2",'⑥ University'!$B$7,IF('① Assumptions'!$B$40="Band 3",'⑥ University'!$B$8,'⑥ University'!$B$9))),'① Assumptions'!$B$41)*(1-'① Assumptions'!$B$38))*(1+'① Assumptions'!$B$8)^F$3,0)) -> 0 | G25: =IF('① Assumptions'!$B$83="Yes",IF(AND(G$4>=19,G$4<=18+'① Assumptions'!$B$36),(IF('① Assumptions'!$B$39="Domestic",IF('① Assumptions'!$B$40="Band 1",'⑥ University'!$B$6,IF('① Assumptions'!$B$40="Band 2",'⑥ University'!$B$7,IF('① Assumptions'!$B$40="Band 3",'⑥ University'!$B$8,'⑥ University'!$B$9))),'① Assumptions'!$B$41)*(1-'① Assumptions'!$B$38))*(1+'① Assumptions'!$B$8)^G$3,0),IF(AND(G$4>=18,G$4<=17+'① Assumptions'!$B$36),(IF('① Assumptions'!$B$39="Domestic",IF('① Assumptions'!$B$40="Band 1",'⑥ University'!$B$6,IF('① Assumptions'!$B$40="Band 2",'⑥ University'!$B$7,IF('① Assumptions'!$B$40="Band 3",'⑥ University'!$B$8,'⑥ University'!$B$9))),'① Assumptions'!$B$41)*(1-'① Assumptions'!$B$38))*(1+'① Assumptions'!$B$8)^G$3,0)) -> 0 | H25: =IF('① Assumptions'!$B$83="Yes",IF(AND(H$4>=19,H$4<=18+'① Assumptions'!$B$36),(IF('① Assumptions'!$B$39="Domestic",IF('① Assumptions'!$B$40="Band 1",'⑥ University'!$B$6,IF('① Assumptions'!$B$40="Band 2",'⑥ University'!$B$7,IF('① Assumptions'!$B$40="Band 3",'⑥ University'!$B$8,'⑥ University'!$B$9))),'① Assumptions'!$B$41)*(1-'① Assumptions'!$B$38))*(1+'① Assumptions'!$B$8)^H$3,0),IF(AND(H$4>=18,H$4<=17+'① Assumptions'!$B$36),(IF('① Assumptions'!$B$39="Domestic",IF('① Assumptions'!$B$40="Band 1",'⑥ University'!$B$6,IF('① Assumptions'!$B$40="Band 2",'⑥ University'!$B$7,IF('① Assumptions'!$B$40="Band 3",'⑥ University'!$B$8,'⑥ University'!$B$9))),'① Assumptions'!$B$41)*(1-'① Assumptions'!$B$38))*(1+'① Assumptions'!$B$8)^H$3,0)) -> 0 | I25: =IF('① Assumptions'!$B$83="Yes",IF(AND(I$4>=19,I$4<=18+'① Assumptions'!$B$36),(IF('① Assumptions'!$B$39="Domestic",IF('① Assumptions'!$B$40="Band 1",'⑥ University'!$B$6,IF('① Assumptions'!$B$40="Band 2",'⑥ University'!$B$7,IF('① Assumptions'!$B$40="Band 3",'⑥ University'!$B$8,'⑥ University'!$B$9))),'① Assumptions'!$B$41)*(1-'① Assumptions'!$B$38))*(1+'① Assumptions'!$B$8)^I$3,0),IF(AND(I$4>=18,I$4<=17+'① Assumptions'!$B$36),(IF('① Assumptions'!$B$39="Domestic",IF('① Assumptions'!$B$40="Band 1",'⑥ University'!$B$6,IF('① Assumptions'!$B$40="Band 2",'⑥ University'!$B$7,IF('① Assumptions'!$B$40="Band 3",'⑥ University'!$B$8,'⑥ University'!$B$9))),'① Assumptions'!$B$41)*(1-'① Assumptions'!$B$38))*(1+'① Assumptions'!$B$8)^I$3,0)) -> 0 | J25: =IF('① Assumptions'!$B$83="Yes",IF(AND(J$4>=19,J$4<=18+'① Assumptions'!$B$36),(IF('① Assumptions'!$B$39="Domestic",IF('① Assumptions'!$B$40="Band 1",'⑥ University'!$B$6,IF('① Assumptions'!$B$40="Band 2",'⑥ University'!$B$7,IF('① Assumptions'!$B$40="Band 3",'⑥ University'!$B$8,'⑥ University'!$B$9))),'① Assumptions'!$B$41)*(1-'① Assumptions'!$B$38))*(1+'① Assumptions'!$B$8)^J$3,0),IF(AND(J$4>=18,J$4<=17+'① Assumptions'!$B$36),(IF('① Assumptions'!$B$39="Domestic",IF('① Assumptions'!$B$40="Band 1",'⑥ University'!$B$6,IF('① Assumptions'!$B$40="Band 2",'⑥ University'!$B$7,IF('① Assumptions'!$B$40="Band 3",'⑥ University'!$B$8,'⑥ University'!$B$9))),'① Assumptions'!$B$41)*(1-'① Assumptions'!$B$38))*(1+'① Assumptions'!$B$8)^J$3,0)) -> 0 | K25: =IF('① Assumptions'!$B$83="Yes",IF(AND(K$4>=19,K$4<=18+'① Assumptions'!$B$36),(IF('① Assumptions'!$B$39="Domestic",IF('① Assumptions'!$B$40="Band 1",'⑥ University'!$B$6,IF('① Assumptions'!$B$40="Band 2",'⑥ University'!$B$7,IF('① Assumptions'!$B$40="Band 3",'⑥ University'!$B$8,'⑥ University'!$B$9))),'① Assumptions'!$B$41)*(1-'① Assumptions'!$B$38))*(1+'① Assumptions'!$B$8)^K$3,0),IF(AND(K$4>=18,K$4<=17+'① Assumptions'!$B$36),(IF('① Assumptions'!$B$39="Domestic",IF('① Assumptions'!$B$40="Band 1",'⑥ University'!$B$6,IF('① Assumptions'!$B$40="Band 2",'⑥ University'!$B$7,IF('① Assumptions'!$B$40="Band 3",'⑥ University'!$B$8,'⑥ University'!$B$9))),'① Assumptions'!$B$41)*(1-'① Assumptions'!$B$38))*(1+'① Assumptions'!$B$8)^K$3,0)) -> 0 | ... Y25: =IF('① Assumptions'!$B$83="Yes",IF(AND(Y$4>=19,Y$4<=18+'① Assumptions'!$B$36),(IF('① Assumptions'!$B$39="Domestic",IF('① Assumptions'!$B$40="Band 1",'⑥ University'!$B$6,IF('① Assumptions'!$B$40="Band 2",'⑥ University'!$B$7,IF('① Assumptions'!$B$40="Band 3",'⑥ University'!$B$8,'⑥ University'!$B$9))),'① Assumptions'!$B$41)*(1-'① Assumptions'!$B$38))*(1+'① Assumptions'!$B$8)^Y$3,0),IF(AND(Y$4>=18,Y$4<=17+'① Assumptions'!$B$36),(IF('① Assumptions'!$B$39="Domestic",IF('① Assumptions'!$B$40="Band 1",'⑥ University'!$B$6,IF('① Assumptions'!$B$40="Band 2",'⑥ University'!$B$7,IF('① Assumptions'!$B$40="Band 3",'⑥ University'!$B$8,'⑥ University'!$B$9))),'① Assumptions'!$B$41)*(1-'① Assumptions'!$B$38))*(1+'① Assumptions'!$B$8)^Y$3,0)) -> 0 | Z25: =SUM(D25:Y25) -> 60854.261
A26: 🏠 Uni Living Costs | B26: Costs | C26: Uni Living Costs | D26: =IF('① Assumptions'!$B$42="Away",IF('① Assumptions'!$B$83="Yes",IF(AND(D$4>=19,D$4<=18+'① Assumptions'!$B$36),'① Assumptions'!$B$43*(1+'① Assumptions'!$B$7)^D$3,0),IF(AND(D$4>=18,D$4<=17+'① Assumptions'!$B$36),'① Assumptions'!$B$43*(1+'① Assumptions'!$B$7)^D$3,0)),0) -> 0 | E26: =IF('① Assumptions'!$B$42="Away",IF('① Assumptions'!$B$83="Yes",IF(AND(E$4>=19,E$4<=18+'① Assumptions'!$B$36),'① Assumptions'!$B$43*(1+'① Assumptions'!$B$7)^E$3,0),IF(AND(E$4>=18,E$4<=17+'① Assumptions'!$B$36),'① Assumptions'!$B$43*(1+'① Assumptions'!$B$7)^E$3,0)),0) -> 0 | F26: =IF('① Assumptions'!$B$42="Away",IF('① Assumptions'!$B$83="Yes",IF(AND(F$4>=19,F$4<=18+'① Assumptions'!$B$36),'① Assumptions'!$B$43*(1+'① Assumptions'!$B$7)^F$3,0),IF(AND(F$4>=18,F$4<=17+'① Assumptions'!$B$36),'① Assumptions'!$B$43*(1+'① Assumptions'!$B$7)^F$3,0)),0) -> 0 | G26: =IF('① Assumptions'!$B$42="Away",IF('① Assumptions'!$B$83="Yes",IF(AND(G$4>=19,G$4<=18+'① Assumptions'!$B$36),'① Assumptions'!$B$43*(1+'① Assumptions'!$B$7)^G$3,0),IF(AND(G$4>=18,G$4<=17+'① Assumptions'!$B$36),'① Assumptions'!$B$43*(1+'① Assumptions'!$B$7)^G$3,0)),0) -> 0 | H26: =IF('① Assumptions'!$B$42="Away",IF('① Assumptions'!$B$83="Yes",IF(AND(H$4>=19,H$4<=18+'① Assumptions'!$B$36),'① Assumptions'!$B$43*(1+'① Assumptions'!$B$7)^H$3,0),IF(AND(H$4>=18,H$4<=17+'① Assumptions'!$B$36),'① Assumptions'!$B$43*(1+'① Assumptions'!$B$7)^H$3,0)),0) -> 0 | I26: =IF('① Assumptions'!$B$42="Away",IF('① Assumptions'!$B$83="Yes",IF(AND(I$4>=19,I$4<=18+'① Assumptions'!$B$36),'① Assumptions'!$B$43*(1+'① Assumptions'!$B$7)^I$3,0),IF(AND(I$4>=18,I$4<=17+'① Assumptions'!$B$36),'① Assumptions'!$B$43*(1+'① Assumptions'!$B$7)^I$3,0)),0) -> 0 | J26: =IF('① Assumptions'!$B$42="Away",IF('① Assumptions'!$B$83="Yes",IF(AND(J$4>=19,J$4<=18+'① Assumptions'!$B$36),'① Assumptions'!$B$43*(1+'① Assumptions'!$B$7)^J$3,0),IF(AND(J$4>=18,J$4<=17+'① Assumptions'!$B$36),'① Assumptions'!$B$43*(1+'① Assumptions'!$B$7)^J$3,0)),0) -> 0 | K26: =IF('① Assumptions'!$B$42="Away",IF('① Assumptions'!$B$83="Yes",IF(AND(K$4>=19,K$4<=18+'① Assumptions'!$B$36),'① Assumptions'!$B$43*(1+'① Assumptions'!$B$7)^K$3,0),IF(AND(K$4>=18,K$4<=17+'① Assumptions'!$B$36),'① Assumptions'!$B$43*(1+'① Assumptions'!$B$7)^K$3,0)),0) -> 0 | ... Y26: =IF('① Assumptions'!$B$42="Away",IF('① Assumptions'!$B$83="Yes",IF(AND(Y$4>=19,Y$4<=18+'① Assumptions'!$B$36),'① Assumptions'!$B$43*(1+'① Assumptions'!$B$7)^Y$3,0),IF(AND(Y$4>=18,Y$4<=17+'① Assumptions'!$B$36),'① Assumptions'!$B$43*(1+'① Assumptions'!$B$7)^Y$3,0)),0) -> 0 | Z26: =SUM(D26:Y26) -> 0
A27: 📚 Textbooks | B27: Costs | C27: Textbooks | D27: =IF('① Assumptions'!$B$83="Yes",IF(AND(D$4>=19,D$4<=18+'① Assumptions'!$B$36),'① Assumptions'!$B$44*(1+'① Assumptions'!$B$7)^D$3,0),IF(AND(D$4>=18,D$4<=17+'① Assumptions'!$B$36),'① Assumptions'!$B$44*(1+'① Assumptions'!$B$7)^D$3,0)) -> 0 | E27: =IF('① Assumptions'!$B$83="Yes",IF(AND(E$4>=19,E$4<=18+'① Assumptions'!$B$36),'① Assumptions'!$B$44*(1+'① Assumptions'!$B$7)^E$3,0),IF(AND(E$4>=18,E$4<=17+'① Assumptions'!$B$36),'① Assumptions'!$B$44*(1+'① Assumptions'!$B$7)^E$3,0)) -> 0 | F27: =IF('① Assumptions'!$B$83="Yes",IF(AND(F$4>=19,F$4<=18+'① Assumptions'!$B$36),'① Assumptions'!$B$44*(1+'① Assumptions'!$B$7)^F$3,0),IF(AND(F$4>=18,F$4<=17+'① Assumptions'!$B$36),'① Assumptions'!$B$44*(1+'① Assumptions'!$B$7)^F$3,0)) -> 0 | G27: =IF('① Assumptions'!$B$83="Yes",IF(AND(G$4>=19,G$4<=18+'① Assumptions'!$B$36),'① Assumptions'!$B$44*(1+'① Assumptions'!$B$7)^G$3,0),IF(AND(G$4>=18,G$4<=17+'① Assumptions'!$B$36),'① Assumptions'!$B$44*(1+'① Assumptions'!$B$7)^G$3,0)) -> 0 | H27: =IF('① Assumptions'!$B$83="Yes",IF(AND(H$4>=19,H$4<=18+'① Assumptions'!$B$36),'① Assumptions'!$B$44*(1+'① Assumptions'!$B$7)^H$3,0),IF(AND(H$4>=18,H$4<=17+'① Assumptions'!$B$36),'① Assumptions'!$B$44*(1+'① Assumptions'!$B$7)^H$3,0)) -> 0 | I27: =IF('① Assumptions'!$B$83="Yes",IF(AND(I$4>=19,I$4<=18+'① Assumptions'!$B$36),'① Assumptions'!$B$44*(1+'① Assumptions'!$B$7)^I$3,0),IF(AND(I$4>=18,I$4<=17+'① Assumptions'!$B$36),'① Assumptions'!$B$44*(1+'① Assumptions'!$B$7)^I$3,0)) -> 0 | J27: =IF('① Assumptions'!$B$83="Yes",IF(AND(J$4>=19,J$4<=18+'① Assumptions'!$B$36),'① Assumptions'!$B$44*(1+'① Assumptions'!$B$7)^J$3,0),IF(AND(J$4>=18,J$4<=17+'① Assumptions'!$B$36),'① Assumptions'!$B$44*(1+'① Assumptions'!$B$7)^J$3,0)) -> 0 | K27: =IF('① Assumptions'!$B$83="Yes",IF(AND(K$4>=19,K$4<=18+'① Assumptions'!$B$36),'① Assumptions'!$B$44*(1+'① Assumptions'!$B$7)^K$3,0),IF(AND(K$4>=18,K$4<=17+'① Assumptions'!$B$36),'① Assumptions'!$B$44*(1+'① Assumptions'!$B$7)^K$3,0)) -> 0 | ... Y27: =IF('① Assumptions'!$B$83="Yes",IF(AND(Y$4>=19,Y$4<=18+'① Assumptions'!$B$36),'① Assumptions'!$B$44*(1+'① Assumptions'!$B$7)^Y$3,0),IF(AND(Y$4>=18,Y$4<=17+'① Assumptions'!$B$36),'① Assumptions'!$B$44*(1+'① Assumptions'!$B$7)^Y$3,0)) -> 0 | Z27: =SUM(D27:Y27) -> 5262.0503
A28: 🛡️ Life Insurance | B28: Costs | C28: Life Insurance | D28: ='① Assumptions'!$B$102*(1+'① Assumptions'!$B$7)^D$3 -> 1500 | E28: ='① Assumptions'!$B$102*(1+'① Assumptions'!$B$7)^E$3 -> 1545 | F28: ='① Assumptions'!$B$102*(1+'① Assumptions'!$B$7)^F$3 -> 1591.35 | G28: ='① Assumptions'!$B$102*(1+'① Assumptions'!$B$7)^G$3 -> 1639.0905 | H28: ='① Assumptions'!$B$102*(1+'① Assumptions'!$B$7)^H$3 -> 1688.2632 | I28: ='① Assumptions'!$B$102*(1+'① Assumptions'!$B$7)^I$3 -> 1738.9111 | J28: ='① Assumptions'!$B$102*(1+'① Assumptions'!$B$7)^J$3 -> 1791.0784 | K28: ='① Assumptions'!$B$102*(1+'① Assumptions'!$B$7)^K$3 -> 1844.8108 | ... Y28: ='① Assumptions'!$B$102*(1+'① Assumptions'!$B$7)^Y$3 -> 2790.4419 | Z28: =SUM(D28:Y28) -> 45805.17
A29: 🛒 Living Costs | B29: Costs | C29: Living Costs | D29: {=SUMPRODUCT(('① Assumptions'!$B$122:$B$132="Yes")*1,(D$4>='① Assumptions'!$D$122:$D$132)*1,(D$4<='① Assumptions'!$E$122:$E$132)*1,'① Assumptions'!$C$122:$C$132)*(1+'① Assumptions'!$B$7)^D$3} -> 14000 | E29: {=SUMPRODUCT(('① Assumptions'!$B$122:$B$132="Yes")*1,(E$4>='① Assumptions'!$D$122:$D$132)*1,(E$4<='① Assumptions'!$E$122:$E$132)*1,'① Assumptions'!$C$122:$C$132)*(1+'① Assumptions'!$B$7)^E$3} -> 14420 | F29: {=SUMPRODUCT(('① Assumptions'!$B$122:$B$132="Yes")*1,(F$4>='① Assumptions'!$D$122:$D$132)*1,(F$4<='① Assumptions'!$E$122:$E$132)*1,'① Assumptions'!$C$122:$C$132)*(1+'① Assumptions'!$B$7)^F$3} -> 14852.6 | G29: {=SUMPRODUCT(('① Assumptions'!$B$122:$B$132="Yes")*1,(G$4>='① Assumptions'!$D$122:$D$132)*1,(G$4<='① Assumptions'!$E$122:$E$132)*1,'① Assumptions'!$C$122:$C$132)*(1+'① Assumptions'!$B$7)^G$3} -> 15298.178 | H29: {=SUMPRODUCT(('① Assumptions'!$B$122:$B$132="Yes")*1,(H$4>='① Assumptions'!$D$122:$D$132)*1,(H$4<='① Assumptions'!$E$122:$E$132)*1,'① Assumptions'!$C$122:$C$132)*(1+'① Assumptions'!$B$7)^H$3} -> 12380.597 | I29: {=SUMPRODUCT(('① Assumptions'!$B$122:$B$132="Yes")*1,(I$4>='① Assumptions'!$D$122:$D$132)*1,(I$4<='① Assumptions'!$E$122:$E$132)*1,'① Assumptions'!$C$122:$C$132)*(1+'① Assumptions'!$B$7)^I$3} -> 12752.015 | J29: {=SUMPRODUCT(('① Assumptions'!$B$122:$B$132="Yes")*1,(J$4>='① Assumptions'!$D$122:$D$132)*1,(J$4<='① Assumptions'!$E$122:$E$132)*1,'① Assumptions'!$C$122:$C$132)*(1+'① Assumptions'!$B$7)^J$3} -> 13134.575 | K29: {=SUMPRODUCT(('① Assumptions'!$B$122:$B$132="Yes")*1,(K$4>='① Assumptions'!$D$122:$D$132)*1,(K$4<='① Assumptions'!$E$122:$E$132)*1,'① Assumptions'!$C$122:$C$132)*(1+'① Assumptions'!$B$7)^K$3} -> 13528.613 | ... Y29: {=SUMPRODUCT(('① Assumptions'!$B$122:$B$132="Yes")*1,(Y$4>='① Assumptions'!$D$122:$D$132)*1,(Y$4<='① Assumptions'!$E$122:$E$132)*1,'① Assumptions'!$C$122:$C$132)*(1+'① Assumptions'!$B$7)^Y$3} -> 20463.24 | Z29: =SUM(D29:Y29) -> 348455.46
A30: 🛡️ Contingency (5%) | B30: Costs | C30: Contingency | D30: =SUM(D$12:D$29)*'① Assumptions'!$B$98 -> 1000 | E30: =SUM(E$12:E$29)*'① Assumptions'!$B$98 -> 1184.4793 | F30: =SUM(F$12:F$29)*'① Assumptions'!$B$98 -> 1230.1232 | G30: =SUM(G$12:G$29)*'① Assumptions'!$B$98 -> 1452.5498 | H30: =SUM(H$12:H$29)*'① Assumptions'!$B$98 -> 1338.5968 | I30: =SUM(I$12:I$29)*'① Assumptions'!$B$98 -> 2414.5528 | J30: =SUM(J$12:J$29)*'① Assumptions'!$B$98 -> 2691.0838 | K30: =SUM(K$12:K$29)*'① Assumptions'!$B$98 -> 2798.1425 | ... Y30: =SUM(Y$12:Y$29)*'① Assumptions'!$B$98 -> 2206.6301 | Z30: =SUM(D30:Y30) -> 58717.28
A31: ∑ TOTAL COSTS | B31: Costs | C31: TOTAL COSTS | D31: =SUM(D$12:D$30) -> 21000 | E31: =SUM(E$12:E$30) -> 24874.064 | F31: =SUM(F$12:F$30) -> 25832.588 | G31: =SUM(G$12:G$30) -> 30503.547 | H31: =SUM(H$12:H$30) -> 28110.533 | I31: =SUM(I$12:I$30) -> 50705.609 | J31: =SUM(J$12:J$30) -> 56512.759 | K31: =SUM(K$12:K$30) -> 58760.992 | ... Y31: =SUM(Y$12:Y$30) -> 46339.232 | Z31: =SUM(D31:Y31) -> 1233062.9
A32: SUMMARY
A33: ▶ Net Cash Flow | B33: Summary | C33: NET CASH FLOW | D33: =D$10-D$31 -> 52369 | E33: =E$10-E$31 -> 1376.9502 | F33: =F$10-F$31 -> 1260.1955 | G33: =G$10-G$31 -> -2547.9701 | H33: =H$10-H$31 -> 580.20877 | I33: =I$10-I$31 -> -21125.532 | J33: =J$10-J$31 -> -26894.044 | K33: =K$10-K$31 -> -29307.943 | ... Y33: =Y$10-Y$31 -> -48478.681 | Z33: =SUM(D33:Y33) -> -660504.36
A34: ▶ Cumulative Balance | B34: Summary | C34: CUMULATIVE BALANCE | D34: =D$33 -> 52369 | E34: =D$34+E$33 -> 53745.95 | F34: =E$34+F$33 -> 55006.146 | G34: =F$34+G$33 -> 52458.176 | H34: =G$34+H$33 -> 53038.384 | I34: =H$34+I$33 -> 31912.853 | J34: =I$34+J$33 -> 5018.8083 | K34: =J$34+K$33 -> -24289.135 | L34: =K$34+L$33 -> -56257.529 | ... Y34: =X$34+Y$33 -> -660504.36 | Z34: =Y34 -> -660504.36
A35: ★ Fund Balance (w/ Interest) | B35: Summary | C35: Fund Balance (w/ Interest) | D35: =D$8+D$7-D$31 -> 52369 | E35: =IF(D$35>=0,D$35*(1+'① Assumptions'!$B$97),D$35*(1+'① Assumptions'!$B$105))+E$8+E$7-E$31 -> 53745.95 | F35: =IF(E$35>=0,E$35*(1+'① Assumptions'!$B$97),E$35*(1+'① Assumptions'!$B$105))+F$8+F$7-F$31 -> 55006.146 | G35: =IF(F$35>=0,F$35*(1+'① Assumptions'!$B$97),F$35*(1+'① Assumptions'!$B$105))+G$8+G$7-G$31 -> 52458.176 | H35: =IF(G$35>=0,G$35*(1+'① Assumptions'!$B$97),G$35*(1+'① Assumptions'!$B$105))+H$8+H$7-H$31 -> 53038.384 | I35: =IF(H$35>=0,H$35*(1+'① Assumptions'!$B$97),H$35*(1+'① Assumptions'!$B$105))+I$8+I$7-I$31 -> 31912.853 | J35: =IF(I$35>=0,I$35*(1+'① Assumptions'!$B$97),I$35*(1+'① Assumptions'!$B$105))+J$8+J$7-J$31 -> 5018.8083 | K35: =IF(J$35>=0,J$35*(1+'① Assumptions'!$B$97),J$35*(1+'① Assumptions'!$B$105))+K$8+K$7-K$31 -> -24289.135 | L35: =IF(K$35>=0,K$35*(1+'① Assumptions'!$B$97),K$35*(1+'① Assumptions'!$B$105))+L$8+L$7-L$31 -> -56257.529 | ... Y35: =IF(X$35>=0,X$35*(1+'① Assumptions'!$B$97),X$35*(1+'① Assumptions'!$B$105))+Y$8+Y$7-Y$31 -> -660504.36 | Z35: =Y35 -> -660504.36
A36: TIME VALUE OF MONEY
A37: ⧗ PV of Net Cash Flow | B37: Time Value | C37: PV of Net Cash Flow | D37: =D$33/(1+'① Assumptions'!$B$103)^D$3 -> 52369 | E37: =E$33/(1+'① Assumptions'!$B$103)^E$3 -> 1320.8155 | F37: =F$33/(1+'① Assumptions'!$B$103)^F$3 -> 1159.5402 | G37: =G$33/(1+'① Assumptions'!$B$103)^G$3 -> -2248.8793 | H37: =H$33/(1+'① Assumptions'!$B$103)^H$3 -> 491.22452 | I37: =I$33/(1+'① Assumptions'!$B$103)^I$3 -> -17156.446 | J37: =J$33/(1+'① Assumptions'!$B$103)^J$3 -> -20950.758 | K37: =K$33/(1+'① Assumptions'!$B$103)^K$3 -> -21900.443 | ... Y37: =Y$33/(1+'① Assumptions'!$B$103)^Y$3 -> -20228.024 | Z37: =SUM(D37:Y37) -> -348503.21
A38: ⧗ Cumulative PV | B38: Time Value | C38: Cumulative PV | D38: =D$37 -> 52369 | E38: =D$38+E$37 -> 53689.815 | F38: =E$38+F$37 -> 54849.356 | G38: =F$38+G$37 -> 52600.476 | H38: =G$38+H$37 -> 53091.701 | I38: =H$38+I$37 -> 35935.255 | J38: =I$38+J$37 -> 14984.497 | K38: =J$38+K$37 -> -6915.9459 | L38: =K$38+L$37 -> -29830.547 | ... Y38: =X$38+Y$37 -> -348503.21 | Z38: =Y38 -> -348503.21
A39: 💳 Debt Interest Cost | B39: Time Value | C39: Debt Interest Cost | D39: =IF(D$35<0,D$35*'① Assumptions'!$B$105,0) -> 0 | E39: =IF(E$35<0,E$35*'① Assumptions'!$B$105,0) -> 0 | F39: =IF(F$35<0,F$35*'① Assumptions'!$B$105,0) -> 0 | G39: =IF(G$35<0,G$35*'① Assumptions'!$B$105,0) -> 0 | H39: =IF(H$35<0,H$35*'① Assumptions'!$B$105,0) -> 0 | I39: =IF(I$35<0,I$35*'① Assumptions'!$B$105,0) -> 0 | J39: =IF(J$35<0,J$35*'① Assumptions'!$B$105,0) -> 0 | K39: =IF(K$35<0,K$35*'① Assumptions'!$B$105,0) -> -1065.6858 | ... Y39: =IF(Y$35<0,Y$35*'① Assumptions'!$B$105,0) -> -28979.629 | Z39: =SUM(D39:Y39) -> -203354.31
A40: 🟢 Fund Balance ≥ $0 (surplus / invested) | B40: 🔴 Fund Balance < $0 (borrowing) | C40: 📊 Bar in TOTALS col = relative cost size | D40: 💛 TOTALS column = 21-year sum | E40: Even cols = white | Odd cols = cream | F40: All 19 integrity checks: ✅ PASS
A41: ✔ MODEL INTEGRITY CHECKS
A42: # | B42: Check Description | C42: Proof (Formula Link) | D42: Expected | E42: Actual | F42: Difference | G42: Status
A43: 1 | B43: Total Income + Total Costs = Net Cash Flow | C43: ="Z33 ("&TEXT(Z33,"$#,##0")&") = Z31 ("&TEXT(Z10,"$#,##0")&") − Z26 ("&TEXT(Z31,"$#,##0")&") → Diff: "&TEXT(Z33-(Z10-Z31),"$#,##0.00") -> Z33 (-$660,504) = Z31 ($572,559) − Z26 ($1,233,063) → Diff: $0.00 | D43: 0 | E43: =Z33-(Z10-Z31) -> 0 | F43: =ABS(E43-D43) -> 0 | G43: =IF(F43<0.01,"✅ PASS","❌ FAIL") -> ✅ PASS
A44: 2 | B44: Cumulative Balance = Sum of Net Cash Flows | C44: ="Y34 ("&TEXT(Y34,"$#,##0")&") = SUM(D33:Y33) → Z33 ("&TEXT(Z33,"$#,##0")&") → Diff: "&TEXT(ABS(Y34-Z33),"$#,##0.00") -> Y34 (-$660,504) = SUM(D33:Y33) → Z33 (-$660,504) → Diff: $0.00 | D44: =Z33 -> -660504.36 | E44: =Y34 -> -660504.36 | F44: =ABS(E44-D44) -> 0 | G44: =IF(F44<0.01,"✅ PASS","❌ FAIL") -> ✅ PASS
A45: 3 | B45: Fund Balance Year 0 = Contributions + Benefits − Costs | C45: ="D35 ("&TEXT(D35,"$#,##0")&") = D29 ("&TEXT(D8,"$#,##0")&") + D28 ("&TEXT(D7,"$#,##0")&") − D26 ("&TEXT(D31,"$#,##0")&")" -> D35 ($52,369) = D29 ($62,000) + D28 ($11,369) − D26 ($21,000) | D45: =D8+D7-D31 -> 52369 | E45: =D35 -> 52369 | F45: =ABS(E45-D45) -> 0 | G45: =IF(F45<0.01,"✅ PASS","❌ FAIL") -> ✅ PASS
A46: 4 | B46: Final Fund Balance = Z35 total matches Y35 (last year) | C46: ="Z35 ("&TEXT(Z35,"$#,##0")&") = Y35 ("&TEXT(Y35,"$#,##0")&") → Diff: "&TEXT(ABS(Z35-Y35),"$#,##0.00") -> Z35 (-$660,504) = Y35 (-$660,504) → Diff: $0.00 | D46: =Y35 -> -660504.36 | E46: =Z35 -> -660504.36 | F46: =ABS(E46-D46) -> 0 | G46: =IF(F46<0.01,"✅ PASS","❌ FAIL") -> ✅ PASS
A47: 5 | B47: Cumulative PV final = Sum of all PV cash flows | C47: ="Y38 ("&TEXT(Y38,"$#,##0")&") = SUM(D37:Y37) → Z37 ("&TEXT(Z37,"$#,##0")&") → Diff: "&TEXT(ABS(Y38-Z37),"$#,##0.00") -> Y38 (-$348,503) = SUM(D37:Y37) → Z37 (-$348,503) → Diff: $0.00 | D47: =Z37 -> -348503.21 | E47: =Y38 -> -348503.21 | F47: =ABS(E47-D47) -> 0 | G47: =IF(F47<0.01,"✅ PASS","❌ FAIL") -> ✅ PASS
A48: 6 | B48: Investment Return = 0 in Year 0 (no prior balance) | C48: ="D30 = "&TEXT(D9,"$#,##0.00")&" (Year 0 has no prior balance to earn/charge return on)" -> D30 = $0.00 (Year 0 has no prior balance to earn/charge return on) | D48: 0 | E48: =D9 -> 0 | F48: =ABS(E48-D48) -> 0 | G48: =IF(F48<0.01,"✅ PASS","❌ FAIL") -> ✅ PASS
A49: 7 | B49: Debt Interest = 0 when Fund Balance ≥ 0 (no debt = no cost) | C49: {="Sum of Debt Int where Balance≥0 = "&TEXT(SUMPRODUCT((D35:Y35>=0)*D39:Y39),"$#,##0.00")&" ("&TEXT(COUNTIF(D35:Y35,">=0"),"0")&" positive years, all with $0 interest)"} -> Sum of Debt Int where Balance≥0 = $0.00 (7 positive years, all with $0 interest) | D49: 0 | E49: {=SUMPRODUCT((D35:Y35>=0)*D39:Y39)} -> 0 | F49: =ABS(E49-D49) -> 0 | G49: =IF(F49<0.01,"✅ PASS","❌ FAIL") -> ✅ PASS
A50: 8 | B50: Borrowing rate applied only when balance < 0 | C50: ="Years with balance<0: "&TEXT(COUNTIF(D35:X35,"<0"),"0")&" → All use rate=Balance×B105 ("&TEXT('① Assumptions'!B105,"0.000%")&"). Mismatches: "&TEXT(E50,"0") -> Years with balance<0: 14 → All use rate=Balance×B105 (4.388%). Mismatches: 0 | D50: 0 | E50: {=SUMPRODUCT((D35:X35<0)*(ROUND(E9:Y9-D35:X35*'① Assumptions'!$B$105,2)<>0))} -> 0 | F50: =ABS(E50-D50) -> 0 | G50: =IF(F50<0.01,"✅ PASS","❌ FAIL") -> ✅ PASS
A51: 9 | B51: Investment rate applied only when balance ≥ 0 | C51: ="Years with balance≥0: "&TEXT(COUNTIF(D35:X35,">=0"),"0")&" → All use rate=Balance×B97 ("&TEXT('① Assumptions'!B97,"0.000%")&"). Mismatches: "&TEXT(E51,"0") -> Years with balance≥0: 7 → All use rate=Balance×B97 (4.050%). Mismatches: 0 | D51: 0 | E51: {=SUMPRODUCT((D35:X35>=0)*(ROUND(E9:Y9-D35:X35*'① Assumptions'!$B$97,2)<>0))} -> 0 | F51: =ABS(E51-D51) -> 0 | G51: =IF(F51<0.01,"✅ PASS","❌ FAIL") -> ✅ PASS
A52: 10 | B52: Total Costs = Sum of all individual cost categories | C52: ="SUM(Z7:Z25) = "&TEXT(SUM(Z12:Z30),"$#,##0")&" vs Z26 = "&TEXT(Z31,"$#,##0")&" → Diff: "&TEXT(ABS(SUM(Z12:Z30)-Z31),"$#,##0.00") -> SUM(Z7:Z25) = $1,233,063 vs Z26 = $1,233,063 → Diff: $0.00 | D52: =SUM(Z12:Z30) -> 1233062.9 | E52: =Z31 -> 1233062.9 | F52: =ABS(E52-D52) -> 2.3283064e-10 | G52: =IF(F52<0.01,"✅ PASS","❌ FAIL") -> ✅ PASS
A53: 11 | B53: Total Income = Benefits + Contributions + Inv. Return | C53: ="Z28 ("&TEXT(Z7,"$#,##0")&") + Z29 ("&TEXT(Z8,"$#,##0")&") + Z30 ("&TEXT(Z9,"$#,##0")&") = "&TEXT(Z7+Z8+Z9,"$#,##0")&" vs Z31 ("&TEXT(Z10,"$#,##0")&")" -> Z28 ($296,693) + Z29 ($437,947) + Z30 (-$162,081) = $572,559 vs Z31 ($572,559) | D53: =Z7+Z8+Z9 -> 572558.52 | E53: =Z10 -> 572558.52 | F53: =ABS(E53-D53) -> 1.1641532e-10 | G53: =IF(F53<0.01,"✅ PASS","❌ FAIL") -> ✅ PASS
A54: 12 | B54: Year count = 22 years (Year 0 to Year 21) | C54: ="COUNTA(D3:Y3) = "&TEXT(COUNTA(D3:Y3),"0")&" years (D3=Year "&TEXT(D3,"0")&" through Y3=Year "&TEXT(Y3,"0")&")" -> COUNTA(D3:Y3) = 22 years (D3=Year 0 through Y3=Year 21) | D54: 22 | E54: =COUNTA(D3:Y3) -> 22 | F54: =ABS(E54-D54) -> 0 | G54: =IF(F54<0.01,"✅ PASS","❌ FAIL") -> ✅ PASS
A56: ✔ ASSUMPTION CROSS-REFERENCES
A57: # | B57: Assumption Parameter | C57: Proof (Formula Link) | D57: Assumptions Tab | E57: Used In Timeline | F57: Match? | G57: Status
A58: 13 | B58: Effective Investment Return Rate | C58: ="Assumptions!B97 ("&TEXT('① Assumptions'!B97,"0.000%")&") vs E30/D35 = "&TEXT(E9,"$#,##0")&" / "&TEXT(D35,"$#,##0")&" = "&TEXT(E9/D35,"0.000%") -> Assumptions!B97 (4.050%) vs E30/D35 = $2,121 / $52,369 = 4.050% | D58: ='① Assumptions'!B97 -> 0.0405 | E58: =IF(D35>=0,E9/D35,"N/A") -> 0.0405 | F58: =IF(E58="N/A","N/A",ABS(E58-D58)<0.0001) -> TRUE | G58: =IF(OR(F58=TRUE,F58="N/A"),"✅ PASS","❌ FAIL") -> ✅ PASS
A59: 14 | B59: Effective Borrowing Rate (After Tax) | C59: ="Assumptions!B105 ("&TEXT('① Assumptions'!B105,"0.000%")&") vs investment return check on negative balance year" -> Assumptions!B105 (4.388%) vs investment return check on negative balance year | D59: ='① Assumptions'!B105 -> 0.043875 | E59: N/A | F59: N/A | G59: =IF(OR(F59=TRUE,F59="N/A"),"✅ PASS","❌ FAIL") -> ✅ PASS
A60: 15 | B60: Risk-Free Rate (PV Discounting) | C60: ="Assumptions!B103 ("&TEXT('① Assumptions'!B103,"0.000%")&") → PV test: D33 ("&TEXT(D33,"$#,##0")&") / (1+4.25%)^0 = D37 ("&TEXT(D37,"$#,##0")&") ✓" -> Assumptions!B103 (4.250%) → PV test: D33 ($52,369) / (1+4.25%)^0 = D37 ($52,369) ✓ | D60: ='① Assumptions'!B103 -> 0.0425 | E60: ='① Assumptions'!B103 -> 0.0425 | F60: =IF(E60="N/A","N/A",ABS(E60-D60)<0.0001) -> TRUE | G60: =IF(OR(F60=TRUE,F60="N/A"),"✅ PASS","❌ FAIL") -> ✅ PASS
A61: 16 | B61: CPI Inflation Rate | C61: ="Assumptions!B7 ("&TEXT('① Assumptions'!B7,"0.00%")&") vs E23/D23−1 = "&TEXT(E28,"$#,##0")&" / "&TEXT(D28,"$#,##0")&" − 1 = "&TEXT(E28/D28-1,"0.00%") -> Assumptions!B7 (3.00%) vs E23/D23−1 = $1,545 / $1,500 − 1 = 3.00% | D61: ='① Assumptions'!B7 -> 0.03 | E61: =IF(D28>0,E28/D28-1,"N/A") -> 0.03 | F61: =IF(E61="N/A","N/A",ABS(E61-D61)<0.0001) -> TRUE | G61: =IF(OR(F61=TRUE,F61="N/A"),"✅ PASS","❌ FAIL") -> ✅ PASS
A62: 17 | B62: Health Insurance Inflation Rate | C62: ="Assumptions!B48 ("&TEXT('① Assumptions'!B48,"0.00%")&") vs E14/D14−1 = "&TEXT(E19,"$#,##0")&" / "&TEXT(D19,"$#,##0")&" − 1 = "&TEXT(E19/D19-1,"0.00%") -> Assumptions!B48 (6.00%) vs E14/D14−1 = $4,770 / $4,500 − 1 = 6.00% | D62: ='① Assumptions'!B48 -> 0.06 | E62: =IF(D19>0,E19/D19-1,"N/A") -> 0.06 | F62: =IF(E62="N/A","N/A",ABS(E62-D62)<0.0001) -> TRUE | G62: =IF(OR(F62=TRUE,F62="N/A"),"✅ PASS","❌ FAIL") -> ✅ PASS
A63: 18 | B63: Contingency % applied to total costs | C63: ="Assumptions!B98 ("&TEXT('① Assumptions'!B98,"0.0%")&") vs D25/SUM(D7:D24) = "&TEXT(D30,"$#,##0")&" / "&TEXT(SUM(D12:D29),"$#,##0")&" = "&TEXT(D30/SUM(D12:D29),"0.0%") -> Assumptions!B98 (5.0%) vs D25/SUM(D7:D24) = $1,000 / $20,000 = 5.0% | D63: ='① Assumptions'!B98 -> 0.05 | E63: =IF(SUM(D12:D29)>0,D30/SUM(D12:D29),"N/A") -> 0.05 | F63: =IF(E63="N/A","N/A",ABS(E63-D63)<0.0001) -> TRUE | G63: =IF(OR(F63=TRUE,F63="N/A"),"✅ PASS","❌ FAIL") -> ✅ PASS
A64: 19 | B64: Tax Rate on Investment Returns | C64: ="Assumptions!B96 ("&TEXT('① Assumptions'!B96,"0.0%")&") vs 1−B97/B95 = 1 − "&TEXT('① Assumptions'!B97,"0.000%")&" / "&TEXT('① Assumptions'!B95,"0.00%")&" = "&TEXT(1-'① Assumptions'!B97/'① Assumptions'!B95,"0.0%") -> Assumptions!B96 (32.5%) vs 1−B97/B95 = 1 − 4.050% / 6.00% = 32.5% | D64: ='① Assumptions'!B96 -> 0.325 | E64: =1-'① Assumptions'!B97/'① Assumptions'!B95 -> 0.325 | F64: =ABS(E64-D64)<0.0001 -> TRUE | G64: =IF(F64=TRUE,"✅ PASS","❌ FAIL") -> ✅ PASS
A66: OVERALL MODEL INTEGRITY | B66: OVERALL MODEL INTEGRITY | F66: =IF(COUNTIF(G43:G54,"✅ PASS")+COUNTIF(G58:G64,"✅ PASS")=19,"✅ ALL 19 CHECKS PASSED","❌ "&(19-COUNTIF(G43:G54,"✅ PASS")-COUNTIF(G58:G64,"✅ PASS"))&" CHECK(S) FAILED — REVIEW ABOVE") -> ✅ ALL 19 CHECKS PASSED | G66: =IF(F66="✅ ALL 19 CHECKS PASSED","✅ ALL 19 CHECKS PASSED","❌ "&(19-COUNTIF(G43:G54,"✅ PASS")-COUNTIF(G58:G64,"✅ PASS"))&" CHECK(S) FAILED") -> ✅ ALL 19 CHECKS PASSED

Sheet ⑤ School Fees
A1: SCHOOL FEE REFERENCE DATA
A2: 📖 Reference data — do not edit. Change your selections on ① Assumptions tab.
A4: VICTORIAN PRIVATE SCHOOLS
A5: School Name | B5: Primary (Prep–Yr6) | C5: Secondary (Yr7–12) | D5: Yr 12 Fee (2025) | E5: Type | F5: Location
A6: Geelong Grammar School | B6: 38000 | C6: 52612 | D6: 52612 | E6: Co-ed | F6: Geelong
A7: Wesley College | B7: 34000 | C7: 47574 | D7: 47574 | E7: Co-ed | F7: Melbourne
A8: St Catherine's School | B8: 33000 | C8: 47120 | D8: 47120 | E8: Girls | F8: Melbourne
A9: Melbourne Grammar School | B9: 33000 | C9: 45000 | D9: 45000 | E9: Boys | F9: Melbourne
A10: Melbourne Girls Grammar | B10: 32000 | C10: 44000 | D10: 44000 | E10: Girls | F10: Melbourne
A11: Lauriston Girls' School | B11: 31000 | C11: 42600 | D11: 42600 | E11: Girls | F11: Melbourne
A12: Scotch College | B12: 31000 | C12: 42000 | D12: 42000 | E12: Boys | F12: Melbourne
A13: Haileybury | B13: 28000 | C13: 40000 | D13: 40000 | E13: Co-ed | F13: Melbourne
A14: Camberwell Grammar School | B14: 27000 | C14: 38000 | D14: 38000 | E14: Boys | F14: Melbourne
A15: St Kevin's College | B15: 25000 | C15: 36000 | D15: 36000 | E15: Boys | F15: Melbourne
A17: PUBLIC SCHOOL ESTIMATE (VIC & NSW)
A18: Voluntary Contributions + Materials | B18: 500 | C18: 800 | E18: Primary / Secondary
A20: NSW PRIVATE SCHOOLS
A21: School Name | B21: Primary (K–Yr6) | C21: Secondary (Yr7–12) | D21: Yr 12 Fee (2025) | E21: Type | F21: Location
A22: Sydney Grammar School | B22: 38000 | C22: 52410 | D22: 52410 | E22: Boys | F22: Sydney
A23: Kambala | B23: 36000 | C23: 51703 | D23: 51703 | E23: Girls | F23: Sydney
A24: The Scots College | B24: 36000 | C24: 51258 | D24: 51258 | E24: Boys | F24: Sydney
A25: SCEGGS Darlinghurst | B25: 35000 | C25: 49936 | D25: 49936 | E25: Girls | F25: Sydney
A26: The King's School | B26: 34000 | C26: 47000 | D26: 47000 | E26: Boys | F26: Parramatta
A27: Cranbrook School | B27: 33000 | C27: 46000 | D27: 46000 | E27: Boys | F27: Sydney
A28: Pymble Ladies' College | B28: 32000 | C28: 44000 | D28: 44000 | E28: Girls | F28: Sydney
A29: Knox Grammar School | B29: 30000 | C29: 42000 | D29: 42000 | E29: Boys | F29: Sydney
A30: Shore School | B30: 29000 | C30: 40000 | D30: 40000 | E30: Co-ed | F30: Sydney
A31: Loreto Kirribilli | B31: 27000 | C31: 38000 | D31: 38000 | E31: Girls | F31: Sydney

Sheet ⑥ University
A1: UNIVERSITY REFERENCE DATA
A2: 📖 Reference data — do not edit. Change your selections on ① Assumptions tab.
A4: DOMESTIC (HECS-HELP) BANDS
A5: Band | B5: Annual Fee | C5: Disciplines
A6: Band 1 | B6: 4529 | C6: Education, Nursing, Clinical Psychology, Languages
A7: Band 2 | B7: 8021 | C7: Agriculture, Maths, Statistics, Science, Health, Engineering, IT, Architecture
A8: Band 3 | B8: 11800 | C8: Humanities, Behavioural Science, Social Studies, Communications
A9: Band 4 | B9: 16528 | C9: Law, Accounting, Commerce, Economics, Administration
A11: INTERNATIONAL FEES (INDICATIVE)
A12: Discipline | B12: Annual Fee | C12: Notes
A13: Arts / Humanities | B13: 25000 | C13: Range $20k–$35k
A14: Business / Commerce | B14: 38000 | C14: Range $30k–$45k
A15: Engineering / Science | B15: 42000 | C15: Range $35k–$50k
A16: Medicine / Dentistry | B16: 50000 | C16: Range $45k–$75k (longer degree)
A18: LIVING COSTS (IF AWAY FROM HOME)
A19: Item | B19: Annual Cost | C19: Notes
A20: Rent (shared accommodation) | B20: 14000 | C20: $250–$350/week
A21: Food & Groceries | B21: 5200 | C21: ~$100/week
A22: Utilities & Internet | B22: 1800 | C22: ~$150/month
A23: Transport | B23: 1500 | C23: Concession card
A24: Total Annual Living Cost | B24: =SUM(B20:B23) -> 22500 | C24: Used in Timeline if 'Away'

Sheet ⑦ Extra-Curriculars
A1: EXTRA-CURRICULAR ACTIVITIES REFERENCE
A2: 📖 Reference data — do not edit. Change your selections on ① Assumptions tab.
A4: COST GUIDE BY AGE BRACKET
A5: Category | B5: Ages 3–6 | C5: Ages 7–12 | D5: Ages 13–18 | E5: Notes
A6: Sports (club reg, equipment) | B6: 800 | C6: 2000 | D6: 3500 | E6: Equipment costs increase with age
A7: Music / Arts (lessons) | B7: 1500 | C7: 2500 | D7: 4000 | E7: Instrument purchase extra $500–$5,000
A8: Tutoring | B8: - | C8: 2500 | D8: 5000 | E8: $50–$100/hr; 1–2x/week
A9: Technology (coding, robotics) | B9: - | C9: 1200 | D9: 1800 | E9: Term-based programs
A10: Camps / Holiday Programs | B10: 1000 | C10: 1500 | D10: 3000 | E10: School holiday care + adventure camps
A11: Swimming Lessons | B11: 1200 | C11: 1000 | D11: - | E11: ~$25–$30/lesson, weekly
A13: Note: Costs in Assumptions tab override these reference figures.
A14: These serve as guidance when selecting annual cost inputs.

Sheet ⑧ Govt Benefits
A1: GOVERNMENT BENEFITS REFERENCE
A2: 📖 Reference data — do not edit. Change your selections on ① Assumptions tab.
A4: FAMILY TAX BENEFIT PART A
A5: Component | B5: Rate | C5: Notes
A6: Max rate (0–12 years) | B6: ~$227.08/fortnight | C6: ~$5,903/year per child
A7: Max rate (13–19 years) | B7: ~$276.42/fortnight | C7: ~$7,187/year per child
A8: End-of-year supplement | B8: Up to $916.15/child | C8: Paid after tax return lodged
A9: Income free area
A10: Reduction rate | B10: 20c per $1 over threshold | C10: Between lower & upper thresholds
A12: FAMILY TAX BENEFIT PART B
A13: Max rate (youngest <5) | B13: ~$188.86/fortnight | C13: ~$4,911/year
A14: Max rate (youngest 5–18) | B14: ~$131.74/fortnight | C14: ~$3,425/year
A15: Primary earner income limit
A16: End-of-year supplement | B16: Up to $430.70 | C16: Paid after tax return lodged
A18: CHILD CARE SUBSIDY (CCS)
A19: Family Income
A20: Up to ~$83,280 | B20: 0.9 | C20: Maximum subsidy
A21: $83,280 – $533,280 | B21: 90%–0% | C21: Tapers down gradually
A22: Over $533,280 | B22: 0 | C22: No subsidy
A24: Note: CCS rebate % is manually entered in Assumptions tab (Section 3).

Sheet Model Test
A1: MODEL VALIDATION & TEST SUITE
A2: Automated formula-by-formula verification of the Timeline Model against Assumptions inputs
A4: TEST SCOREBOARD
A5: Total Tests | B5: =COUNTIF(F:F,"✅ PASS")+COUNTIF(F:F,"❌ FAIL") -> 8 | D5: Tests Passed | E5: =COUNTIF(F:F,"✅ PASS") -> 7 | G5: Pass Rate | H5: =IF(B5>0,E5/B5,0) -> 0.875
A6: Tests Failed | B6: =COUNTIF(F:F,"❌ FAIL") -> 1 | D6: Warnings | E6: =COUNTIF(F:F,"⚠️ CHECK") -> 0 | G6: Model Status | H6: =IF(B6=0,"✅ ALL TESTS PASS","❌ "&B6&" FAILURES") -> ❌ 1 FAILURES
A8: CURRENT ASSUMPTIONS SNAPSHOT
A9: Birth Year | B9: ='① Assumptions'!B5 -> 2024 | D9: School | E9: ='① Assumptions'!B13 -> Haileybury | G9: Monthly Contrib | H9: ='① Assumptions'!B91 -> 1000
A10: State | B10: ='① Assumptions'!B6 -> VIC | D10: Entry Grade | E10: ='① Assumptions'!B12 -> 5 | G10: Lump Sum | H10: ='① Assumptions'!B90 -> 50000
A11: CPI | B11: ='① Assumptions'!B7 -> 0.03 | D11: Edu Inflation | E11: ='① Assumptions'!B8 -> 0.05 | G11: Return Rate | H11: ='① Assumptions'!B95 -> 0.06
A13: TEST 1: CHILDCARE (Column D)
A14: Test | B14: Year | C14: Age | D14: Timeline Value | E14: Expected Value | F14: Result | G14: Formula Logic | H14: Tolerance
A15: CC-1: Age 0 = $0 (before start) | B15: 0 | C15: 0 | D15: =#REF! -> #REF! | E15: 0 | F15: =IF(ABS(D15-E15)<0.01,"✅ PASS","❌ FAIL") -> #REF! | G15: Age 0 < Start Age 1 → $0 | H15: 0.01
A16: CC-2: Age 1 = Net×CPI^1 | B16: 1 | C16: 1 | D16: =#REF! -> #REF! | E16: ='① Assumptions'!B26*(1+'① Assumptions'!B7)^1 -> 2898.3073 | F16: =IF(ABS(D16-E16)<0.01,"✅ PASS","❌ FAIL") -> #REF! | G16: 7030.4 × 1.03^1 = 7241.31 | H16: 0.01
A17: CC-3: Age 2 = Net×CPI^2 | B17: 2 | C17: 2 | D17: =#REF! -> #REF! | E17: ='① Assumptions'!B26*(1+'① Assumptions'!B7)^2 -> 2985.2565 | F17: =IF(ABS(D17-E17)<0.01,"✅ PASS","❌ FAIL") -> #REF! | G17: 7030.4 × 1.03^2 | H17: 0.01
A18: CC-4: Age 4 = Net×CPI^4 (last yr) | B18: 4 | C18: 4 | D18: =#REF! -> #REF! | E18: ='① Assumptions'!B26*(1+'① Assumptions'!B7)^4 -> 3167.0586 | F18: =IF(ABS(D18-E18)<0.01,"✅ PASS","❌ FAIL") -> #REF! | G18: Last childcare year | H18: 0.01
A19: CC-5: Age 5 = $0 (after end) | B19: 5 | C19: 5 | D19: =#REF! -> #REF! | E19: 0 | F19: =IF(ABS(D19-E19)<0.01,"✅ PASS","❌ FAIL") -> #REF! | G19: Age 5 > End Age 4 → $0 | H19: 0.01
A20: CC-6: Net cost formula | B20: — | C20: — | D20: ='① Assumptions'!B26 -> 2813.8906 | E20: ='① Assumptions'!B25*(1-'① Assumptions'!B22) -> 2813.8906 | F20: =IF(ABS(D20-E20)<0.01,"✅ PASS","❌ FAIL") -> ✅ PASS | G20: Gross × (1 − CCS%) = Net | H20: 0.01
A21: CC-7: Gross cost formula | B21: — | C21: — | D21: ='① Assumptions'!B25 -> 16224 | E21: ='① Assumptions'!B20*'① Assumptions'!B21*52 -> 17576 | F21: =IF(ABS(D21-E21)<0.01,"✅ PASS","❌ FAIL") -> ❌ FAIL | G21: DailyRate × Days/wk × 52 | H21: 0.01
A23: TEST 2: BEFORE/AFTER SCHOOL CARE (Column E)
A24: Test | B24: Year | C24: Age | D24: Timeline Value | E24: Expected Value | F24: Result | G24: Formula Logic | H24: Tolerance
A25: BAC-1: Age 4 = $0 (before start) | B25: 4 | C25: 4 | D25: =#REF! -> #REF! | E25: 0 | F25: =IF(ABS(D25-E25)<0.01,"✅ PASS","❌ FAIL") -> #REF! | G25: Age 4 < 5 → $0 | H25: 0.01
A26: BAC-2: Age 5 = $12k×CPI^5 | B26: 5 | C26: 5 | D26: =#REF! -> #REF! | E26: ='① Assumptions'!B33*(1+'① Assumptions'!B7)^5 -> 13911.289 | F26: =IF(ABS(D26-E26)<0.01,"✅ PASS","❌ FAIL") -> #REF! | G26: 12000 × 1.03^5 | H26: 0.01
A27: BAC-3: Age 12 = $12k×CPI^12 (last yr) | B27: 12 | C27: 12 | D27: =#REF! -> #REF! | E27: ='① Assumptions'!B33*(1+'① Assumptions'!B7)^12 -> 17109.131 | F27: =IF(ABS(D27-E27)<0.01,"✅ PASS","❌ FAIL") -> #REF! | G27: 12000 × 1.03^12 | H27: 0.01
A28: BAC-4: Age 13 = $0 (after end) | B28: 13 | C28: 13 | D28: =#REF! -> #REF! | E28: 0 | F28: =IF(ABS(D28-E28)<0.01,"✅ PASS","❌ FAIL") -> #REF! | G28: Age 13 > 12 → $0 | H28: 0.01
A29: BAC-5: Annual cost formula | B29: — | C29: — | D29: ='① Assumptions'!B33 -> 12000 | E29: ='① Assumptions'!B30*'① Assumptions'!B31*'① Assumptions'!B32*40 -> 12000 | F29: =IF(ABS(D29-E29)<0.01,"✅ PASS","❌ FAIL") -> ✅ PASS | G29: Rate×Days×Sessions×40wks | H29: 0.01
A30: BAC-6: Total 21yr | B30: — | C30: — | D30: =#REF! -> #REF! | E30: =SUM(#REF!) -> #REF! | F30: =IF(ABS(D30-E30)<0.01,"✅ PASS","❌ FAIL") -> #REF! | G30: SUM matches TOTALS row | H30: 0.01
A32: TEST 3: SCHOOL FEES (Column F) — CRITICAL
A33: Test | B33: Year | C33: Age | D33: Timeline Value | E33: Expected Value | F33: Result | G33: Formula Logic | H33: Tolerance
A34: SF-1: Age 4 = $0 (pre-school) | B34: 4 | C34: 4 | D34: =#REF! -> #REF! | E34: 0 | F34: =IF(ABS(D34-E34)<0.01,"✅ PASS","❌ FAIL") -> #REF! | G34: Age 4 < 5 → no school | H34: 0.01
A35: SF-2: Age 5 = Public Primary×EI^5 | B35: 5 | C35: 5 | D35: =#REF! -> #REF! | E35: ='⑤ School Fees'!B18*(1+'① Assumptions'!B8)^5 -> 638.14078 | F35: =IF(ABS(D35-E35)<0.01,"✅ PASS","❌ FAIL") -> #REF! | G35: Before Grade 5 → Public $500 | H35: 0.01
A36: SF-3: Age 9 = Public Primary×EI^9 | B36: 9 | C36: 9 | D36: =#REF! -> #REF! | E36: ='⑤ School Fees'!B18*(1+'① Assumptions'!B8)^9 -> 775.66411 | F36: =IF(ABS(D36-E36)<0.01,"✅ PASS","❌ FAIL") -> #REF! | G36: Last year before Grade 5 entry | H36: 0.01
A37: SF-4: Age 10 = Haileybury Pri×EI^10 | B37: 10 | C37: 10 | D37: =#REF! -> #REF! | E37: =VLOOKUP('① Assumptions'!B13,'⑤ School Fees'!A6:C15,2,FALSE)*(1+'① Assumptions'!B8)^10 -> 45609.05 | F37: =IF(ABS(D37-E37)<0.01,"✅ PASS","❌ FAIL") -> #REF! | G37: Grade 5 entry → Haileybury $28k | H37: 0.01
A38: SF-5: Age 11 = Haileybury Pri×EI^11 | B38: 11 | C38: 11 | D38: =#REF! -> #REF! | E38: =VLOOKUP('① Assumptions'!B13,'⑤ School Fees'!A6:C15,2,FALSE)*(1+'① Assumptions'!B8)^11 -> 47889.502 | F38: =IF(ABS(D38-E38)<0.01,"✅ PASS","❌ FAIL") -> #REF! | G38: Last year Primary (age ≤11) | H38: 0.01
A39: SF-6: Age 12 = Haileybury Sec×EI^12 | B39: 12 | C39: 12 | D39: =#REF! -> #REF! | E39: =VLOOKUP('① Assumptions'!B13,'⑤ School Fees'!A6:C15,3,FALSE)*(1+'① Assumptions'!B8)^12 -> 71834.253 | F39: =IF(ABS(D39-E39)<0.01,"✅ PASS","❌ FAIL") -> #REF! | G39: Year 7 → Secondary $40k | H39: 0.01
A40: SF-7: Age 17 = Haileybury Sec×EI^17 | B40: 17 | C40: 17 | D40: =#REF! -> #REF! | E40: =VLOOKUP('① Assumptions'!B13,'⑤ School Fees'!A6:C15,3,FALSE)*(1+'① Assumptions'!B8)^17 -> 91680.733 | F40: =IF(ABS(D40-E40)<0.01,"✅ PASS","❌ FAIL") -> #REF! | G40: Year 12 (last school year) | H40: 0.01
A41: SF-8: Age 18 = $0 (school over) | B41: 18 | C41: 18 | D41: =#REF! -> #REF! | E41: 0 | F41: =IF(ABS(D41-E41)<0.01,"✅ PASS","❌ FAIL") -> #REF! | G41: Age 18 > 17 → $0 | H41: 0.01
A42: SF-9: VLOOKUP returns correct fee | B42: — | C42: — | D42: =VLOOKUP('① Assumptions'!B13,'⑤ School Fees'!A6:C15,2,FALSE) -> 28000 | E42: 28000 | F42: =IF(ABS(D42-E42)<0.01,"✅ PASS","❌ FAIL") -> ✅ PASS | G42: Haileybury Primary = $28,000 | H42: 0.01
A43: SF-10: VLOOKUP Secondary fee | B43: — | C43: — | D43: =VLOOKUP('① Assumptions'!B13,'⑤ School Fees'!A6:C15,3,FALSE) -> 40000 | E43: 40000 | F43: =IF(ABS(D43-E43)<0.01,"✅ PASS","❌ FAIL") -> ✅ PASS | G43: Haileybury Secondary = $40,000 | H43: 0.01
A44: SF-11: Total School Fees | B44: — | C44: — | D44: =#REF! -> #REF! | E44: =SUM(#REF!) -> #REF! | F44: =IF(ABS(D44-E44)<0.01,"✅ PASS","❌ FAIL") -> #REF! | G44: SUM matches TOTALS row | H44: 0.01
A46: TEST 4: UNIFORMS, CAMPS & EXTRA-CURRICULARS (Columns G, H, I)
A47: Test | B47: Year | C47: Age | D47: Timeline Value | E47: Expected Value | F47: Result | G47: Formula Logic | H47: Tolerance
A48: UNI-1: Uniform Age 4 = $0 | B48: 4 | C48: 4 | D48: =#REF! -> #REF! | E48: 0 | F48: =IF(ABS(D48-E48)<0.01,"✅ PASS","❌ FAIL") -> #REF! | G48: Age < 5 → $0 | H48: 0.01
A49: UNI-2: Uniform Age 5 = $1500×CPI^5 | B49: 5 | C49: 5 | D49: =#REF! -> #REF! | E49: ='① Assumptions'!B85*(1+'① Assumptions'!B7)^5 -> 1738.9111 | F49: =IF(ABS(D49-E49)<0.01,"✅ PASS","❌ FAIL") -> #REF! | G49: 1500 × 1.03^5 | H49: 0.01
A50: UNI-3: Uniform Age 17 = $1500×CPI^17 | B50: 17 | C50: 17 | D50: =#REF! -> #REF! | E50: ='① Assumptions'!B85*(1+'① Assumptions'!B7)^17 -> 2479.2714 | F50: =IF(ABS(D50-E50)<0.01,"✅ PASS","❌ FAIL") -> #REF! | G50: Last school year | H50: 0.01
A51: UNI-4: Uniform Age 18 = $0 | B51: 18 | C51: 18 | D51: =#REF! -> #REF! | E51: 0 | F51: =IF(ABS(D51-E51)<0.01,"✅ PASS","❌ FAIL") -> #REF! | G51: Age > 17 → $0 | H51: 0.01
A52: CMP-1: Camp Age 5 = $1000×CPI^5 | B52: 5 | C52: 5 | D52: =#REF! -> #REF! | E52: ='① Assumptions'!B86*(1+'① Assumptions'!B7)^5 -> 1159.2741 | F52: =IF(ABS(D52-E52)<0.01,"✅ PASS","❌ FAIL") -> #REF! | G52: 1000 × 1.03^5 | H52: 0.01
A53: CMP-2: Camp Age 17 = $1000×CPI^17 | B53: 17 | C53: 17 | D53: =#REF! -> #REF! | E53: ='① Assumptions'!B86*(1+'① Assumptions'!B7)^17 -> 1652.8476 | F53: =IF(ABS(D53-E53)<0.01,"✅ PASS","❌ FAIL") -> #REF! | G53: 1000 × 1.03^17 | H53: 0.01
A54: EC-1: Age 3 = Swimming only | B54: 3 | C54: 3 | D54: =#REF! -> #REF! | E54: =1200*(1+'① Assumptions'!B7)^3 -> 1311.2724 | F54: =IF(ABS(D54-E54)<0.01,"✅ PASS","❌ FAIL") -> #REF! | G54: Only Swimming active at age 3 | H54: 0.01
A55: EC-2: Age 5 = Sports+Camps+Swim | B55: 5 | C55: 5 | D55: =#REF! -> #REF! | E55: =(2500+2000+1200)*(1+'① Assumptions'!B7)^5 -> 6607.8622 | F55: =IF(ABS(D55-E55)<0.01,"✅ PASS","❌ FAIL") -> #REF! | G55: Sports+Camps+Swimming | H55: 0.01
A56: EC-3: Age 10 = Sports+Music+Tutor+Camps | B56: 10 | C56: 10 | D56: =#REF! -> #REF! | E56: =(2500+3000+4000+2000+1200)*(1+'① Assumptions'!B7)^10 -> 17067.738 | F56: =IF(ABS(D56-E56)<0.01,"✅ PASS","❌ FAIL") -> #REF! | G56: All 5 active ECs at age 10 | H56: 0.01
A57: EC-4: Age 18 = Sports+Music+Tutor | B57: 18 | C57: 18 | D57: =#REF! -> #REF! | E57: =(2500+3000+4000)*(1+'① Assumptions'!B7)^18 -> 16173.114 | F57: =IF(ABS(D57-E57)<0.01,"✅ PASS","❌ FAIL") -> #REF! | G57: Sports+Music+Tutoring (ends 18) | H57: 0.01
A59: TEST 5: TECHNOLOGY, HEALTH, ORTHODONTICS & ALLIED HEALTH (Columns J, K, L, M)
A60: Test | B60: Year | C60: Age | D60: Timeline Value | E60: Expected Value | F60: Result | G60: Formula Logic | H60: Tolerance
A61: TECH-1: Age 9 = $0 (before laptop) | B61: 9 | C61: 9 | D61: =#REF! -> #REF! | E61: 0 | F61: =IF(ABS(D61-E61)<0.01,"✅ PASS","❌ FAIL") -> #REF! | G61: Age 9 < laptop start 10 | H61: 0.01
A62: TECH-2: Age 10 = Laptop $2k×CPI^10 | B62: 10 | C62: 10 | D62: =#REF! -> #REF! | E62: ='① Assumptions'!B67*(1+'① Assumptions'!B7)^10 -> 2687.8328 | F62: =IF(ABS(D62-E62)<0.01,"✅ PASS","❌ FAIL") -> #REF! | G62: First laptop at age 10 | H62: 0.01
A63: TECH-3: Age 12 = Phone $1200×CPI^12 | B63: 12 | C63: 12 | D63: =#REF! -> #REF! | E63: ='① Assumptions'!B71*(1+'① Assumptions'!B7)^12 -> 1710.9131 | F63: =IF(ABS(D63-E63)<0.01,"✅ PASS","❌ FAIL") -> #REF! | G63: First phone at age 12 | H63: 0.01
A64: TECH-4: Age 13 = Laptop (cycle) | B64: 13 | C64: 13 | D64: =#REF! -> #REF! | E64: ='① Assumptions'!B67*(1+'① Assumptions'!B7)^13 -> 2937.0674 | F64: =IF(ABS(D64-E64)<0.01,"✅ PASS","❌ FAIL") -> #REF! | G64: Laptop every 3yr: 10,13,16,19 | H64: 0.01
A65: TECH-5: Age 11 = $0 (no cycle hit) | B65: 11 | C65: 11 | D65: =#REF! -> #REF! | E65: 0 | F65: =IF(ABS(D65-E65)<0.01,"✅ PASS","❌ FAIL") -> #REF! | G65: Age 11: (11-10)%3≠0 → $0 | H65: 0.01
A66: HI-1: Health Ins Age 0 = $4500 | B66: 0 | C66: 0 | D66: =#REF! -> #REF! | E66: ='① Assumptions'!B47*(1+'① Assumptions'!B7)^0 -> 4500 | F66: =IF(ABS(D66-E66)<0.01,"✅ PASS","❌ FAIL") -> #REF! | G66: 4500 × 1.03^0 = 4500 | H66: 0.01
A67: HI-2: Health Ins Age 21 = $4500×CPI^21 | B67: 21 | C67: 21 | D67: =#REF! -> #REF! | E67: ='① Assumptions'!B47*(1+'① Assumptions'!B7)^21 -> 8371.3256 | F67: =IF(ABS(D67-E67)<0.01,"✅ PASS","❌ FAIL") -> #REF! | G67: 4500 × 1.03^21 | H67: 0.01
A68: ORT-1: Ortho Age 11 = $0 | B68: 11 | C68: 11 | D68: =#REF! -> #REF! | E68: 0 | F68: =IF(ABS(D68-E68)<0.01,"✅ PASS","❌ FAIL") -> #REF! | G68: Age 11 < start age 12 | H68: 0.01
A69: ORT-2: Ortho Age 12 = (7000/2)×CPI^12 | B69: 12 | C69: 12 | D69: =#REF! -> #REF! | E69: =('① Assumptions'!B50/'① Assumptions'!B52)*(1+'① Assumptions'!B7)^12 -> 4990.1631 | F69: =IF(ABS(D69-E69)<0.01,"✅ PASS","❌ FAIL") -> #REF! | G69: 7000/2 = 3500/yr × 1.03^12 | H69: 0.01
A70: ORT-3: Ortho Age 14 = $0 (done) | B70: 14 | C70: 14 | D70: =#REF! -> #REF! | E70: 0 | F70: =IF(ABS(D70-E70)<0.01,"✅ PASS","❌ FAIL") -> #REF! | G70: Age 14 ≥ 12+2 → done | H70: 0.01
A71: AH-1: Allied Health Age 3 | B71: 3 | C71: 3 | D71: =#REF! -> #REF! | E71: ='① Assumptions'!B53*(1+'① Assumptions'!B7)^3 -> 2185.454 | F71: =IF(ABS(D71-E71)<0.01,"✅ PASS","❌ FAIL") -> #REF! | G71: 2000 × 1.03^3 (age 3–8) | H71: 0.01
A72: AH-2: Allied Health Age 9 = $0 | B72: 9 | C72: 9 | D72: =#REF! -> #REF! | E72: 0 | F72: =IF(ABS(D72-E72)<0.01,"✅ PASS","❌ FAIL") -> #REF! | G72: Age 9 > end age 8 → $0 | H72: 0.01
A73: AH-3: Allied Health Age 2 = $0 | B73: 2 | C73: 2 | D73: =#REF! -> #REF! | E73: 0 | F73: =IF(ABS(D73-E73)<0.01,"✅ PASS","❌ FAIL") -> #REF! | G73: Age 2 < start age 3 → $0 | H73: 0.01
A75: TEST 6: DRIVING, CAR COSTS & GAP YEAR (Columns N, O, P)
A76: Test | B76: Year | C76: Age | D76: Timeline Value | E76: Expected Value | F76: Result | G76: Formula Logic | H76: Tolerance
A77: DRV-1: Driving Age 15 = $0 | B77: 15 | C77: 15 | D77: =#REF! -> #REF! | E77: 0 | F77: =IF(ABS(D77-E77)<0.01,"✅ PASS","❌ FAIL") -> #REF! | G77: Age 15 ≠ 16 → $0 | H77: 0.01
A78: DRV-2: Driving Age 16 = $1500×CPI^16 | B78: 16 | C78: 16 | D78: =#REF! -> #REF! | E78: ='① Assumptions'!B76*(1+'① Assumptions'!B7)^16 -> 2407.0597 | F78: =IF(ABS(D78-E78)<0.01,"✅ PASS","❌ FAIL") -> #REF! | G78: Lessons at age 16 only | H78: 0.01
A79: DRV-3: Driving Age 17 = $0 | B79: 17 | C79: 17 | D79: =#REF! -> #REF! | E79: 0 | F79: =IF(ABS(D79-E79)<0.01,"✅ PASS","❌ FAIL") -> #REF! | G79: Age 17 ≠ 16 → $0 | H79: 0.01
A80: CAR-1: Car Age 17 = $0 | B80: 17 | C80: 17 | D80: =#REF! -> #REF! | E80: 0 | F80: =IF(ABS(D80-E80)<0.01,"✅ PASS","❌ FAIL") -> #REF! | G80: Age 17 < purchase age 18 | H80: 0.01
A81: CAR-2: Car Age 18 = Purchase+Running | B81: 18 | C81: 18 | D81: =#REF! -> #REF! | E81: =('① Assumptions'!B78+'① Assumptions'!B80)*(1+'① Assumptions'!B7)^18 -> 30643.795 | F81: =IF(ABS(D81-E81)<0.01,"✅ PASS","❌ FAIL") -> #REF! | G81: (15000+3000) × 1.03^18 | H81: 0.01
A82: CAR-3: Car Age 19 = Running only | B82: 19 | C82: 19 | D82: =#REF! -> #REF! | E82: ='① Assumptions'!B80*(1+'① Assumptions'!B7)^19 -> 5260.5182 | F82: =IF(ABS(D82-E82)<0.01,"✅ PASS","❌ FAIL") -> #REF! | G82: 3000 × 1.03^19 (running only) | H82: 0.01
A83: GAP-1: Gap Year all = $0 (disabled) | B83: — | C83: — | D83: =#REF! -> #REF! | E83: 0 | F83: =IF(ABS(D83-E83)<0.01,"✅ PASS","❌ FAIL") -> #REF! | G83: Gap Year = No → all $0 | H83: 0.01
A84: LI-1: Life Insurance Age 0 = $1500 | B84: 0 | C84: 0 | D84: =#REF! -> #REF! | E84: ='① Assumptions'!B102*(1+'① Assumptions'!B7)^0 -> 1500 | F84: =IF(ABS(D84-E84)<0.01,"✅ PASS","❌ FAIL") -> #REF! | G84: 1500 × 1.03^0 = 1500 | H84: 0.01
A85: LI-2: Life Insurance Age 21 | B85: 21 | C85: 21 | D85: =#REF! -> #REF! | E85: ='① Assumptions'!B102*(1+'① Assumptions'!B7)^21 -> 2790.4419 | F85: =IF(ABS(D85-E85)<0.01,"✅ PASS","❌ FAIL") -> #REF! | G85: 1500 × 1.03^21 | H85: 0.01
A87: TEST 7: UNIVERSITY FEES, LIVING COSTS & TEXTBOOKS (Columns Q, R, S)
A88: Test | B88: Year | C88: Age | D88: Timeline Value | E88: Expected Value | F88: Result | G88: Formula Logic | H88: Tolerance
A89: UF-1: Age 17 = $0 (still school) | B89: 17 | C89: 17 | D89: =#REF! -> #REF! | E89: 0 | F89: =IF(ABS(D89-E89)<0.01,"✅ PASS","❌ FAIL") -> #REF! | G89: No gap year → uni at 18 | H89: 0.01
A90: UF-2: Age 18 = Band2×EI^18 | B90: 18 | C90: 18 | D90: =#REF! -> #REF! | E90: ='⑥ University'!B7*(1+'① Assumptions'!B8)^18 -> 19303.493 | F90: =IF(ABS(D90-E90)<0.01,"✅ PASS","❌ FAIL") -> #REF! | G90: Band 2 ($8,021) × 1.05^18 | H90: 0.01
A91: UF-3: Age 19 = Band2×EI^19 | B91: 19 | C91: 19 | D91: =#REF! -> #REF! | E91: ='⑥ University'!B7*(1+'① Assumptions'!B8)^19 -> 20268.668 | F91: =IF(ABS(D91-E91)<0.01,"✅ PASS","❌ FAIL") -> #REF! | G91: Year 2 of 3-year degree | H91: 0.01
A92: UF-4: Age 20 = Band2×EI^20 | B92: 20 | C92: 20 | D92: =#REF! -> #REF! | E92: ='⑥ University'!B7*(1+'① Assumptions'!B8)^20 -> 21282.101 | F92: =IF(ABS(D92-E92)<0.01,"✅ PASS","❌ FAIL") -> #REF! | G92: Year 3 of 3-year degree | H92: 0.01
A93: UF-5: Age 21 = $0 (degree over) | B93: 21 | C93: 21 | D93: =#REF! -> #REF! | E93: 0 | F93: =IF(ABS(D93-E93)<0.01,"✅ PASS","❌ FAIL") -> #REF! | G93: 3-year degree complete | H93: 0.01
A94: UF-6: Band 2 base fee lookup | B94: — | C94: — | D94: ='⑥ University'!B7 -> 8021 | E94: 8021 | F94: =IF(ABS(D94-E94)<0.01,"✅ PASS","❌ FAIL") -> ✅ PASS | G94: Band 2 = $8,021/yr | H94: 0.01
A95: ULC-1: Living Cost = $0 (At Home) | B95: — | C95: — | D95: =#REF! -> #REF! | E95: 0 | F95: =IF(ABS(D95-E95)<0.01,"✅ PASS","❌ FAIL") -> #REF! | G95: Living = At Home → $0 total | H95: 0.01
A96: TXT-1: Textbooks Age 18 | B96: 18 | C96: 18 | D96: =#REF! -> #REF! | E96: ='① Assumptions'!B44*(1+'① Assumptions'!B7)^18 -> 1702.4331 | F96: =IF(ABS(D96-E96)<0.01,"✅ PASS","❌ FAIL") -> #REF! | G96: 1000 × 1.03^18 | H96: 0.01
A97: TXT-2: Textbooks Age 20 | B97: 20 | C97: 20 | D97: =#REF! -> #REF! | E97: ='① Assumptions'!B44*(1+'① Assumptions'!B7)^20 -> 1806.1112 | F97: =IF(ABS(D97-E97)<0.01,"✅ PASS","❌ FAIL") -> #REF! | G97: 1000 × 1.03^20 | H97: 0.01
A98: TXT-3: Textbooks Age 21 = $0 | B98: 21 | C98: 21 | D98: =#REF! -> #REF! | E98: 0 | F98: =IF(ABS(D98-E98)<0.01,"✅ PASS","❌ FAIL") -> #REF! | G98: Post-uni → $0 | H98: 0.01
A99: UF-7: Uni Fees Total | B99: — | C99: — | D99: =#REF! -> #REF! | E99: =SUM(#REF!) -> #REF! | F99: =IF(ABS(D99-E99)<0.01,"✅ PASS","❌ FAIL") -> #REF! | G99: SUM matches TOTALS row | H99: 0.01
A101: TEST 8: GOVERNMENT BENEFITS (Column V)
A102: Test | B102: Year | C102: Age | D102: Timeline Value | E102: Expected Value | F102: Result | G102: Formula Logic | H102: Tolerance
A103: GB-1: Age 0 = FTB A+Supp+B | B103: 0 | C103: 0 | D103: =#REF! -> #REF! | E103: =('① Assumptions'!B109+'① Assumptions'!B112+'① Assumptions'!B111)*(1+'① Assumptions'!B7)^0 -> 11369 | F103: =IF(ABS(D103-E103)<0.01,"✅ PASS","❌ FAIL") -> #REF! | G103: (5903+916+4550) = $11,369 | H103: 0.01
A104: GB-2: Age 5 = FTB A+Supp+B×CPI^5 | B104: 5 | C104: 5 | D104: =#REF! -> #REF! | E104: =('① Assumptions'!B109+'① Assumptions'!B112+'① Assumptions'!B111)*(1+'① Assumptions'!B7)^5 -> 13179.787 | F104: =IF(ABS(D104-E104)<0.01,"✅ PASS","❌ FAIL") -> #REF! | G104: All 3 benefits active | H104: 0.01
A105: GB-3: Age 16 = FTB A+Supp+B×CPI^16 | B105: 16 | C105: 16 | D105: =#REF! -> #REF! | E105: =('① Assumptions'!B109+'① Assumptions'!B112+'① Assumptions'!B111)*(1+'① Assumptions'!B7)^16 -> 18243.908 | F105: =IF(ABS(D105-E105)<0.01,"✅ PASS","❌ FAIL") -> #REF! | G105: FTB B ends at 16 (inclusive) | H105: 0.01
A106: GB-4: Age 17 = FTB A+Supp only | B106: 17 | C106: 17 | D106: =#REF! -> #REF! | E106: =('① Assumptions'!B109+'① Assumptions'!B112)*(1+'① Assumptions'!B7)^17 -> 11270.768 | F106: =IF(ABS(D106-E106)<0.01,"✅ PASS","❌ FAIL") -> #REF! | G106: FTB B ended; A+Supp only | H106: 0.01
A107: GB-5: Age 19 = FTB A+Supp×CPI^19 | B107: 19 | C107: 19 | D107: =#REF! -> #REF! | E107: =('① Assumptions'!B109+'① Assumptions'!B112)*(1+'① Assumptions'!B7)^19 -> 11957.158 | F107: =IF(ABS(D107-E107)<0.01,"✅ PASS","❌ FAIL") -> #REF! | G107: FTB A ends at 19 (inclusive) | H107: 0.01
A108: GB-6: Age 20 = $0 (all ended) | B108: 20 | C108: 20 | D108: =#REF! -> #REF! | E108: 0 | F108: =IF(ABS(D108-E108)<0.01,"✅ PASS","❌ FAIL") -> #REF! | G108: Age 20 > FTB A end 19 → $0 | H108: 0.01
A109: GB-7: Age 21 = $0 | B109: 21 | C109: 21 | D109: =#REF! -> #REF! | E109: 0 | F109: =IF(ABS(D109-E109)<0.01,"✅ PASS","❌ FAIL") -> #REF! | G109: All benefits ceased | H109: 0.01
A110: GB-8: Benefits Total | B110: — | C110: — | D110: =#REF! -> #REF! | E110: =SUM(#REF!) -> #REF! | F110: =IF(ABS(D110-E110)<0.01,"✅ PASS","❌ FAIL") -> #REF! | G110: SUM matches TOTALS row | H110: 0.01
...

Sheet Interest Rate Curve
A1: INTEREST RATE CURVE — FUND BALANCE & OPPORTUNITY COST
A2: All values are ƒx FORMULAS — change inputs on the Assumptions tab. Risk-free rate is set in Assumptions B103.
A4: SECTION 1: FUND BALANCE AT YEAR 21 ACROSS RATES OF RETURN
A5: Assumed Gross Return | B5: Effective Net Return | C5: Fund Balance (Year 21) | D5: Opportunity Cost (FV) | E5: Break-Even Contribution | F5: Surplus / Deficit
A6: 0.01 | B6: =IF('① Assumptions'!$B$100="Yes",A6,A6*(1-'① Assumptions'!$B$96)) -> 0.00675 | C6: {='① Assumptions'!$B$90*(1+B6)^21+SUMPRODUCT(('① Assumptions'!$B$93*(1+'① Assumptions'!$B$94)^#REF!+#REF!-#REF!)*(1+B6)^(21-#REF!))} -> #REF! | D6: {=SUMPRODUCT((#REF!-#REF!)*(1+A6)^(21-#REF!))} -> #REF! | E6: {=IFERROR((SUMPRODUCT((#REF!-#REF!)*(1+B6)^(21-#REF!))-'① Assumptions'!$B$90*(1+B6)^21)/SUMPRODUCT((1+'① Assumptions'!$B$94)^#REF!*(1+B6)^(21-#REF!)),"N/A")} -> N/A | F6: =IF(C6>=0,"✅ Surplus","❌ Deficit") -> #REF!
A7: 0.015 | B7: =IF('① Assumptions'!$B$100="Yes",A7,A7*(1-'① Assumptions'!$B$96)) -> 0.010125 | C7: {='① Assumptions'!$B$90*(1+B7)^21+SUMPRODUCT(('① Assumptions'!$B$93*(1+'① Assumptions'!$B$94)^#REF!+#REF!-#REF!)*(1+B7)^(21-#REF!))} -> #REF! | D7: {=SUMPRODUCT((#REF!-#REF!)*(1+A7)^(21-#REF!))} -> #REF! | E7: {=IFERROR((SUMPRODUCT((#REF!-#REF!)*(1+B7)^(21-#REF!))-'① Assumptions'!$B$90*(1+B7)^21)/SUMPRODUCT((1+'① Assumptions'!$B$94)^#REF!*(1+B7)^(21-#REF!)),"N/A")} -> N/A | F7: =IF(C7>=0,"✅ Surplus","❌ Deficit") -> #REF!
A8: 0.02 | B8: =IF('① Assumptions'!$B$100="Yes",A8,A8*(1-'① Assumptions'!$B$96)) -> 0.0135 | C8: {='① Assumptions'!$B$90*(1+B8)^21+SUMPRODUCT(('① Assumptions'!$B$93*(1+'① Assumptions'!$B$94)^#REF!+#REF!-#REF!)*(1+B8)^(21-#REF!))} -> #REF! | D8: {=SUMPRODUCT((#REF!-#REF!)*(1+A8)^(21-#REF!))} -> #REF! | E8: {=IFERROR((SUMPRODUCT((#REF!-#REF!)*(1+B8)^(21-#REF!))-'① Assumptions'!$B$90*(1+B8)^21)/SUMPRODUCT((1+'① Assumptions'!$B$94)^#REF!*(1+B8)^(21-#REF!)),"N/A")} -> N/A | F8: =IF(C8>=0,"✅ Surplus","❌ Deficit") -> #REF!
A9: 0.025 | B9: =IF('① Assumptions'!$B$100="Yes",A9,A9*(1-'① Assumptions'!$B$96)) -> 0.016875 | C9: {='① Assumptions'!$B$90*(1+B9)^21+SUMPRODUCT(('① Assumptions'!$B$93*(1+'① Assumptions'!$B$94)^#REF!+#REF!-#REF!)*(1+B9)^(21-#REF!))} -> #REF! | D9: {=SUMPRODUCT((#REF!-#REF!)*(1+A9)^(21-#REF!))} -> #REF! | E9: {=IFERROR((SUMPRODUCT((#REF!-#REF!)*(1+B9)^(21-#REF!))-'① Assumptions'!$B$90*(1+B9)^21)/SUMPRODUCT((1+'① Assumptions'!$B$94)^#REF!*(1+B9)^(21-#REF!)),"N/A")} -> N/A | F9: =IF(C9>=0,"✅ Surplus","❌ Deficit") -> #REF!
A10: 0.03 | B10: =IF('① Assumptions'!$B$100="Yes",A10,A10*(1-'① Assumptions'!$B$96)) -> 0.02025 | C10: {='① Assumptions'!$B$90*(1+B10)^21+SUMPRODUCT(('① Assumptions'!$B$93*(1+'① Assumptions'!$B$94)^#REF!+#REF!-#REF!)*(1+B10)^(21-#REF!))} -> #REF! | D10: {=SUMPRODUCT((#REF!-#REF!)*(1+A10)^(21-#REF!))} -> #REF! | E10: {=IFERROR((SUMPRODUCT((#REF!-#REF!)*(1+B10)^(21-#REF!))-'① Assumptions'!$B$90*(1+B10)^21)/SUMPRODUCT((1+'① Assumptions'!$B$94)^#REF!*(1+B10)^(21-#REF!)),"N/A")} -> N/A | F10: =IF(C10>=0,"✅ Surplus","❌ Deficit") -> #REF!
A11: 0.035 | B11: =IF('① Assumptions'!$B$100="Yes",A11,A11*(1-'① Assumptions'!$B$96)) -> 0.023625 | C11: {='① Assumptions'!$B$90*(1+B11)^21+SUMPRODUCT(('① Assumptions'!$B$93*(1+'① Assumptions'!$B$94)^#REF!+#REF!-#REF!)*(1+B11)^(21-#REF!))} -> #REF! | D11: {=SUMPRODUCT((#REF!-#REF!)*(1+A11)^(21-#REF!))} -> #REF! | E11: {=IFERROR((SUMPRODUCT((#REF!-#REF!)*(1+B11)^(21-#REF!))-'① Assumptions'!$B$90*(1+B11)^21)/SUMPRODUCT((1+'① Assumptions'!$B$94)^#REF!*(1+B11)^(21-#REF!)),"N/A")} -> N/A | F11: =IF(C11>=0,"✅ Surplus","❌ Deficit") -> #REF!
A12: 0.04 | B12: =IF('① Assumptions'!$B$100="Yes",A12,A12*(1-'① Assumptions'!$B$96)) -> 0.027 | C12: {='① Assumptions'!$B$90*(1+B12)^21+SUMPRODUCT(('① Assumptions'!$B$93*(1+'① Assumptions'!$B$94)^#REF!+#REF!-#REF!)*(1+B12)^(21-#REF!))} -> #REF! | D12: {=SUMPRODUCT((#REF!-#REF!)*(1+A12)^(21-#REF!))} -> #REF! | E12: {=IFERROR((SUMPRODUCT((#REF!-#REF!)*(1+B12)^(21-#REF!))-'① Assumptions'!$B$90*(1+B12)^21)/SUMPRODUCT((1+'① Assumptions'!$B$94)^#REF!*(1+B12)^(21-#REF!)),"N/A")} -> N/A | F12: =IF(C12>=0,"✅ Surplus","❌ Deficit") -> #REF!
A13: 0.045 | B13: =IF('① Assumptions'!$B$100="Yes",A13,A13*(1-'① Assumptions'!$B$96)) -> 0.030375 | C13: {='① Assumptions'!$B$90*(1+B13)^21+SUMPRODUCT(('① Assumptions'!$B$93*(1+'① Assumptions'!$B$94)^#REF!+#REF!-#REF!)*(1+B13)^(21-#REF!))} -> #REF! | D13: {=SUMPRODUCT((#REF!-#REF!)*(1+A13)^(21-#REF!))} -> #REF! | E13: {=IFERROR((SUMPRODUCT((#REF!-#REF!)*(1+B13)^(21-#REF!))-'① Assumptions'!$B$90*(1+B13)^21)/SUMPRODUCT((1+'① Assumptions'!$B$94)^#REF!*(1+B13)^(21-#REF!)),"N/A")} -> N/A | F13: =IF(C13>=0,"✅ Surplus","❌ Deficit") -> #REF!
A14: 0.05 | B14: =IF('① Assumptions'!$B$100="Yes",A14,A14*(1-'① Assumptions'!$B$96)) -> 0.03375 | C14: {='① Assumptions'!$B$90*(1+B14)^21+SUMPRODUCT(('① Assumptions'!$B$93*(1+'① Assumptions'!$B$94)^#REF!+#REF!-#REF!)*(1+B14)^(21-#REF!))} -> #REF! | D14: {=SUMPRODUCT((#REF!-#REF!)*(1+A14)^(21-#REF!))} -> #REF! | E14: {=IFERROR((SUMPRODUCT((#REF!-#REF!)*(1+B14)^(21-#REF!))-'① Assumptions'!$B$90*(1+B14)^21)/SUMPRODUCT((1+'① Assumptions'!$B$94)^#REF!*(1+B14)^(21-#REF!)),"N/A")} -> N/A | F14: =IF(C14>=0,"✅ Surplus","❌ Deficit") -> #REF!
A15: 0.055 | B15: =IF('① Assumptions'!$B$100="Yes",A15,A15*(1-'① Assumptions'!$B$96)) -> 0.037125 | C15: {='① Assumptions'!$B$90*(1+B15)^21+SUMPRODUCT(('① Assumptions'!$B$93*(1+'① Assumptions'!$B$94)^#REF!+#REF!-#REF!)*(1+B15)^(21-#REF!))} -> #REF! | D15: {=SUMPRODUCT((#REF!-#REF!)*(1+A15)^(21-#REF!))} -> #REF! | E15: {=IFERROR((SUMPRODUCT((#REF!-#REF!)*(1+B15)^(21-#REF!))-'① Assumptions'!$B$90*(1+B15)^21)/SUMPRODUCT((1+'① Assumptions'!$B$94)^#REF!*(1+B15)^(21-#REF!)),"N/A")} -> N/A | F15: =IF(C15>=0,"✅ Surplus","❌ Deficit") -> #REF!
A16: 0.06 | B16: =IF('① Assumptions'!$B$100="Yes",A16,A16*(1-'① Assumptions'!$B$96)) -> 0.0405 | C16: {='① Assumptions'!$B$90*(1+B16)^21+SUMPRODUCT(('① Assumptions'!$B$93*(1+'① Assumptions'!$B$94)^#REF!+#REF!-#REF!)*(1+B16)^(21-#REF!))} -> #REF! | D16: {=SUMPRODUCT((#REF!-#REF!)*(1+A16)^(21-#REF!))} -> #REF! | E16: {=IFERROR((SUMPRODUCT((#REF!-#REF!)*(1+B16)^(21-#REF!))-'① Assumptions'!$B$90*(1+B16)^21)/SUMPRODUCT((1+'① Assumptions'!$B$94)^#REF!*(1+B16)^(21-#REF!)),"N/A")} -> N/A | F16: =IF(C16>=0,"✅ Surplus","❌ Deficit") -> #REF!
A17: 0.065 | B17: =IF('① Assumptions'!$B$100="Yes",A17,A17*(1-'① Assumptions'!$B$96)) -> 0.043875 | C17: {='① Assumptions'!$B$90*(1+B17)^21+SUMPRODUCT(('① Assumptions'!$B$93*(1+'① Assumptions'!$B$94)^#REF!+#REF!-#REF!)*(1+B17)^(21-#REF!))} -> #REF! | D17: {=SUMPRODUCT((#REF!-#REF!)*(1+A17)^(21-#REF!))} -> #REF! | E17: {=IFERROR((SUMPRODUCT((#REF!-#REF!)*(1+B17)^(21-#REF!))-'① Assumptions'!$B$90*(1+B17)^21)/SUMPRODUCT((1+'① Assumptions'!$B$94)^#REF!*(1+B17)^(21-#REF!)),"N/A")} -> N/A | F17: =IF(C17>=0,"✅ Surplus","❌ Deficit") -> #REF!
... A32: 0.14 | B32: =IF('① Assumptions'!$B$100="Yes",A32,A32*(1-'① Assumptions'!$B$96)) -> 0.0945 | C32: {='① Assumptions'!$B$90*(1+B32)^21+SUMPRODUCT(('① Assumptions'!$B$93*(1+'① Assumptions'!$B$94)^#REF!+#REF!-#REF!)*(1+B32)^(21-#REF!))} -> #REF! | D32: {=SUMPRODUCT((#REF!-#REF!)*(1+A32)^(21-#REF!))} -> #REF! | E32: {=IFERROR((SUMPRODUCT((#REF!-#REF!)*(1+B32)^(21-#REF!))-'① Assumptions'!$B$90*(1+B32)^21)/SUMPRODUCT((1+'① Assumptions'!$B$94)^#REF!*(1+B32)^(21-#REF!)),"N/A")} -> N/A | F32: =IF(C32>=0,"✅ Surplus","❌ Deficit") -> #REF!
A35: SECTION 2: YEAR-BY-YEAR FUND BALANCE TRAJECTORY
A36: Year | B36: Child Age | C36: ="Fund Bal @ Risk-Free ("&TEXT('① Assumptions'!B103,"0.0%")&" gross)" -> Fund Bal @ Risk-Free (4.3% gross) | D36: ="Fund Bal @ Base Case ("&TEXT('① Assumptions'!B95,"0.0%")&" gross)" -> Fund Bal @ Base Case (6.0% gross) | E36: ="Fund Bal @ High ("&TEXT('① Assumptions'!B95+0.04,"0.0%")&" gross)" -> Fund Bal @ High (10.0% gross) | F36: ="Opp Cost (FV @ Risk-Free "&TEXT('① Assumptions'!B103,"0.0%")&")" -> Opp Cost (FV @ Risk-Free 4.3%) | G36: $0 Break-Even Line
A37: 0 | B37: =#REF! -> #REF! | C37: ='① Assumptions'!$B$90+'① Assumptions'!$B$93+#REF!-#REF! -> #REF! | D37: ='① Assumptions'!$B$90+'① Assumptions'!$B$93+#REF!-#REF! -> #REF! | E37: ='① Assumptions'!$B$90+'① Assumptions'!$B$93+#REF!-#REF! -> #REF! | F37: =(#REF!-#REF!)*(1+'① Assumptions'!$B$103)^(21-A37) -> #REF! | G37: 0
A38: 1 | B38: =#REF! -> #REF! | C38: =C37*(1+IF('① Assumptions'!$B$100="Yes",'① Assumptions'!$B$103,'① Assumptions'!$B$103*(1-'① Assumptions'!$B$96)))+'① Assumptions'!$B$93*(1+'① Assumptions'!$B$94)^A38+#REF!-#REF! -> #REF! | D38: =D37*(1+'① Assumptions'!$B$97)+'① Assumptions'!$B$93*(1+'① Assumptions'!$B$94)^A38+#REF!-#REF! -> #REF! | E38: =E37*(1+IF('① Assumptions'!$B$100="Yes",'① Assumptions'!$B$95+0.04,('① Assumptions'!$B$95+0.04)*(1-'① Assumptions'!$B$96)))+'① Assumptions'!$B$93*(1+'① Assumptions'!$B$94)^A38+#REF!-#REF! -> #REF! | F38: =F37+(#REF!-#REF!)*(1+'① Assumptions'!$B$103)^(21-A38) -> #REF! | G38: 0
A39: 2 | B39: =#REF! -> #REF! | C39: =C38*(1+IF('① Assumptions'!$B$100="Yes",'① Assumptions'!$B$103,'① Assumptions'!$B$103*(1-'① Assumptions'!$B$96)))+'① Assumptions'!$B$93*(1+'① Assumptions'!$B$94)^A39+#REF!-#REF! -> #REF! | D39: =D38*(1+'① Assumptions'!$B$97)+'① Assumptions'!$B$93*(1+'① Assumptions'!$B$94)^A39+#REF!-#REF! -> #REF! | E39: =E38*(1+IF('① Assumptions'!$B$100="Yes",'① Assumptions'!$B$95+0.04,('① Assumptions'!$B$95+0.04)*(1-'① Assumptions'!$B$96)))+'① Assumptions'!$B$93*(1+'① Assumptions'!$B$94)^A39+#REF!-#REF! -> #REF! | F39: =F38+(#REF!-#REF!)*(1+'① Assumptions'!$B$103)^(21-A39) -> #REF! | G39: 0
A40: 3 | B40: =#REF! -> #REF! | C40: =C39*(1+IF('① Assumptions'!$B$100="Yes",'① Assumptions'!$B$103,'① Assumptions'!$B$103*(1-'① Assumptions'!$B$96)))+'① Assumptions'!$B$93*(1+'① Assumptions'!$B$94)^A40+#REF!-#REF! -> #REF! | D40: =D39*(1+'① Assumptions'!$B$97)+'① Assumptions'!$B$93*(1+'① Assumptions'!$B$94)^A40+#REF!-#REF! -> #REF! | E40: =E39*(1+IF('① Assumptions'!$B$100="Yes",'① Assumptions'!$B$95+0.04,('① Assumptions'!$B$95+0.04)*(1-'① Assumptions'!$B$96)))+'① Assumptions'!$B$93*(1+'① Assumptions'!$B$94)^A40+#REF!-#REF! -> #REF! | F40: =F39+(#REF!-#REF!)*(1+'① Assumptions'!$B$103)^(21-A40) -> #REF! | G40: 0
A41: 4 | B41: =#REF! -> #REF! | C41: =C40*(1+IF('① Assumptions'!$B$100="Yes",'① Assumptions'!$B$103,'① Assumptions'!$B$103*(1-'① Assumptions'!$B$96)))+'① Assumptions'!$B$93*(1+'① Assumptions'!$B$94)^A41+#REF!-#REF! -> #REF! | D41: =D40*(1+'① Assumptions'!$B$97)+'① Assumptions'!$B$93*(1+'① Assumptions'!$B$94)^A41+#REF!-#REF! -> #REF! | E41: =E40*(1+IF('① Assumptions'!$B$100="Yes",'① Assumptions'!$B$95+0.04,('① Assumptions'!$B$95+0.04)*(1-'① Assumptions'!$B$96)))+'① Assumptions'!$B$93*(1+'① Assumptions'!$B$94)^A41+#REF!-#REF! -> #REF! | F41: =F40+(#REF!-#REF!)*(1+'① Assumptions'!$B$103)^(21-A41) -> #REF! | G41: 0
A42: 5 | B42: =#REF! -> #REF! | C42: =C41*(1+IF('① Assumptions'!$B$100="Yes",'① Assumptions'!$B$103,'① Assumptions'!$B$103*(1-'① Assumptions'!$B$96)))+'① Assumptions'!$B$93*(1+'① Assumptions'!$B$94)^A42+#REF!-#REF! -> #REF! | D42: =D41*(1+'① Assumptions'!$B$97)+'① Assumptions'!$B$93*(1+'① Assumptions'!$B$94)^A42+#REF!-#REF! -> #REF! | E42: =E41*(1+IF('① Assumptions'!$B$100="Yes",'① Assumptions'!$B$95+0.04,('① Assumptions'!$B$95+0.04)*(1-'① Assumptions'!$B$96)))+'① Assumptions'!$B$93*(1+'① Assumptions'!$B$94)^A42+#REF!-#REF! -> #REF! | F42: =F41+(#REF!-#REF!)*(1+'① Assumptions'!$B$103)^(21-A42) -> #REF! | G42: 0
A43: 6 | B43: =#REF! -> #REF! | C43: =C42*(1+IF('① Assumptions'!$B$100="Yes",'① Assumptions'!$B$103,'① Assumptions'!$B$103*(1-'① Assumptions'!$B$96)))+'① Assumptions'!$B$93*(1+'① Assumptions'!$B$94)^A43+#REF!-#REF! -> #REF! | D43: =D42*(1+'① Assumptions'!$B$97)+'① Assumptions'!$B$93*(1+'① Assumptions'!$B$94)^A43+#REF!-#REF! -> #REF! | E43: =E42*(1+IF('① Assumptions'!$B$100="Yes",'① Assumptions'!$B$95+0.04,('① Assumptions'!$B$95+0.04)*(1-'① Assumptions'!$B$96)))+'① Assumptions'!$B$93*(1+'① Assumptions'!$B$94)^A43+#REF!-#REF! -> #REF! | F43: =F42+(#REF!-#REF!)*(1+'① Assumptions'!$B$103)^(21-A43) -> #REF! | G43: 0
A44: 7 | B44: =#REF! -> #REF! | C44: =C43*(1+IF('① Assumptions'!$B$100="Yes",'① Assumptions'!$B$103,'① Assumptions'!$B$103*(1-'① Assumptions'!$B$96)))+'① Assumptions'!$B$93*(1+'① Assumptions'!$B$94)^A44+#REF!-#REF! -> #REF! | D44: =D43*(1+'① Assumptions'!$B$97)+'① Assumptions'!$B$93*(1+'① Assumptions'!$B$94)^A44+#REF!-#REF! -> #REF! | E44: =E43*(1+IF('① Assumptions'!$B$100="Yes",'① Assumptions'!$B$95+0.04,('① Assumptions'!$B$95+0.04)*(1-'① Assumptions'!$B$96)))+'① Assumptions'!$B$93*(1+'① Assumptions'!$B$94)^A44+#REF!-#REF! -> #REF! | F44: =F43+(#REF!-#REF!)*(1+'① Assumptions'!$B$103)^(21-A44) -> #REF! | G44: 0
A45: 8 | B45: =#REF! -> #REF! | C45: =C44*(1+IF('① Assumptions'!$B$100="Yes",'① Assumptions'!$B$103,'① Assumptions'!$B$103*(1-'① Assumptions'!$B$96)))+'① Assumptions'!$B$93*(1+'① Assumptions'!$B$94)^A45+#REF!-#REF! -> #REF! | D45: =D44*(1+'① Assumptions'!$B$97)+'① Assumptions'!$B$93*(1+'① Assumptions'!$B$94)^A45+#REF!-#REF! -> #REF! | E45: =E44*(1+IF('① Assumptions'!$B$100="Yes",'① Assumptions'!$B$95+0.04,('① Assumptions'!$B$95+0.04)*(1-'① Assumptions'!$B$96)))+'① Assumptions'!$B$93*(1+'① Assumptions'!$B$94)^A45+#REF!-#REF! -> #REF! | F45: =F44+(#REF!-#REF!)*(1+'① Assumptions'!$B$103)^(21-A45) -> #REF! | G45: 0
A46: 9 | B46: =#REF! -> #REF! | C46: =C45*(1+IF('① Assumptions'!$B$100="Yes",'① Assumptions'!$B$103,'① Assumptions'!$B$103*(1-'① Assumptions'!$B$96)))+'① Assumptions'!$B$93*(1+'① Assumptions'!$B$94)^A46+#REF!-#REF! -> #REF! | D46: =D45*(1+'① Assumptions'!$B$97)+'① Assumptions'!$B$93*(1+'① Assumptions'!$B$94)^A46+#REF!-#REF! -> #REF! | E46: =E45*(1+IF('① Assumptions'!$B$100="Yes",'① Assumptions'!$B$95+0.04,('① Assumptions'!$B$95+0.04)*(1-'① Assumptions'!$B$96)))+'① Assumptions'!$B$93*(1+'① Assumptions'!$B$94)^A46+#REF!-#REF! -> #REF! | F46: =F45+(#REF!-#REF!)*(1+'① Assumptions'!$B$103)^(21-A46) -> #REF! | G46: 0
A47: 10 | B47: =#REF! -> #REF! | C47: =C46*(1+IF('① Assumptions'!$B$100="Yes",'① Assumptions'!$B$103,'① Assumptions'!$B$103*(1-'① Assumptions'!$B$96)))+'① Assumptions'!$B$93*(1+'① Assumptions'!$B$94)^A47+#REF!-#REF! -> #REF! | D47: =D46*(1+'① Assumptions'!$B$97)+'① Assumptions'!$B$93*(1+'① Assumptions'!$B$94)^A47+#REF!-#REF! -> #REF! | E47: =E46*(1+IF('① Assumptions'!$B$100="Yes",'① Assumptions'!$B$95+0.04,('① Assumptions'!$B$95+0.04)*(1-'① Assumptions'!$B$96)))+'① Assumptions'!$B$93*(1+'① Assumptions'!$B$94)^A47+#REF!-#REF! -> #REF! | F47: =F46+(#REF!-#REF!)*(1+'① Assumptions'!$B$103)^(21-A47) -> #REF! | G47: 0
A48: 11 | B48: =#REF! -> #REF! | C48: =C47*(1+IF('① Assumptions'!$B$100="Yes",'① Assumptions'!$B$103,'① Assumptions'!$B$103*(1-'① Assumptions'!$B$96)))+'① Assumptions'!$B$93*(1+'① Assumptions'!$B$94)^A48+#REF!-#REF! -> #REF! | D48: =D47*(1+'① Assumptions'!$B$97)+'① Assumptions'!$B$93*(1+'① Assumptions'!$B$94)^A48+#REF!-#REF! -> #REF! | E48: =E47*(1+IF('① Assumptions'!$B$100="Yes",'① Assumptions'!$B$95+0.04,('① Assumptions'!$B$95+0.04)*(1-'① Assumptions'!$B$96)))+'① Assumptions'!$B$93*(1+'① Assumptions'!$B$94)^A48+#REF!-#REF! -> #REF! | F48: =F47+(#REF!-#REF!)*(1+'① Assumptions'!$B$103)^(21-A48) -> #REF! | G48: 0
A49: 12 | B49: =#REF! -> #REF! | C49: =C48*(1+IF('① Assumptions'!$B$100="Yes",'① Assumptions'!$B$103,'① Assumptions'!$B$103*(1-'① Assumptions'!$B$96)))+'① Assumptions'!$B$93*(1+'① Assumptions'!$B$94)^A49+#REF!-#REF! -> #REF! | D49: =D48*(1+'① Assumptions'!$B$97)+'① Assumptions'!$B$93*(1+'① Assumptions'!$B$94)^A49+#REF!-#REF! -> #REF! | E49: =E48*(1+IF('① Assumptions'!$B$100="Yes",'① Assumptions'!$B$95+0.04,('① Assumptions'!$B$95+0.04)*(1-'① Assumptions'!$B$96)))+'① Assumptions'!$B$93*(1+'① Assumptions'!$B$94)^A49+#REF!-#REF! -> #REF! | F49: =F48+(#REF!-#REF!)*(1+'① Assumptions'!$B$103)^(21-A49) -> #REF! | G49: 0
... A58: 21 | B58: =#REF! -> #REF! | C58: =C57*(1+IF('① Assumptions'!$B$100="Yes",'① Assumptions'!$B$103,'① Assumptions'!$B$103*(1-'① Assumptions'!$B$96)))+'① Assumptions'!$B$93*(1+'① Assumptions'!$B$94)^A58+#REF!-#REF! -> #REF! | D58: =D57*(1+'① Assumptions'!$B$97)+'① Assumptions'!$B$93*(1+'① Assumptions'!$B$94)^A58+#REF!-#REF! -> #REF! | E58: =E57*(1+IF('① Assumptions'!$B$100="Yes",'① Assumptions'!$B$95+0.04,('① Assumptions'!$B$95+0.04)*(1-'① Assumptions'!$B$96)))+'① Assumptions'!$B$93*(1+'① Assumptions'!$B$94)^A58+#REF!-#REF! -> #REF! | F58: =F57+(#REF!-#REF!)*(1+'① Assumptions'!$B$103)^(21-A58) -> #REF! | G58: 0
