Workbook

Sheet Inputs
A1: LOAN vs SUPERANNUATION CALCULATOR
A2: Input all your details below. Blue values are editable inputs.
A3: ✏️ Blue border = YOUR INPUT (edit these) 🔒 Grey italic = AUTO-CALCULATED (do not edit)
A4: SECTION 1: PERSONAL DETAILS
A5: Field | C5: Value | D5: Type
A6: Annual Gross Salary | C6: 150000 | D6: ✏️ INPUT
A7: Age | C7: 38 | D7: ✏️ INPUT
A8: Annual Salary Growth Rate | C8: 0.1 | D8: ✏️ INPUT
A9: Preservation Age | C9: 60 | D9: ✏️ INPUT
A10: Years to Preservation | C10: =C9-C7 -> 22 | D10: 🔒 FORMULA
A11: Filing Status | C11: Single | D11: ✏️ INPUT
A12: Private Health Insurance? | C12: Yes | D12: ✏️ INPUT
A14: SECTION 2: TAX CALCULATION (2024-25 ATO Rates)
A15: Tax Bracket | B15: Lower | C15: Upper | D15: Rate
A16: Nil | B16: 0 | C16: 18200 | D16: 0
A17: 16c | B17: 18201 | C17: 45000 | D17: 0.16
A18: 30c | B18: 45001 | C18: 135000 | D18: 0.3
A19: 37c | B19: 135001 | C19: 190000 | D19: 0.37
A20: 45c | B20: 190001 | C20: 999999999 | D20: 0.45
A22: Field | C22: Value | D22: Type
A23: Taxable Income (Gross Salary) | C23: =C6 -> 150000 | D23: 🔒 FORMULA
A24: Income Tax Payable | C24: =IF(C23<=18200,0,IF(C23<=45000,(C23-18200)*0.16,IF(C23<=135000,4288+(C23-45000)*0.3,IF(C23<=190000,31288+(C23-135000)*0.37,51638+(C23-190000)*0.45)))) -> 36838 | D24: 🔒 FORMULA
A25: Medicare Levy (2%) | C25: =C23*0.02 -> 3000 | D25: 🔒 FORMULA
A26: Total Tax (incl. Medicare) | C26: =C24+C25 -> 39838 | D26: 🔒 FORMULA
A27: Effective Tax Rate | C27: =IF(C23>0,C26/C23,0) -> 0.26558667 | D27: 🔒 FORMULA
A28: Marginal Tax Rate | C28: =IF(C23>190000,0.45,IF(C23>135000,0.37,IF(C23>45000,0.3,IF(C23>18200,0.16,0)))) -> 0.37 | D28: 🔒 FORMULA
A29: Marginal Rate + Medicare | C29: =C28+0.02 -> 0.39 | D29: 🔒 FORMULA
A30: Annual Take-Home Pay | C30: =C23-C26 -> 110162 | D30: 🔒 FORMULA
A31: Monthly Take-Home Pay | C31: =C30/12 -> 9180.1667 | D31: 🔒 FORMULA
A33: SECTION 3: SUPERANNUATION
A34: Field | C34: Value | D34: Type
A35: Current Super Balance | C35: 150000 | D35: ✏️ INPUT
A36: Employer SG Rate | C36: 0.115 | D36: ✏️ INPUT
A37: Employer SG Amount (Annual) | C37: =C6*C36 -> 17250 | D37: 🔒 FORMULA
A38: Concessional Cap (Annual) | C38: 30000 | D38: ✏️ INPUT
A39: Carry-Forward Concessional Cap (Past 5 Years)
A40: 2019-20 (Year -5) | C40: 0 | D40: ✏️ INPUT
A41: 2020-21 (Year -4) | C41: 0 | D41: ✏️ INPUT
A42: 2021-22 (Year -3) | C42: 5000 | D42: ✏️ INPUT
A43: 2022-23 (Year -2) | C43: 10000 | D43: ✏️ INPUT
A44: 2023-24 (Year -1) | C44: 10000 | D44: ✏️ INPUT
A45: Total Carry-Forward Available | C45: =SUM(C40:C44) -> 25000 | D45: 🔒 FORMULA
A46: Eligible? (Super balance < $500k) | C46: =IF(C35<500000,"YES","NO") -> YES | D46: 🔒 FORMULA
A48: Ongoing SS Space (Cap − SG) | C48: =C49 -> 12750 | D48: 🔒 FORMULA — $0 means SG exceeds cap
A49: Remaining Concessional Cap | C49: =MAX(0,C38-C37) -> 12750 | D49: 🔒 FORMULA
A50: Total Available Cap (incl. Carry-Forward) | C50: =IF(C46="YES",C49+C45,C49) -> 37750 | D50: 🔒 FORMULA
A51: Assumed Super Return (p.a.) | C51: 0.01 | D51: ✏️ INPUT
A52: Super Earnings Tax Rate | C52: 0.15 | D52: ✏️ INPUT
A53: After-Tax Super Return | C53: =C51*(1-C52) -> 0.0085 | D53: 🔒 FORMULA
A54: Concessional Contributions Tax | C54: 0.15 | D54: ✏️ INPUT
A55: Division 293 Applies? | C55: =IF(C6+C37>250000,"YES","NO") -> NO | D55: 🔒 FORMULA
A56: Effective Contributions Tax Rate | C56: =IF(C55="YES",0.3,0.15) -> 0.15 | D56: 🔒 FORMULA
A57: Division 293 Calculation Detail | C57: Value
A58: Div 293 Threshold | C58: 250000 | D58: 🔒 FORMULA
A59: Taxable Income | C59: =C6 -> 150000 | D59: 🔒 FORMULA
A60: Low Tax Super Contributions | C60: =C37 -> 17250 | D60: 🔒 FORMULA
A61: Income + Contributions | C61: =C59+C60 -> 167250 | D61: 🔒 FORMULA
A62: Excess Over Threshold | C62: =MAX(0,C61-C58) -> 0 | D62: 🔒 FORMULA
A63: Div 293 Tax Payable (on SS) | C63: =IF(C55="YES",MIN(C50,C62)*0.15,0) -> 0 | D63: 🔒 FORMULA
A64: Standard 15% Contributions Tax | C64: =C50*0.15 -> 5662.5 | D64: 🔒 FORMULA
A66: SECTION 4: HOME LOAN
A67: Field | C67: Value | D67: Type
A68: Outstanding Loan Balance | C68: 1000000 | D68: ✏️ INPUT
A69: Annual Interest Rate (Variable) | C69: 0.062 | D69: ✏️ INPUT
A70: Monthly Interest Rate | C70: =C69/12 -> 0.0051666667 | D70: 🔒 FORMULA
A71: Remaining Loan Term (Years) | C71: 25 | D71: ✏️ INPUT
A72: Remaining Loan Term (Months) | C72: =C71*12 -> 300 | D72: 🔒 FORMULA
A73: Minimum Monthly Repayment | C73: =IF(C70>0,PMT(C70,C72,-C68),C68/C72) -> 6565.821 | D73: 🔒 FORMULA
A74: Total Interest Over Loan Life | C74: =(C73*C72)-C68 -> 969746.29 | D74: 🔒 FORMULA
A75: Use Offset Account? | C75: Yes | D75: ✏️ INPUT
A76: Current Offset Balance | C76: 50000 | D76: ✏️ INPUT
A77: Effective Loan Balance (after Offset) | C77: =IF(C75="Yes",C68-C76,C68) -> 950000 | D77: 🔒 FORMULA
A78: Loan Interest is NOT Tax Deductible | C78: N/A | D78: 🔒 STATIC
A80: SECTION 5: SCENARIO PARAMETERS
A81: Field | C81: Value | D81: Type
A82: Monthly Excess Cash to Deploy | C82: 1500 | D82: ✏️ INPUT
A83: Annual Excess Cash | C83: =C82*12 -> 18000 | D83: 🔒 FORMULA
A84: Inflation Assumption (p.a.) | C84: 0.025 | D84: ✏️ INPUT
A86: Analysis Horizons
A87: Short-Term (Years) | C87: 5 | D87: ✏️ INPUT
A88: Medium-Term (Years) | C88: 10 | D88: ✏️ INPUT
A89: Long-Term (Years) | C89: 20 | D89: ✏️ INPUT
A91: SECTION 6: KEY DERIVED METRICS
A92: Metric | C92: Value | D92: Type
A93: Tax Saved per $1 Salary Sacrificed | C93: =C29-C56 -> 0.24 | D93: 🔒 FORMULA
A94: Effective Interest Rate (After-Tax) | C94: =C69 -> 0.062 | D94: 🔒 FORMULA
A95: Super Return (After Earnings Tax) | C95: =C53 -> 0.0085 | D95: 🔒 FORMULA
A96: Loan Rate vs Super Return Gap | C96: =C94-C95 -> 0.0535 | D96: 🔒 FORMULA
A98: Salary Sacrifice Benefit (per $1)
A99: Pre-tax cost of $1 into super | C99: =1-C56 -> 0.85 | D99: 🔒 FORMULA
A100: After-tax cost of $1 kept as salary | C100: =1-C29 -> 0.61 | D100: 🔒 FORMULA
A101: Effective cost per $1 in super | C101: =C100/1 -> 0.61 | D101: 🔒 FORMULA
A102: Multiplier: Super $ per Take-Home $ | C102: =C99/(1-C29) -> 1.3934426 | D102: 🔒 FORMULA

Sheet Dashboard
A1: LOAN vs SUPER DECISION DASHBOARD
A2: Australian Tax-Aware Calculator — Summary of Scenarios
A21: RECOMMENDATION
A22: =IF(Calculations!L97="B","→ Salary sacrifice $"&TEXT(Calculations!C50/20,"#,##0")&"/yr gross (excess concessional) into super. All $"&TEXT(Inputs!C83,"#,##0")&"/yr cash consumed by forgone pay + excess ATO tax. Super compounding delivers highest net wealth despite 0% tax benefit on excess.",IF(Calculations!L97="A","→ Direct all excess cash to extra loan repayments. The interest savings outweigh super benefits.","→ Use the offset account. Flexible access + interest savings provide the best outcome.")) -> → Salary sacrifice $25,129/yr gross (excess concessional) into super. All $18,000/yr cash consumed by forgone pay + excess ATO tax. Super compounding delivers highest net wealth despite 0% tax benefit on excess.
A24: NET WEALTH GAIN BY HORIZON | F24: KEY METRICS
A25: Scenario | B25: 5 Years | C25: 10 Years | D25: 20 Years | F25: Metric | G25: Value | H25: Notes
A26: A: Extra Loan Repayments | B26: =Calculations!I82 -> 11873.635 | C26: =Calculations!I87 -> 59494.534 | D26: =Calculations!I97 -> 298306.35 | F26: Loan Payoff (Scenario A) | G26: =Calculations!C108 -> 18 | H26: With extra repayments
A27: B: Salary Sacrifice (Excess) | B27: =Calculations!J82 -> 134599.38 | C27: =Calculations!J87 -> 255693.54 | D27: =Calculations!J97 -> 523752.55 | F27: Loan Payoff (Scenario B) | G27: =Calculations!C109 -> >20 | H27: All years sacrifice (excess concessional)
A28: C: Offset Account | B28: =Calculations!K82 -> 26660 | C28: =Calculations!K87 -> 81220 | D28: =Calculations!K97 -> 228390.38 | F28: Loan Payoff (Baseline) | G28: =Inputs!C71 -> 25 | H28: Standard term, no extras
A29: Winner | B29: =Calculations!L82 -> B | C29: =Calculations!L87 -> B | D29: =Calculations!L97 -> B
A30: B vs A Advantage | B30: =Calculations!M82 -> 122725.74 | C30: =Calculations!M87 -> 196199.01 | D30: =Calculations!M97 -> 225446.2 | F30: Super Balance at 20 Yrs | G30: =Calculations!H49 -> 1541470.9 | H30: Scenario B (incl. SG)
F31: Baseline Super at 20 Yrs | G31: =Calculations!B97 -> 1065918.5 | H31: SG only, no sacrifice
A32: CASH FLOW IMPACT (YEAR 1) | F32: Extra Super from SS | G32: =Calculations!E97 -> 475552.35 | H32: 20yr excess sacrifice compounded
A33: Item | B33: Scenario A | C33: Scenario B | D33: Scenario C
A34: Gross Salary Sacrifice | B34: - | C34: =Calculations!C30 -> 31835.294 | D34: - | F34: Division 293 Applies? | G34: =Inputs!C55 -> NO | H34: Extra 15% tax on super
A35: After-Tax Cost (Total) | B35: - | C35: =Calculations!J30 -> 19419.529 | D35: - | F35: Effective SS Tax Rate | G35: =Inputs!C56 -> 0.15 | H35: 30% with Div 293
A36: Tax Saved from SS | B36: - | C36: =Calculations!I30 -> 7640.4706 | D36: - | F36: Tax Saved per $1 SS | G36: =Inputs!C93 -> 0.24 | H36: Marginal rate minus super tax
A37: ATO Excess Tax (Personal) | B37: - | C37: =Calculations!M30 -> 0 | D37: -
A38: Extra Loan Repayment (Annual) | B38: =Inputs!C83 -> 18000 | C38: =Calculations!K30 -> -1419.5294 | D38: - | F38: Monthly Excess Cash | G38: =Inputs!C82 -> 1500 | H38: Amount deployed each month
A39: Offset Deposit (Annual) | B39: - | C39: - | D39: =Inputs!C83 -> 18000
A40: Total Cash Deployed | B40: =Inputs!C83 -> 18000 | C40: =Calculations!J30+Calculations!K30 -> 18000 | D40: =Inputs!C83 -> 18000
A42: WHY SCENARIO B WINS
A43: Factor | B43: Impact | C43: Explanation
A44: 1. Employer SG Compounding | B44: Dominant | C44: $31,625/yr SG compounds at 5.1% inside super — all 3 scenarios benefit equally
A45: 2. Ongoing Salary Sacrifice (Excess) | B45: ="+$"&TEXT(Calculations!E97,"#,##0")&" at 20 yrs" -> +$475,552 at 20 yrs | C45: $21k-$31k/yr gross sacrificed → $18k/yr net into super (after fund tax). Compounds for 20 years despite excess tax
A46: 3. Additional Tax Cost (Excess) | B46: ="$"&TEXT(Calculations!M50,"#,##0")&" over 20 yrs" -> $54,841 over 20 yrs | C46: Excess contributions taxed at marginal 47% (vs 15% fund). ATO bills 32% extra on excess — this is the price of super compounding
A47: 4. Loan Rate vs Super Return | B47: ="Gap: "&TEXT(Inputs!C96,"0.0%") -> Gap: 5.4% | C47: Loan at 6.2% vs super at 5.1% — loan costs more per dollar, but super's tax advantages and SG offset this
A48: 5. Exceeding Concessional Cap | B48: ="$"&TEXT(Calculations!N50,"#,##0")&" excess" -> $228,503 excess | C48: Total excess contributions over 20 years. All taxed at marginal rate (no concessional benefit). Super compounding still wins.
A49: 6. Super Access Restriction | B49: ="Locked "&TEXT(Inputs!C10,"0")&" yrs" -> Locked 22 yrs | C49: Super inaccessible until preservation age 60. Offset provides full liquidity.
A51: CHART DATA: NET WEALTH GAIN OVER TIME | F51: SNAPSHOT COMPARISON
A52: Year | B52: A: Extra Repayments | C52: B: Salary Sacrifice | D52: C: Offset Account | F52: Horizon | G52: A: Extra Repay | H52: B: Salary Sacrifice | I52: C: Offset
A53: 0 | B53: 0 | C53: 0 | D53: 0 | F53: 5 Years | G53: =B26 -> 11873.635 | H53: =B27 -> 134599.38 | I53: =B28 -> 26660
A54: 1 | B54: =Calculations!I78 -> 0 | C54: =Calculations!J78 -> 42784.963 | D54: =Calculations!K78 -> 3100 | F54: 10 Years | G54: =C26 -> 59494.534 | H54: =C27 -> 255693.54 | I54: =C28 -> 81220
A55: 2 | B55: =Calculations!I79 -> 1116 | C55: =Calculations!J79 -> 65347.052 | D55: =Calculations!K79 -> 7316 | F55: 20 Years | G55: =D26 -> 298306.35 | H55: =D27 -> 523752.55 | I55: =D28 -> 228390.38
A56: 3 | B56: =Calculations!I80 -> 3417.192 | C56: =Calculations!J80 -> 88165.612 | D56: =Calculations!K80 -> 12648
A57: 4 | B57: =Calculations!I81 -> 6977.0579 | C57: =Calculations!J81 -> 111247.35 | D57: =Calculations!K81 -> 19096
A58: 5 | B58: =Calculations!I82 -> 11873.635 | C58: =Calculations!J82 -> 134599.38 | D58: =Calculations!K82 -> 26660
A59: 6 | B59: =Calculations!I83 -> 18189.801 | C59: =Calculations!J83 -> 158229.21 | D59: =Calculations!K83 -> 35340
A60: 7 | B60: =Calculations!I84 -> 26013.569 | C60: =Calculations!J84 -> 182144.82 | D60: =Calculations!K84 -> 45136
A61: 8 | B61: =Calculations!I85 -> 35438.41 | C61: =Calculations!J85 -> 206354.67 | D61: =Calculations!K85 -> 56048
A62: 9 | B62: =Calculations!I86 -> 46563.591 | C62: =Calculations!J86 -> 230867.73 | D62: =Calculations!K86 -> 68076
A63: 10 | B63: =Calculations!I87 -> 59494.534 | C63: =Calculations!J87 -> 255693.54 | D63: =Calculations!K87 -> 81220
A64: 11 | B64: =Calculations!I88 -> 74343.195 | C64: =Calculations!J88 -> 280842.26 | D64: =Calculations!K88 -> 95480
A65: 12 | B65: =Calculations!I89 -> 91228.473 | C65: =Calculations!J89 -> 306324.67 | D65: =Calculations!K89 -> 110856
A66: 13 | B66: =Calculations!I90 -> 110276.64 | C66: =Calculations!J90 -> 332152.29 | D66: =Calculations!K90 -> 127348
A67: 14 | B67: =Calculations!I91 -> 131621.79 | C67: =Calculations!J91 -> 358337.36 | D67: =Calculations!K91 -> 144956
... A73: 20 | B73: =Calculations!I97 -> 298306.35 | C73: =Calculations!J97 -> 523752.55 | D73: =Calculations!K97 -> 228390.38

Sheet Optimizer
A1: ALLOCATION OPTIMIZER
A2: Find the optimal split of your excess cash across Extra Repayments, Salary Sacrifice, and Offset Account
A3: ✏️ Blue = YOUR INPUT 🔒 Grey = CALCULATED
A5: YOUR ALLOCATION | F5: BLENDED RESULT
A6: Strategy | B6: % of Cash | C6: Annual $ | D6: Monthly $ | F6: Metric | G6: 5 Years | H6: 10 Years | I6: 20 Years
A7: A: Extra Loan Repayments | B7: 0.5 | C7: =B7*Inputs!C83 -> 9000 | D7: =C7/12 -> 750 | F7: Blended Net Wealth Gain | G7: =B7*Dashboard!B26+B8*Dashboard!B27+B9*Dashboard!B28 -> 73236.508 | H7: =B7*Dashboard!C26+B8*Dashboard!C27+B9*Dashboard!C28 -> 157594.04 | I7: =B7*Dashboard!D26+B8*Dashboard!D27+B9*Dashboard!D28 -> 411029.45
A8: B: Salary Sacrifice (Excess) | B8: 0.5 | C8: =B8*Inputs!C83 -> 9000 | D8: =C8/12 -> 750
A9: C: Offset Account | B9: 0 | C9: =B9*Inputs!C83 -> 0 | D9: =C9/12 -> 0 | F9: vs 100% Extra Repay (A) | G9: =G7-Dashboard!B26 -> 61362.872 | H9: =H7-Dashboard!C26 -> 98099.504 | I9: =I7-Dashboard!D26 -> 112723.1
F10: vs 100% Salary Sacrifice (B) | G10: =G7-Dashboard!B27 -> -61362.872 | H10: =H7-Dashboard!C27 -> -98099.504 | I10: =I7-Dashboard!D27 -> -112723.1
A11: Total Allocation | B11: =B7+B8+B9 -> 1 | C11: =C7+C8+C9 -> 18000 | D11: =D7+D8+D9 -> 1500 | F11: vs 100% Offset (C) | G11: =G7-Dashboard!B28 -> 46576.508 | H11: =H7-Dashboard!C28 -> 76374.038 | I11: =I7-Dashboard!D28 -> 182639.07
A12: =IF(ABS(B11-1)>0.001,"⚠️ Allocations must sum to 100%","✅ Allocation valid") -> ✅ Allocation valid
F13: Best Pure Scenario | G13: =Dashboard!B29 -> B | H13: =Dashboard!C29 -> B | I13: =Dashboard!D29 -> B
A14: Effective SS Amount (Year 1) | C14: =MIN(C8/(1-Inputs!C29),Inputs!C50) -> 14754.098 | D14: Capped at carry-forward | F14: Blended beats best pure? | G14: =IF(G7>=MAX(Dashboard!B26:B28),"✅ YES","❌ NO") -> ❌ NO | H14: =IF(H7>=MAX(Dashboard!C26:C28),"✅ YES","❌ NO") -> ❌ NO | I14: =IF(I7>=MAX(Dashboard!D26:D28),"✅ YES","❌ NO") -> ❌ NO
A16: OPTIMISATION MATRIX — 20-YEAR NET WEALTH GAIN BY ALLOCATION SPLIT
A17: % → Extra Repay (A) ↓ | % → Salary Sacrifice (B) →
A18: Remainder → Offset (C) | B18: 0 | C18: 0.1 | D18: 0.2 | E18: 0.3 | F18: 0.4 | G18: 0.5 | H18: 1
B19: 0% SS | C19: 10% SS | D19: 20% SS | E19: 30% SS | F19: 40% SS | G19: 50% SS | H19: 100% SS
A20: 0% Repay | B20: =IF($K20+B$18>1,"",($K20*Dashboard!$D$26)+(B$18*Dashboard!$D$27)+((1-$K20-B$18)*Dashboard!$D$28)) -> 228390.38 | C20: =IF($K20+C$18>1,"",($K20*Dashboard!$D$26)+(C$18*Dashboard!$D$27)+((1-$K20-C$18)*Dashboard!$D$28)) -> 257926.6 | D20: =IF($K20+D$18>1,"",($K20*Dashboard!$D$26)+(D$18*Dashboard!$D$27)+((1-$K20-D$18)*Dashboard!$D$28)) -> 287462.82 | E20: =IF($K20+E$18>1,"",($K20*Dashboard!$D$26)+(E$18*Dashboard!$D$27)+((1-$K20-E$18)*Dashboard!$D$28)) -> 316999.03 | F20: =IF($K20+F$18>1,"",($K20*Dashboard!$D$26)+(F$18*Dashboard!$D$27)+((1-$K20-F$18)*Dashboard!$D$28)) -> 346535.25 | G20: =IF($K20+G$18>1,"",($K20*Dashboard!$D$26)+(G$18*Dashboard!$D$27)+((1-$K20-G$18)*Dashboard!$D$28)) -> 376071.47 | H20: =IF($K20+H$18>1,"",($K20*Dashboard!$D$26)+(H$18*Dashboard!$D$27)+((1-$K20-H$18)*Dashboard!$D$28)) -> 523752.55 | K20: 0
A21: 10% Repay | B21: =IF($K21+B$18>1,"",($K21*Dashboard!$D$26)+(B$18*Dashboard!$D$27)+((1-$K21-B$18)*Dashboard!$D$28)) -> 235381.98 | C21: =IF($K21+C$18>1,"",($K21*Dashboard!$D$26)+(C$18*Dashboard!$D$27)+((1-$K21-C$18)*Dashboard!$D$28)) -> 264918.2 | D21: =IF($K21+D$18>1,"",($K21*Dashboard!$D$26)+(D$18*Dashboard!$D$27)+((1-$K21-D$18)*Dashboard!$D$28)) -> 294454.41 | E21: =IF($K21+E$18>1,"",($K21*Dashboard!$D$26)+(E$18*Dashboard!$D$27)+((1-$K21-E$18)*Dashboard!$D$28)) -> 323990.63 | F21: =IF($K21+F$18>1,"",($K21*Dashboard!$D$26)+(F$18*Dashboard!$D$27)+((1-$K21-F$18)*Dashboard!$D$28)) -> 353526.85 | G21: =IF($K21+G$18>1,"",($K21*Dashboard!$D$26)+(G$18*Dashboard!$D$27)+((1-$K21-G$18)*Dashboard!$D$28)) -> 383063.06 | H21: =IF($K21+H$18>1,"",($K21*Dashboard!$D$26)+(H$18*Dashboard!$D$27)+((1-$K21-H$18)*Dashboard!$D$28)) | K21: 0.1
A22: 20% Repay | B22: =IF($K22+B$18>1,"",($K22*Dashboard!$D$26)+(B$18*Dashboard!$D$27)+((1-$K22-B$18)*Dashboard!$D$28)) -> 242373.58 | C22: =IF($K22+C$18>1,"",($K22*Dashboard!$D$26)+(C$18*Dashboard!$D$27)+((1-$K22-C$18)*Dashboard!$D$28)) -> 271909.79 | D22: =IF($K22+D$18>1,"",($K22*Dashboard!$D$26)+(D$18*Dashboard!$D$27)+((1-$K22-D$18)*Dashboard!$D$28)) -> 301446.01 | E22: =IF($K22+E$18>1,"",($K22*Dashboard!$D$26)+(E$18*Dashboard!$D$27)+((1-$K22-E$18)*Dashboard!$D$28)) -> 330982.23 | F22: =IF($K22+F$18>1,"",($K22*Dashboard!$D$26)+(F$18*Dashboard!$D$27)+((1-$K22-F$18)*Dashboard!$D$28)) -> 360518.44 | G22: =IF($K22+G$18>1,"",($K22*Dashboard!$D$26)+(G$18*Dashboard!$D$27)+((1-$K22-G$18)*Dashboard!$D$28)) -> 390054.66 | H22: =IF($K22+H$18>1,"",($K22*Dashboard!$D$26)+(H$18*Dashboard!$D$27)+((1-$K22-H$18)*Dashboard!$D$28)) | K22: 0.2
A23: 30% Repay | B23: =IF($K23+B$18>1,"",($K23*Dashboard!$D$26)+(B$18*Dashboard!$D$27)+((1-$K23-B$18)*Dashboard!$D$28)) -> 249365.17 | C23: =IF($K23+C$18>1,"",($K23*Dashboard!$D$26)+(C$18*Dashboard!$D$27)+((1-$K23-C$18)*Dashboard!$D$28)) -> 278901.39 | D23: =IF($K23+D$18>1,"",($K23*Dashboard!$D$26)+(D$18*Dashboard!$D$27)+((1-$K23-D$18)*Dashboard!$D$28)) -> 308437.61 | E23: =IF($K23+E$18>1,"",($K23*Dashboard!$D$26)+(E$18*Dashboard!$D$27)+((1-$K23-E$18)*Dashboard!$D$28)) -> 337973.82 | F23: =IF($K23+F$18>1,"",($K23*Dashboard!$D$26)+(F$18*Dashboard!$D$27)+((1-$K23-F$18)*Dashboard!$D$28)) -> 367510.04 | G23: =IF($K23+G$18>1,"",($K23*Dashboard!$D$26)+(G$18*Dashboard!$D$27)+((1-$K23-G$18)*Dashboard!$D$28)) -> 397046.26 | H23: =IF($K23+H$18>1,"",($K23*Dashboard!$D$26)+(H$18*Dashboard!$D$27)+((1-$K23-H$18)*Dashboard!$D$28)) | K23: 0.3
A24: 40% Repay | B24: =IF($K24+B$18>1,"",($K24*Dashboard!$D$26)+(B$18*Dashboard!$D$27)+((1-$K24-B$18)*Dashboard!$D$28)) -> 256356.77 | C24: =IF($K24+C$18>1,"",($K24*Dashboard!$D$26)+(C$18*Dashboard!$D$27)+((1-$K24-C$18)*Dashboard!$D$28)) -> 285892.99 | D24: =IF($K24+D$18>1,"",($K24*Dashboard!$D$26)+(D$18*Dashboard!$D$27)+((1-$K24-D$18)*Dashboard!$D$28)) -> 315429.2 | E24: =IF($K24+E$18>1,"",($K24*Dashboard!$D$26)+(E$18*Dashboard!$D$27)+((1-$K24-E$18)*Dashboard!$D$28)) -> 344965.42 | F24: =IF($K24+F$18>1,"",($K24*Dashboard!$D$26)+(F$18*Dashboard!$D$27)+((1-$K24-F$18)*Dashboard!$D$28)) -> 374501.64 | G24: =IF($K24+G$18>1,"",($K24*Dashboard!$D$26)+(G$18*Dashboard!$D$27)+((1-$K24-G$18)*Dashboard!$D$28)) -> 404037.85 | H24: =IF($K24+H$18>1,"",($K24*Dashboard!$D$26)+(H$18*Dashboard!$D$27)+((1-$K24-H$18)*Dashboard!$D$28)) | K24: 0.4
A25: 50% Repay | B25: =IF($K25+B$18>1,"",($K25*Dashboard!$D$26)+(B$18*Dashboard!$D$27)+((1-$K25-B$18)*Dashboard!$D$28)) -> 263348.37 | C25: =IF($K25+C$18>1,"",($K25*Dashboard!$D$26)+(C$18*Dashboard!$D$27)+((1-$K25-C$18)*Dashboard!$D$28)) -> 292884.58 | D25: =IF($K25+D$18>1,"",($K25*Dashboard!$D$26)+(D$18*Dashboard!$D$27)+((1-$K25-D$18)*Dashboard!$D$28)) -> 322420.8 | E25: =IF($K25+E$18>1,"",($K25*Dashboard!$D$26)+(E$18*Dashboard!$D$27)+((1-$K25-E$18)*Dashboard!$D$28)) -> 351957.02 | F25: =IF($K25+F$18>1,"",($K25*Dashboard!$D$26)+(F$18*Dashboard!$D$27)+((1-$K25-F$18)*Dashboard!$D$28)) -> 381493.23 | G25: =IF($K25+G$18>1,"",($K25*Dashboard!$D$26)+(G$18*Dashboard!$D$27)+((1-$K25-G$18)*Dashboard!$D$28)) -> 411029.45 | H25: =IF($K25+H$18>1,"",($K25*Dashboard!$D$26)+(H$18*Dashboard!$D$27)+((1-$K25-H$18)*Dashboard!$D$28)) | K25: 0.5
A26: 60% Repay | B26: =IF($K26+B$18>1,"",($K26*Dashboard!$D$26)+(B$18*Dashboard!$D$27)+((1-$K26-B$18)*Dashboard!$D$28)) -> 270339.96 | C26: =IF($K26+C$18>1,"",($K26*Dashboard!$D$26)+(C$18*Dashboard!$D$27)+((1-$K26-C$18)*Dashboard!$D$28)) -> 299876.18 | D26: =IF($K26+D$18>1,"",($K26*Dashboard!$D$26)+(D$18*Dashboard!$D$27)+((1-$K26-D$18)*Dashboard!$D$28)) -> 329412.4 | E26: =IF($K26+E$18>1,"",($K26*Dashboard!$D$26)+(E$18*Dashboard!$D$27)+((1-$K26-E$18)*Dashboard!$D$28)) -> 358948.61 | F26: =IF($K26+F$18>1,"",($K26*Dashboard!$D$26)+(F$18*Dashboard!$D$27)+((1-$K26-F$18)*Dashboard!$D$28)) -> 388484.83 | G26: =IF($K26+G$18>1,"",($K26*Dashboard!$D$26)+(G$18*Dashboard!$D$27)+((1-$K26-G$18)*Dashboard!$D$28)) | H26: =IF($K26+H$18>1,"",($K26*Dashboard!$D$26)+(H$18*Dashboard!$D$27)+((1-$K26-H$18)*Dashboard!$D$28)) | K26: 0.6
A27: 70% Repay | B27: =IF($K27+B$18>1,"",($K27*Dashboard!$D$26)+(B$18*Dashboard!$D$27)+((1-$K27-B$18)*Dashboard!$D$28)) -> 277331.56 | C27: =IF($K27+C$18>1,"",($K27*Dashboard!$D$26)+(C$18*Dashboard!$D$27)+((1-$K27-C$18)*Dashboard!$D$28)) -> 306867.78 | D27: =IF($K27+D$18>1,"",($K27*Dashboard!$D$26)+(D$18*Dashboard!$D$27)+((1-$K27-D$18)*Dashboard!$D$28)) -> 336403.99 | E27: =IF($K27+E$18>1,"",($K27*Dashboard!$D$26)+(E$18*Dashboard!$D$27)+((1-$K27-E$18)*Dashboard!$D$28)) -> 365940.21 | F27: =IF($K27+F$18>1,"",($K27*Dashboard!$D$26)+(F$18*Dashboard!$D$27)+((1-$K27-F$18)*Dashboard!$D$28)) | G27: =IF($K27+G$18>1,"",($K27*Dashboard!$D$26)+(G$18*Dashboard!$D$27)+((1-$K27-G$18)*Dashboard!$D$28)) | H27: =IF($K27+H$18>1,"",($K27*Dashboard!$D$26)+(H$18*Dashboard!$D$27)+((1-$K27-H$18)*Dashboard!$D$28)) | K27: 0.7
A28: 80% Repay | B28: =IF($K28+B$18>1,"",($K28*Dashboard!$D$26)+(B$18*Dashboard!$D$27)+((1-$K28-B$18)*Dashboard!$D$28)) -> 284323.16 | C28: =IF($K28+C$18>1,"",($K28*Dashboard!$D$26)+(C$18*Dashboard!$D$27)+((1-$K28-C$18)*Dashboard!$D$28)) -> 313859.37 | D28: =IF($K28+D$18>1,"",($K28*Dashboard!$D$26)+(D$18*Dashboard!$D$27)+((1-$K28-D$18)*Dashboard!$D$28)) -> 343395.59 | E28: =IF($K28+E$18>1,"",($K28*Dashboard!$D$26)+(E$18*Dashboard!$D$27)+((1-$K28-E$18)*Dashboard!$D$28)) | F28: =IF($K28+F$18>1,"",($K28*Dashboard!$D$26)+(F$18*Dashboard!$D$27)+((1-$K28-F$18)*Dashboard!$D$28)) | G28: =IF($K28+G$18>1,"",($K28*Dashboard!$D$26)+(G$18*Dashboard!$D$27)+((1-$K28-G$18)*Dashboard!$D$28)) | H28: =IF($K28+H$18>1,"",($K28*Dashboard!$D$26)+(H$18*Dashboard!$D$27)+((1-$K28-H$18)*Dashboard!$D$28)) | K28: 0.8
A29: 90% Repay | B29: =IF($K29+B$18>1,"",($K29*Dashboard!$D$26)+(B$18*Dashboard!$D$27)+((1-$K29-B$18)*Dashboard!$D$28)) -> 291314.75 | C29: =IF($K29+C$18>1,"",($K29*Dashboard!$D$26)+(C$18*Dashboard!$D$27)+((1-$K29-C$18)*Dashboard!$D$28)) -> 320850.97 | D29: =IF($K29+D$18>1,"",($K29*Dashboard!$D$26)+(D$18*Dashboard!$D$27)+((1-$K29-D$18)*Dashboard!$D$28)) | E29: =IF($K29+E$18>1,"",($K29*Dashboard!$D$26)+(E$18*Dashboard!$D$27)+((1-$K29-E$18)*Dashboard!$D$28)) | F29: =IF($K29+F$18>1,"",($K29*Dashboard!$D$26)+(F$18*Dashboard!$D$27)+((1-$K29-F$18)*Dashboard!$D$28)) | G29: =IF($K29+G$18>1,"",($K29*Dashboard!$D$26)+(G$18*Dashboard!$D$27)+((1-$K29-G$18)*Dashboard!$D$28)) | H29: =IF($K29+H$18>1,"",($K29*Dashboard!$D$26)+(H$18*Dashboard!$D$27)+((1-$K29-H$18)*Dashboard!$D$28)) | K29: 0.9
A30: 100% Repay | B30: =IF($K30+B$18>1,"",($K30*Dashboard!$D$26)+(B$18*Dashboard!$D$27)+((1-$K30-B$18)*Dashboard!$D$28)) -> 298306.35 | C30: =IF($K30+C$18>1,"",($K30*Dashboard!$D$26)+(C$18*Dashboard!$D$27)+((1-$K30-C$18)*Dashboard!$D$28)) | D30: =IF($K30+D$18>1,"",($K30*Dashboard!$D$26)+(D$18*Dashboard!$D$27)+((1-$K30-D$18)*Dashboard!$D$28)) | E30: =IF($K30+E$18>1,"",($K30*Dashboard!$D$26)+(E$18*Dashboard!$D$27)+((1-$K30-E$18)*Dashboard!$D$28)) | F30: =IF($K30+F$18>1,"",($K30*Dashboard!$D$26)+(F$18*Dashboard!$D$27)+((1-$K30-F$18)*Dashboard!$D$28)) | G30: =IF($K30+G$18>1,"",($K30*Dashboard!$D$26)+(G$18*Dashboard!$D$27)+((1-$K30-G$18)*Dashboard!$D$28)) | H30: =IF($K30+H$18>1,"",($K30*Dashboard!$D$26)+(H$18*Dashboard!$D$27)+((1-$K30-H$18)*Dashboard!$D$28)) | K30: 1
A32: OPTIMAL ALLOCATION (20-YEAR HORIZON) | F32: LOAN PAYOFF SPEED
A33: Max 20-Year Net Wealth | C33: =MAX(B20:H30) -> 523752.55 | F33: Fastest Loan Payoff | H33: =MIN(Dashboard!G26,Dashboard!G27) -> 18 | I33: years
A34: Best Split | C34: ="100% Salary Sacrifice (B)" -> 100% Salary Sacrifice (B) | F34: via 100% Extra Repay (A)
A36: LIQUIDITY-ADJUSTED VIEW | F36: KEY TRADE-OFFS
A37: Metric | B37: Extra Repay | C37: Salary Sacrifice | D37: Offset | F37: Factor | G37: Extra Repay | H37: Salary Sacrifice | I37: Offset
A38: 20-Year Net Wealth | B38: =Dashboard!D26 -> 298306.35 | C38: =Dashboard!D27 -> 523752.55 | D38: =Dashboard!D28 -> 228390.38 | F38: Liquidity | G38: 🟡 Reduces debt | H38: 🔴 Locked until 60 | I38: 🟢 Fully liquid
A39: Accessible Wealth | B39: =B38 -> 298306.35 | C39: =Dashboard!D27-Calculations!E97 -> 48200.194 | D39: =D38 -> 228390.38 | F39: Risk Reduction | G39: 🟢 Reduces debt risk | H39: 🟡 Market risk | I39: 🟢 Reduces interest
A40: Locked in Super | B40: - | C40: =Calculations!E97 -> 475552.35 | D40: - | F40: Tax Benefit | G40: None | H40: =TEXT(Inputs!C93,"$0.00")&"/$ saved" -> $0.24/$ saved | I40: Indirect (interest)
A41: Best for Accessible Wealth? | B41: =IF(B39>=MAX(B39,C39,D39),"⭐","") -> ⭐ | C41: =IF(C39>=MAX(B39,C39,D39),"⭐","") | D41: =IF(D39>=MAX(B39,C39,D39),"⭐","") | F41: Flexibility | G41: 🟡 Can't undo | H41: 🔴 Irreversible | I41: 🟢 Fully reversible
A43: RECOMMENDED STRATEGY
A44: =IF(Dashboard!D29="B","1. Salary sacrifice $"&TEXT(Inputs!C50,"#,##0")&" in Year 1 (use carry-forward cap). Tax saving: $"&TEXT(Calculations!I30,"#,##0"),"1. Direct all $"&TEXT(Inputs!C83,"#,##0")&"/yr to "&IF(Dashboard!D29="A","extra loan repayments","offset account")) -> 1. Salary sacrifice $37,750 in Year 1 (use carry-forward cap). Tax saving: $7,640
A45: =IF(Dashboard!D29="B","2. From Year 2 onward, redirect $"&TEXT(Inputs!C82,"#,##0")&"/mo to extra loan repayments (loan pays off in ~"&TEXT(Dashboard!G27,"0")&" years)","2. Continue until loan is paid off in ~"&TEXT(Dashboard!G26,"0")&" years") -> 2. From Year 2 onward, redirect $1,500/mo to extra loan repayments (loan pays off in ~>20 years)
A46: ="3. Total 20-year net wealth gain: $"&TEXT(MAX(Dashboard!D26:D28),"#,##0")&" ("&Dashboard!D29&" strategy). Extra super from SS: $"&TEXT(Calculations!E97,"#,##0")&" (locked until age "&TEXT(Inputs!C9,"0")&")" -> 3. Total 20-year net wealth gain: $523,753 (B strategy). Extra super from SS: $475,552 (locked until age 60)
A48: AUTO-OPTIMIZER | K48: HELPER CALCS
A49: Select your priority below. The optimizer calculates the best allocation using formulas — no macro needed. | K49: Horizon Lookup | M49: A: Repay | N49: B: SS | O49: C: Offset
K50: Total Wealth | M50: =IF(B56=5,Dashboard!B26,IF(B56=10,Dashboard!C26,Dashboard!D26)) -> 59494.534 | N50: =IF(B56=5,Dashboard!B27,IF(B56=10,Dashboard!C27,Dashboard!D27)) -> 255693.54 | O50: =IF(B56=5,Dashboard!B28,IF(B56=10,Dashboard!C28,Dashboard!D28)) -> 81220
A51: YOUR PRIORITY | B51: Selection | F51: HOW IT WORKS | K51: Accessible Wealth | M51: =M50 -> 59494.534 | N51: =N50-IF(B56=20,Calculations!E97,IF(B56=10,Calculations!H87-Calculations!B87,Calculations!H82-Calculations!B82)) -> 578959.26 | O51: =O50 -> 81220
A52: Optimisation Goal | B52: 1 | F52: 1 = Max total wealth (includes locked super) | K52: Payoff Score | M52: =1/Dashboard!G26 -> 0.055555556 | N52: =1/Dashboard!G27 -> #VALUE! | O52: =1/Dashboard!G28 -> 0.04
F53: 2 = Max accessible wealth (excludes locked super) | K53: Goal 1 Winner | M53: =IF(AND(M50=MAX(M50:O50),M50>N50),1,0) -> 0 | N53: =IF(N50=MAX(M50:O50),1,0) -> 1 | O53: =IF(AND(O50=MAX(M50:O50),M53=0,N53=0),1,0) -> 0
F54: 3 = Fastest loan payoff | K54: Goal 2 Winner | M54: =IF(AND(M51=MAX(M51:O51),M51>N51),1,0) -> 0 | N54: =IF(N51=MAX(M51:O51),1,0) -> 1 | O54: =IF(AND(O51=MAX(M51:O51),M54=0,N54=0),1,0) -> 0
F55: 4 = Balanced (equal weight: wealth + liquidity + payoff speed) | K55: Goal 3 Winner | M55: =IF(AND(M52=MAX(M52:O52),M51>=MAX(N51,O51)),1,0) -> #VALUE! | N55: =IF(AND(N52=MAX(M52:O52),N51>M51),1,IF(AND(N52=MAX(M52:O52),M55<>1),1,0)) -> #VALUE! | O55: =IF(AND(O52=MAX(M52:O52),M55=0,N55=0),1,0) -> #VALUE!
A56: Horizon | B56: 10 | C56: years | F56: Enter 5, 10, or 20 to match your analysis horizons | K56: Goal 4 (Balanced) | M56: =(M50/MAX(M50:O50)+M51/MAX(M51:O51)+M52/MAX(M52:O52))/3 -> #VALUE! | N56: =(N50/MAX(M50:O50)+N51/MAX(M51:O51)+N52/MAX(M52:O52))/3 -> #VALUE! | O56: =(O50/MAX(M50:O50)+O51/MAX(M51:O51)+O52/MAX(M52:O52))/3 -> #VALUE!
K57: Goal 4 Winner | M57: =IF(M56=MAX(M56:O56),1,0) -> #VALUE! | N57: =IF(N56=MAX(M56:O56),1,0) -> #VALUE! | O57: =IF(O56=MAX(M56:O56),1,0) -> #VALUE!
A58: OPTIMISED RESULT | K58: Final Winner | M58: =IF(B52=1,M53,IF(B52=2,M54,IF(B52=3,M55,M57))) -> 0 | N58: =IF(B52=1,N53,IF(B52=2,N54,IF(B52=3,N55,N57))) -> 1 | O58: =IF(B52=1,O53,IF(B52=2,O54,IF(B52=3,O55,O57))) -> 0
A59: Strategy | B59: Optimal % | C59: Annual $ | D59: Monthly $ | F59: Metric | G59: Value
A60: A: Extra Loan Repayments | B60: =M58 -> 0 | C60: =B60*Inputs!C83 -> 0 | D60: =C60/12 -> 0 | F60: Net Wealth Gain | G60: =B60*IF(B56=5,Dashboard!B26,IF(B56=10,Dashboard!C26,Dashboard!D26))+B61*IF(B56=5,Dashboard!B27,IF(B56=10,Dashboard!C27,Dashboard!D27))+B62*IF(B56=5,Dashboard!B28,IF(B56=10,Dashboard!C28,Dashboard!D28)) -> 255693.54
A61: B: Salary Sacrifice | B61: =N58 -> 1 | C61: =B61*Inputs!C83 -> 18000 | D61: =C61/12 -> 1500 | F61: Accessible Wealth | G61: =G60-IF(B61=1,IF(B56=20,Calculations!E97,IF(B56=10,Calculations!H87-Calculations!B87,Calculations!H82-Calculations!B82)),0) -> 578959.26
A62: C: Offset Account | B62: =O58 -> 0 | C62: =B62*Inputs!C83 -> 0 | D62: =C62/12 -> 0 | F62: Locked in Super | G62: =IF(B61=1,IF(B56=20,Calculations!E97,IF(B56=10,Calculations!H87-Calculations!B87,Calculations!H82-Calculations!B82)),0) -> -323265.72
A63: Total | B63: =B60+B61+B62 -> 1 | C63: =C60+C61+C62 -> 18000 | D63: =D60+D61+D62 -> 1500 | F63: Optimisation Goal | G63: =IF(B52=1,"Max Total Wealth",IF(B52=2,"Max Accessible Wealth",IF(B52=3,"Fastest Loan Payoff","Balanced (weighted)"))) -> Max Total Wealth
A65: =IF(B61=1,"→ Salary sacrifice $"&TEXT(MIN(Inputs!C83/(1-Inputs!C29),Inputs!C50),"#,##0")&" in Year 1, then redirect all $"&TEXT(Inputs!C82,"#,##0")&"/mo to extra loan repayments from Year 2",IF(B60=1,"→ Direct all $"&TEXT(Inputs!C82,"#,##0")&"/mo ($"&TEXT(Inputs!C83,"#,##0")&"/yr) to extra loan repayments for fastest debt reduction","→ Deposit all $"&TEXT(Inputs!C82,"#,##0")&"/mo ($"&TEXT(Inputs!C83,"#,##0")&"/yr) into your offset account for maximum liquidity")) -> → Salary sacrifice $29,508 in Year 1, then redirect all $1,500/mo to extra loan repayments from Year 2
A66: ="Net wealth gain at "&TEXT(B56,"0")&" years: $"&TEXT(G60,"#,##0")&IF(G62>0," (of which $"&TEXT(G62,"#,##0")&" locked in super until age "&TEXT(Inputs!C9,"0")&")","") -> Net wealth gain at 10 years: $255,694
A67: ="Optimised for: "&G63 -> Optimised for: Max Total Wealth

Sheet Calculations
A1: CALCULATIONS
A2: Year-by-year projections. All formulas reference the Inputs tab. Blue = scenario-specific inputs.
A4: SCENARIO A: EXTRA LOAN REPAYMENTS
A5: Year | B5: Loan Balance (Start) | C5: Interest Accrued | D5: Min Annual Repayment | E5: Extra Annual Repayment | F5: Total Annual Repayment | G5: Principal Repaid | H5: Loan Balance (End) | I5: Baseline Interest (No Extra) | J5: Interest Saved This Year | K5: Cumulative Interest Saved | L5: Baseline Loan Balance (No Extra)
A6: 1 | B6: =Inputs!$C$68 -> 1000000 | C6: =B6*Inputs!$C$69 -> 62000 | D6: =Inputs!$C$73*12 -> 78789.852 | E6: =MIN(Inputs!$C$83,MAX(0,B6+C6-D6)) -> 18000 | F6: =D6+E6 -> 96789.852 | G6: =MIN(B6,F6-C6) -> 34789.852 | H6: =MAX(0,B6-G6) -> 965210.15 | I6: =L6*Inputs!$C$69 -> 62000 | J6: =I6-C6 -> 0 | K6: =J6 -> 0 | L6: =Inputs!$C$68 -> 1000000
A7: 2 | B7: =H6 -> 965210.15 | C7: =B7*Inputs!$C$69 -> 59843.029 | D7: =IF(B7>0,Inputs!$C$73*12,0) -> 78789.852 | E7: =IF(B7>0,MIN(Inputs!$C$83,MAX(0,B7+C7-D7)),0) -> 18000 | F7: =D7+E7 -> 96789.852 | G7: =MIN(B7,F7-C7) -> 36946.822 | H7: =MAX(0,B7-G7) -> 928263.33 | I7: =IF(L7>0,L7*Inputs!$C$69,0) -> 60959.029 | J7: =I7-C7 -> 1116 | K7: =K6+J7 -> 1116 | L7: =MAX(0,L6*(1+Inputs!$C$69)-Inputs!$C$73*12) -> 983210.15
A8: 3 | B8: =H7 -> 928263.33 | C8: =B8*Inputs!$C$69 -> 57552.326 | D8: =IF(B8>0,Inputs!$C$73*12,0) -> 78789.852 | E8: =IF(B8>0,MIN(Inputs!$C$83,MAX(0,B8+C8-D8)),0) -> 18000 | F8: =D8+E8 -> 96789.852 | G8: =MIN(B8,F8-C8) -> 39237.525 | H8: =MAX(0,B8-G8) -> 889025.8 | I8: =IF(L8>0,L8*Inputs!$C$69,0) -> 59853.518 | J8: =I8-C8 -> 2301.192 | K8: =K7+J8 -> 3417.192 | L8: =MAX(0,L7*(1+Inputs!$C$69)-Inputs!$C$73*12) -> 965379.33
A9: 4 | B9: =H8 -> 889025.8 | C9: =B9*Inputs!$C$69 -> 55119.6 | D9: =IF(B9>0,Inputs!$C$73*12,0) -> 78789.852 | E9: =IF(B9>0,MIN(Inputs!$C$83,MAX(0,B9+C9-D9)),0) -> 18000 | F9: =D9+E9 -> 96789.852 | G9: =MIN(B9,F9-C9) -> 41670.252 | H9: =MAX(0,B9-G9) -> 847355.55 | I9: =IF(L9>0,L9*Inputs!$C$69,0) -> 58679.466 | J9: =I9-C9 -> 3559.8659 | K9: =K8+J9 -> 6977.0579 | L9: =MAX(0,L8*(1+Inputs!$C$69)-Inputs!$C$73*12) -> 946442.99
A10: 5 | B10: =H9 -> 847355.55 | C10: =B10*Inputs!$C$69 -> 52536.044 | D10: =IF(B10>0,Inputs!$C$73*12,0) -> 78789.852 | E10: =IF(B10>0,MIN(Inputs!$C$83,MAX(0,B10+C10-D10)),0) -> 18000 | F10: =D10+E10 -> 96789.852 | G10: =MIN(B10,F10-C10) -> 44253.808 | H10: =MAX(0,B10-G10) -> 803101.74 | I10: =IF(L10>0,L10*Inputs!$C$69,0) -> 57432.622 | J10: =I10-C10 -> 4896.5776 | K10: =K9+J10 -> 11873.635 | L10: =MAX(0,L9*(1+Inputs!$C$69)-Inputs!$C$73*12) -> 926332.61
A11: 6 | B11: =H10 -> 803101.74 | C11: =B11*Inputs!$C$69 -> 49792.308 | D11: =IF(B11>0,Inputs!$C$73*12,0) -> 78789.852 | E11: =IF(B11>0,MIN(Inputs!$C$83,MAX(0,B11+C11-D11)),0) -> 18000 | F11: =D11+E11 -> 96789.852 | G11: =MIN(B11,F11-C11) -> 46997.544 | H11: =MAX(0,B11-G11) -> 756104.2 | I11: =IF(L11>0,L11*Inputs!$C$69,0) -> 56108.473 | J11: =I11-C11 -> 6316.1654 | K11: =K10+J11 -> 18189.801 | L11: =MAX(0,L10*(1+Inputs!$C$69)-Inputs!$C$73*12) -> 904975.38
A12: 7 | B12: =H11 -> 756104.2 | C12: =B12*Inputs!$C$69 -> 46878.46 | D12: =IF(B12>0,Inputs!$C$73*12,0) -> 78789.852 | E12: =IF(B12>0,MIN(Inputs!$C$83,MAX(0,B12+C12-D12)),0) -> 18000 | F12: =D12+E12 -> 96789.852 | G12: =MIN(B12,F12-C12) -> 49911.391 | H12: =MAX(0,B12-G12) -> 706192.81 | I12: =IF(L12>0,L12*Inputs!$C$69,0) -> 54702.228 | J12: =I12-C12 -> 7823.7677 | K12: =K11+J12 -> 26013.569 | L12: =MAX(0,L11*(1+Inputs!$C$69)-Inputs!$C$73*12) -> 882294
A13: 8 | B13: =H12 -> 706192.81 | C13: =B13*Inputs!$C$69 -> 43783.954 | D13: =IF(B13>0,Inputs!$C$73*12,0) -> 78789.852 | E13: =IF(B13>0,MIN(Inputs!$C$83,MAX(0,B13+C13-D13)),0) -> 18000 | F13: =D13+E13 -> 96789.852 | G13: =MIN(B13,F13-C13) -> 53005.898 | H13: =MAX(0,B13-G13) -> 653186.91 | I13: =IF(L13>0,L13*Inputs!$C$69,0) -> 53208.795 | J13: =I13-C13 -> 9424.8413 | K13: =K12+J13 -> 35438.41 | L13: =MAX(0,L12*(1+Inputs!$C$69)-Inputs!$C$73*12) -> 858206.38
A14: 9 | B14: =H13 -> 653186.91 | C14: =B14*Inputs!$C$69 -> 40497.588 | D14: =IF(B14>0,Inputs!$C$73*12,0) -> 78789.852 | E14: =IF(B14>0,MIN(Inputs!$C$83,MAX(0,B14+C14-D14)),0) -> 18000 | F14: =D14+E14 -> 96789.852 | G14: =MIN(B14,F14-C14) -> 56292.263 | H14: =MAX(0,B14-G14) -> 596894.65 | I14: =IF(L14>0,L14*Inputs!$C$69,0) -> 51622.77 | J14: =I14-C14 -> 11125.181 | K14: =K13+J14 -> 46563.591 | L14: =MAX(0,L13*(1+Inputs!$C$69)-Inputs!$C$73*12) -> 832625.32
A15: 10 | B15: =H14 -> 596894.65 | C15: =B15*Inputs!$C$69 -> 37007.468 | D15: =IF(B15>0,Inputs!$C$73*12,0) -> 78789.852 | E15: =IF(B15>0,MIN(Inputs!$C$83,MAX(0,B15+C15-D15)),0) -> 18000 | F15: =D15+E15 -> 96789.852 | G15: =MIN(B15,F15-C15) -> 59782.383 | H15: =MAX(0,B15-G15) -> 537112.26 | I15: =IF(L15>0,L15*Inputs!$C$69,0) -> 49938.411 | J15: =I15-C15 -> 12930.943 | K15: =K14+J15 -> 59494.534 | L15: =MAX(0,L14*(1+Inputs!$C$69)-Inputs!$C$73*12) -> 805458.24
A16: 11 | B16: =H15 -> 537112.26 | C16: =B16*Inputs!$C$69 -> 33300.96 | D16: =IF(B16>0,Inputs!$C$73*12,0) -> 78789.852 | E16: =IF(B16>0,MIN(Inputs!$C$83,MAX(0,B16+C16-D16)),0) -> 18000 | F16: =D16+E16 -> 96789.852 | G16: =MIN(B16,F16-C16) -> 63488.891 | H16: =MAX(0,B16-G16) -> 473623.37 | I16: =IF(L16>0,L16*Inputs!$C$69,0) -> 48149.621 | J16: =I16-C16 -> 14848.661 | K16: =K15+J16 -> 74343.195 | L16: =MAX(0,L15*(1+Inputs!$C$69)-Inputs!$C$73*12) -> 776606.8
A17: 12 | B17: =H16 -> 473623.37 | C17: =B17*Inputs!$C$69 -> 29364.649 | D17: =IF(B17>0,Inputs!$C$73*12,0) -> 78789.852 | E17: =IF(B17>0,MIN(Inputs!$C$83,MAX(0,B17+C17-D17)),0) -> 18000 | F17: =D17+E17 -> 96789.852 | G17: =MIN(B17,F17-C17) -> 67425.203 | H17: =MAX(0,B17-G17) -> 406198.17 | I17: =IF(L17>0,L17*Inputs!$C$69,0) -> 46249.927 | J17: =I17-C17 -> 16885.278 | K17: =K16+J17 -> 91228.473 | L17: =MAX(0,L16*(1+Inputs!$C$69)-Inputs!$C$73*12) -> 745966.57
A18: 13 | B18: =H17 -> 406198.17 | C18: =B18*Inputs!$C$69 -> 25184.286 | D18: =IF(B18>0,Inputs!$C$73*12,0) -> 78789.852 | E18: =IF(B18>0,MIN(Inputs!$C$83,MAX(0,B18+C18-D18)),0) -> 18000 | F18: =D18+E18 -> 96789.852 | G18: =MIN(B18,F18-C18) -> 71605.565 | H18: =MAX(0,B18-G18) -> 334592.6 | I18: =IF(L18>0,L18*Inputs!$C$69,0) -> 44232.452 | J18: =I18-C18 -> 19048.165 | K18: =K17+J18 -> 110276.64 | L18: =MAX(0,L17*(1+Inputs!$C$69)-Inputs!$C$73*12) -> 713426.64
... A25: 20 | B25: =H24 -> 0 | C25: =B25*Inputs!$C$69 -> 0 | D25: =IF(B25>0,Inputs!$C$73*12,0) -> 0 | E25: =IF(B25>0,MIN(Inputs!$C$83,MAX(0,B25+C25-D25)),0) -> 0 | F25: =D25+E25 -> 0 | G25: =MIN(B25,F25-C25) -> 0 | H25: =MAX(0,B25-G25) -> 0 | I25: =IF(L25>0,L25*Inputs!$C$69,0) -> 26138.118 | J25: =I25-C25 -> 26138.118 | K25: =K24+J25 -> 298306.35 | L25: =MAX(0,L24*(1+Inputs!$C$69)-Inputs!$C$73*12) -> 421582.55
A26: TOTAL | C26: =SUM(C6:C25) -> 646421.5 | D26: =SUM(D6:D25) -> 1418217.3 | E26: =SUM(E6:E25) -> 306000 | F26: =SUM(F6:F25) -> 1724217.3 | G26: =SUM(G6:G25) -> 1000000 | I26: =SUM(I6:I25) -> 944727.85 | K26: =K25 -> 298306.35
A28: SCENARIO B: SALARY SACRIFICE TO SUPERANNUATION | M28: ADDITIONAL TAX COSTS
A29: Year | B29: Super Balance (Start) | C29: Gross Salary Sacrifice | D29: Contributions Tax (Fund) | E29: Net Added (SS + SG) | F29: Investment Return | G29: Earnings Tax | H29: Super Balance (End) | I29: Tax Saved vs Salary | J29: After-Tax Cost (Pay + Excess Tax) | K29: Residual to Loan | L29: Loan Balance (End) | M29: ATO Excess Tax (Personal) | N29: Excess Contributions | O29: Total Extra Tax (Fund + ATO)
A30: 1 | B30: =Inputs!$C$35 -> 150000 | C30: =(Inputs!$C$83+Inputs!$C$50*(Inputs!$C$29-Inputs!$C$54))/(1-Inputs!$C$54) -> 31835.294 | D30: =MIN(C30,Inputs!$C$50)*Inputs!$C$56+MAX(0,C30-Inputs!$C$50)*Inputs!$C$54 -> 4775.2941 | E30: =(C30-D30)+Inputs!$C$6*(1+Inputs!$C$8)^(A30-1)*Inputs!$C$36*(1-Inputs!$C$56) -> 41722.5 | F30: =(B30+E30)*Inputs!$C$51 -> 1917.225 | G30: =F30*Inputs!$C$52 -> 287.58375 | H30: =B30+E30+F30-G30 -> 193352.14 | I30: =MIN(C30,Inputs!$C$50)*Inputs!$C$29-MIN(C30,Inputs!$C$50)*Inputs!$C$56 -> 7640.4706 | J30: =C30*(1-Inputs!$C$29)+MAX(0,C30-Inputs!$C$50)*(Inputs!$C$29-Inputs!$C$54) -> 19419.529 | K30: =Inputs!$C$83-J30 -> -1419.5294 | L30: =MAX(0,Inputs!$C$68*(1+Inputs!$C$69)-(Inputs!$C$73*12+K30)) -> 984629.68 | M30: =MAX(0,C30-Inputs!$C$50)*(Inputs!$C$29-Inputs!$C$54) -> 0 | N30: =MAX(0,C30-Inputs!$C$50) -> 0 | O30: =D30+M30 -> 4775.2941
A31: 2 | B31: =H30 -> 193352.14 | C31: =(Inputs!$C$83+Inputs!$C$49*(Inputs!$C$29-Inputs!$C$54))/(1-Inputs!$C$54) -> 24776.471 | D31: =MIN(C31,Inputs!$C$49)*Inputs!$C$56+MAX(0,C31-Inputs!$C$49)*Inputs!$C$54 -> 3716.4706 | E31: =(C31-D31)+Inputs!$C$6*(1+Inputs!$C$8)^(A31-1)*Inputs!$C$36*(1-Inputs!$C$56) -> 37188.75 | F31: =(B31+E31)*Inputs!$C$51 -> 2305.4089 | G31: =F31*Inputs!$C$52 -> 345.81134 | H31: =B31+E31+F31-G31 -> 232500.49 | I31: =MIN(C31,Inputs!$C$49)*Inputs!$C$29-MIN(C31,Inputs!$C$49)*Inputs!$C$56 -> 3060 | J31: =C31*(1-Inputs!$C$29)+MAX(0,C31-Inputs!$C$49)*(Inputs!$C$29-Inputs!$C$54) -> 18000 | K31: =Inputs!$C$83-J31 -> 0 | L31: =IF(L30>0,MAX(0,L30*(1+Inputs!$C$69)-(Inputs!$C$73*12+K31)),0) -> 966886.87 | M31: =MAX(0,C31-Inputs!$C$49)*(Inputs!$C$29-Inputs!$C$54) -> 2886.3529 | N31: =MAX(0,C31-Inputs!$C$49) -> 12026.471 | O31: =D31+M31 -> 6602.8235
A32: 3 | B32: =H31 -> 232500.49 | C32: =(Inputs!$C$83+Inputs!$C$49*(Inputs!$C$29-Inputs!$C$54))/(1-Inputs!$C$54) -> 24776.471 | D32: =MIN(C32,Inputs!$C$49)*Inputs!$C$56+MAX(0,C32-Inputs!$C$49)*Inputs!$C$54 -> 3716.4706 | E32: =(C32-D32)+Inputs!$C$6*(1+Inputs!$C$8)^(A32-1)*Inputs!$C$36*(1-Inputs!$C$56) -> 38801.625 | F32: =(B32+E32)*Inputs!$C$51 -> 2713.0211 | G32: =F32*Inputs!$C$52 -> 406.95317 | H32: =B32+E32+F32-G32 -> 273608.18 | I32: =MIN(C32,Inputs!$C$49)*Inputs!$C$29-MIN(C32,Inputs!$C$49)*Inputs!$C$56 -> 3060 | J32: =C32*(1-Inputs!$C$29)+MAX(0,C32-Inputs!$C$49)*(Inputs!$C$29-Inputs!$C$54) -> 18000 | K32: =Inputs!$C$83-J32 -> 0 | L32: =IF(L31>0,MAX(0,L31*(1+Inputs!$C$69)-(Inputs!$C$73*12+K32)),0) -> 948044 | M32: =MAX(0,C32-Inputs!$C$49)*(Inputs!$C$29-Inputs!$C$54) -> 2886.3529 | N32: =MAX(0,C32-Inputs!$C$49) -> 12026.471 | O32: =D32+M32 -> 6602.8235
A33: 4 | B33: =H32 -> 273608.18 | C33: =(Inputs!$C$83+Inputs!$C$49*(Inputs!$C$29-Inputs!$C$54))/(1-Inputs!$C$54) -> 24776.471 | D33: =MIN(C33,Inputs!$C$49)*Inputs!$C$56+MAX(0,C33-Inputs!$C$49)*Inputs!$C$54 -> 3716.4706 | E33: =(C33-D33)+Inputs!$C$6*(1+Inputs!$C$8)^(A33-1)*Inputs!$C$36*(1-Inputs!$C$56) -> 40575.788 | F33: =(B33+E33)*Inputs!$C$51 -> 3141.8397 | G33: =F33*Inputs!$C$52 -> 471.27595 | H33: =B33+E33+F33-G33 -> 316854.53 | I33: =MIN(C33,Inputs!$C$49)*Inputs!$C$29-MIN(C33,Inputs!$C$49)*Inputs!$C$56 -> 3060 | J33: =C33*(1-Inputs!$C$29)+MAX(0,C33-Inputs!$C$49)*(Inputs!$C$29-Inputs!$C$54) -> 18000 | K33: =Inputs!$C$83-J33 -> 0 | L33: =IF(L32>0,MAX(0,L32*(1+Inputs!$C$69)-(Inputs!$C$73*12+K33)),0) -> 928032.88 | M33: =MAX(0,C33-Inputs!$C$49)*(Inputs!$C$29-Inputs!$C$54) -> 2886.3529 | N33: =MAX(0,C33-Inputs!$C$49) -> 12026.471 | O33: =D33+M33 -> 6602.8235
A34: 5 | B34: =H33 -> 316854.53 | C34: =(Inputs!$C$83+Inputs!$C$49*(Inputs!$C$29-Inputs!$C$54))/(1-Inputs!$C$54) -> 24776.471 | D34: =MIN(C34,Inputs!$C$49)*Inputs!$C$56+MAX(0,C34-Inputs!$C$49)*Inputs!$C$54 -> 3716.4706 | E34: =(C34-D34)+Inputs!$C$6*(1+Inputs!$C$8)^(A34-1)*Inputs!$C$36*(1-Inputs!$C$56) -> 42527.366 | F34: =(B34+E34)*Inputs!$C$51 -> 3593.819 | G34: =F34*Inputs!$C$52 -> 539.07285 | H34: =B34+E34+F34-G34 -> 362436.65 | I34: =MIN(C34,Inputs!$C$49)*Inputs!$C$29-MIN(C34,Inputs!$C$49)*Inputs!$C$56 -> 3060 | J34: =C34*(1-Inputs!$C$29)+MAX(0,C34-Inputs!$C$49)*(Inputs!$C$29-Inputs!$C$54) -> 18000 | K34: =Inputs!$C$83-J34 -> 0 | L34: =IF(L33>0,MAX(0,L33*(1+Inputs!$C$69)-(Inputs!$C$73*12+K34)),0) -> 906781.06 | M34: =MAX(0,C34-Inputs!$C$49)*(Inputs!$C$29-Inputs!$C$54) -> 2886.3529 | N34: =MAX(0,C34-Inputs!$C$49) -> 12026.471 | O34: =D34+M34 -> 6602.8235
A35: 6 | B35: =H34 -> 362436.65 | C35: =(Inputs!$C$83+Inputs!$C$49*(Inputs!$C$29-Inputs!$C$54))/(1-Inputs!$C$54) -> 24776.471 | D35: =MIN(C35,Inputs!$C$49)*Inputs!$C$56+MAX(0,C35-Inputs!$C$49)*Inputs!$C$54 -> 3716.4706 | E35: =(C35-D35)+Inputs!$C$6*(1+Inputs!$C$8)^(A35-1)*Inputs!$C$36*(1-Inputs!$C$56) -> 44674.103 | F35: =(B35+E35)*Inputs!$C$51 -> 4071.1075 | G35: =F35*Inputs!$C$52 -> 610.66612 | H35: =B35+E35+F35-G35 -> 410571.19 | I35: =MIN(C35,Inputs!$C$49)*Inputs!$C$29-MIN(C35,Inputs!$C$49)*Inputs!$C$56 -> 3060 | J35: =C35*(1-Inputs!$C$29)+MAX(0,C35-Inputs!$C$49)*(Inputs!$C$29-Inputs!$C$54) -> 18000 | K35: =Inputs!$C$83-J35 -> 0 | L35: =IF(L34>0,MAX(0,L34*(1+Inputs!$C$69)-(Inputs!$C$73*12+K35)),0) -> 884211.64 | M35: =MAX(0,C35-Inputs!$C$49)*(Inputs!$C$29-Inputs!$C$54) -> 2886.3529 | N35: =MAX(0,C35-Inputs!$C$49) -> 12026.471 | O35: =D35+M35 -> 6602.8235
A36: 7 | B36: =H35 -> 410571.19 | C36: =(Inputs!$C$83+Inputs!$C$49*(Inputs!$C$29-Inputs!$C$54))/(1-Inputs!$C$54) -> 24776.471 | D36: =MIN(C36,Inputs!$C$49)*Inputs!$C$56+MAX(0,C36-Inputs!$C$49)*Inputs!$C$54 -> 3716.4706 | E36: =(C36-D36)+Inputs!$C$6*(1+Inputs!$C$8)^(A36-1)*Inputs!$C$36*(1-Inputs!$C$56) -> 47035.513 | F36: =(B36+E36)*Inputs!$C$51 -> 4576.067 | G36: =F36*Inputs!$C$52 -> 686.41005 | H36: =B36+E36+F36-G36 -> 461496.36 | I36: =MIN(C36,Inputs!$C$49)*Inputs!$C$29-MIN(C36,Inputs!$C$49)*Inputs!$C$56 -> 3060 | J36: =C36*(1-Inputs!$C$29)+MAX(0,C36-Inputs!$C$49)*(Inputs!$C$29-Inputs!$C$54) -> 18000 | K36: =Inputs!$C$83-J36 -> 0 | L36: =IF(L35>0,MAX(0,L35*(1+Inputs!$C$69)-(Inputs!$C$73*12+K36)),0) -> 860242.91 | M36: =MAX(0,C36-Inputs!$C$49)*(Inputs!$C$29-Inputs!$C$54) -> 2886.3529 | N36: =MAX(0,C36-Inputs!$C$49) -> 12026.471 | O36: =D36+M36 -> 6602.8235
A37: 8 | B37: =H36 -> 461496.36 | C37: =(Inputs!$C$83+Inputs!$C$49*(Inputs!$C$29-Inputs!$C$54))/(1-Inputs!$C$54) -> 24776.471 | D37: =MIN(C37,Inputs!$C$49)*Inputs!$C$56+MAX(0,C37-Inputs!$C$49)*Inputs!$C$54 -> 3716.4706 | E37: =(C37-D37)+Inputs!$C$6*(1+Inputs!$C$8)^(A37-1)*Inputs!$C$36*(1-Inputs!$C$56) -> 49633.064 | F37: =(B37+E37)*Inputs!$C$51 -> 5111.2942 | G37: =F37*Inputs!$C$52 -> 766.69414 | H37: =B37+E37+F37-G37 -> 515474.02 | I37: =MIN(C37,Inputs!$C$49)*Inputs!$C$29-MIN(C37,Inputs!$C$49)*Inputs!$C$56 -> 3060 | J37: =C37*(1-Inputs!$C$29)+MAX(0,C37-Inputs!$C$49)*(Inputs!$C$29-Inputs!$C$54) -> 18000 | K37: =Inputs!$C$83-J37 -> 0 | L37: =IF(L36>0,MAX(0,L36*(1+Inputs!$C$69)-(Inputs!$C$73*12+K37)),0) -> 834788.12 | M37: =MAX(0,C37-Inputs!$C$49)*(Inputs!$C$29-Inputs!$C$54) -> 2886.3529 | N37: =MAX(0,C37-Inputs!$C$49) -> 12026.471 | O37: =D37+M37 -> 6602.8235
A38: 9 | B38: =H37 -> 515474.02 | C38: =(Inputs!$C$83+Inputs!$C$49*(Inputs!$C$29-Inputs!$C$54))/(1-Inputs!$C$54) -> 24776.471 | D38: =MIN(C38,Inputs!$C$49)*Inputs!$C$56+MAX(0,C38-Inputs!$C$49)*Inputs!$C$54 -> 3716.4706 | E38: =(C38-D38)+Inputs!$C$6*(1+Inputs!$C$8)^(A38-1)*Inputs!$C$36*(1-Inputs!$C$56) -> 52490.371 | F38: =(B38+E38)*Inputs!$C$51 -> 5679.644 | G38: =F38*Inputs!$C$52 -> 851.94659 | H38: =B38+E38+F38-G38 -> 572792.09 | I38: =MIN(C38,Inputs!$C$49)*Inputs!$C$29-MIN(C38,Inputs!$C$49)*Inputs!$C$56 -> 3060 | J38: =C38*(1-Inputs!$C$29)+MAX(0,C38-Inputs!$C$49)*(Inputs!$C$29-Inputs!$C$54) -> 18000 | K38: =Inputs!$C$83-J38 -> 0 | L38: =IF(L37>0,MAX(0,L37*(1+Inputs!$C$69)-(Inputs!$C$73*12+K38)),0) -> 807755.13 | M38: =MAX(0,C38-Inputs!$C$49)*(Inputs!$C$29-Inputs!$C$54) -> 2886.3529 | N38: =MAX(0,C38-Inputs!$C$49) -> 12026.471 | O38: =D38+M38 -> 6602.8235
A39: 10 | B39: =H38 -> 572792.09 | C39: =(Inputs!$C$83+Inputs!$C$49*(Inputs!$C$29-Inputs!$C$54))/(1-Inputs!$C$54) -> 24776.471 | D39: =MIN(C39,Inputs!$C$49)*Inputs!$C$56+MAX(0,C39-Inputs!$C$49)*Inputs!$C$54 -> 3716.4706 | E39: =(C39-D39)+Inputs!$C$6*(1+Inputs!$C$8)^(A39-1)*Inputs!$C$36*(1-Inputs!$C$56) -> 55633.408 | F39: =(B39+E39)*Inputs!$C$51 -> 6284.255 | G39: =F39*Inputs!$C$52 -> 942.63825 | H39: =B39+E39+F39-G39 -> 633767.12 | I39: =MIN(C39,Inputs!$C$49)*Inputs!$C$29-MIN(C39,Inputs!$C$49)*Inputs!$C$56 -> 3060 | J39: =C39*(1-Inputs!$C$29)+MAX(0,C39-Inputs!$C$49)*(Inputs!$C$29-Inputs!$C$54) -> 18000 | K39: =Inputs!$C$83-J39 -> 0 | L39: =IF(L38>0,MAX(0,L38*(1+Inputs!$C$69)-(Inputs!$C$73*12+K39)),0) -> 779046.1 | M39: =MAX(0,C39-Inputs!$C$49)*(Inputs!$C$29-Inputs!$C$54) -> 2886.3529 | N39: =MAX(0,C39-Inputs!$C$49) -> 12026.471 | O39: =D39+M39 -> 6602.8235
A40: 11 | B40: =H39 -> 633767.12 | C40: =(Inputs!$C$83+Inputs!$C$49*(Inputs!$C$29-Inputs!$C$54))/(1-Inputs!$C$54) -> 24776.471 | D40: =MIN(C40,Inputs!$C$49)*Inputs!$C$56+MAX(0,C40-Inputs!$C$49)*Inputs!$C$54 -> 3716.4706 | E40: =(C40-D40)+Inputs!$C$6*(1+Inputs!$C$8)^(A40-1)*Inputs!$C$36*(1-Inputs!$C$56) -> 59090.749 | F40: =(B40+E40)*Inputs!$C$51 -> 6928.5787 | G40: =F40*Inputs!$C$52 -> 1039.2868 | H40: =B40+E40+F40-G40 -> 698747.16 | I40: =MIN(C40,Inputs!$C$49)*Inputs!$C$29-MIN(C40,Inputs!$C$49)*Inputs!$C$56 -> 3060 | J40: =C40*(1-Inputs!$C$29)+MAX(0,C40-Inputs!$C$49)*(Inputs!$C$29-Inputs!$C$54) -> 18000 | K40: =Inputs!$C$83-J40 -> 0 | L40: =IF(L39>0,MAX(0,L39*(1+Inputs!$C$69)-(Inputs!$C$73*12+K40)),0) -> 748557.1 | M40: =MAX(0,C40-Inputs!$C$49)*(Inputs!$C$29-Inputs!$C$54) -> 2886.3529 | N40: =MAX(0,C40-Inputs!$C$49) -> 12026.471 | O40: =D40+M40 -> 6602.8235
A41: 12 | B41: =H40 -> 698747.16 | C41: =(Inputs!$C$83+Inputs!$C$49*(Inputs!$C$29-Inputs!$C$54))/(1-Inputs!$C$54) -> 24776.471 | D41: =MIN(C41,Inputs!$C$49)*Inputs!$C$56+MAX(0,C41-Inputs!$C$49)*Inputs!$C$54 -> 3716.4706 | E41: =(C41-D41)+Inputs!$C$6*(1+Inputs!$C$8)^(A41-1)*Inputs!$C$36*(1-Inputs!$C$56) -> 62893.824 | F41: =(B41+E41)*Inputs!$C$51 -> 7616.4098 | G41: =F41*Inputs!$C$52 -> 1142.4615 | H41: =B41+E41+F41-G41 -> 768114.93 | I41: =MIN(C41,Inputs!$C$49)*Inputs!$C$29-MIN(C41,Inputs!$C$49)*Inputs!$C$56 -> 3060 | J41: =C41*(1-Inputs!$C$29)+MAX(0,C41-Inputs!$C$49)*(Inputs!$C$29-Inputs!$C$54) -> 18000 | K41: =Inputs!$C$83-J41 -> 0 | L41: =IF(L40>0,MAX(0,L40*(1+Inputs!$C$69)-(Inputs!$C$73*12+K41)),0) -> 716177.79 | M41: =MAX(0,C41-Inputs!$C$49)*(Inputs!$C$29-Inputs!$C$54) -> 2886.3529 | N41: =MAX(0,C41-Inputs!$C$49) -> 12026.471 | O41: =D41+M41 -> 6602.8235
A42: 13 | B42: =H41 -> 768114.93 | C42: =(Inputs!$C$83+Inputs!$C$49*(Inputs!$C$29-Inputs!$C$54))/(1-Inputs!$C$54) -> 24776.471 | D42: =MIN(C42,Inputs!$C$49)*Inputs!$C$56+MAX(0,C42-Inputs!$C$49)*Inputs!$C$54 -> 3716.4706 | E42: =(C42-D42)+Inputs!$C$6*(1+Inputs!$C$8)^(A42-1)*Inputs!$C$36*(1-Inputs!$C$56) -> 67077.206 | F42: =(B42+E42)*Inputs!$C$51 -> 8351.9214 | G42: =F42*Inputs!$C$52 -> 1252.7882 | H42: =B42+E42+F42-G42 -> 842291.27 | I42: =MIN(C42,Inputs!$C$49)*Inputs!$C$29-MIN(C42,Inputs!$C$49)*Inputs!$C$56 -> 3060 | J42: =C42*(1-Inputs!$C$29)+MAX(0,C42-Inputs!$C$49)*(Inputs!$C$29-Inputs!$C$54) -> 18000 | K42: =Inputs!$C$83-J42 -> 0 | L42: =IF(L41>0,MAX(0,L41*(1+Inputs!$C$69)-(Inputs!$C$73*12+K42)),0) -> 681790.96 | M42: =MAX(0,C42-Inputs!$C$49)*(Inputs!$C$29-Inputs!$C$54) -> 2886.3529 | N42: =MAX(0,C42-Inputs!$C$49) -> 12026.471 | O42: =D42+M42 -> 6602.8235
... A49: 20 | B49: =H48 -> 1417744.3 | C49: =(Inputs!$C$83+Inputs!$C$49*(Inputs!$C$29-Inputs!$C$54))/(1-Inputs!$C$54) -> 24776.471 | D49: =MIN(C49,Inputs!$C$49)*Inputs!$C$56+MAX(0,C49-Inputs!$C$49)*Inputs!$C$54 -> 3716.4706 | E49: =(C49-D49)+Inputs!$C$6*(1+Inputs!$C$8)^(A49-1)*Inputs!$C$36*(1-Inputs!$C$56) -> 110734.52 | F49: =(B49+E49)*Inputs!$C$51 -> 15284.788 | G49: =F49*Inputs!$C$52 -> 2292.7182 | H49: =B49+E49+F49-G49 -> 1541470.9 | I49: =MIN(C49,Inputs!$C$49)*Inputs!$C$29-MIN(C49,Inputs!$C$49)*Inputs!$C$56 -> 3060 | J49: =C49*(1-Inputs!$C$29)+MAX(0,C49-Inputs!$C$49)*(Inputs!$C$29-Inputs!$C$54) -> 18000 | K49: =Inputs!$C$83-J49 -> 0 | L49: =IF(L48>0,MAX(0,L48*(1+Inputs!$C$69)-(Inputs!$C$73*12+K49)),0) -> 373382.36 | M49: =MAX(0,C49-Inputs!$C$49)*(Inputs!$C$29-Inputs!$C$54) -> 2886.3529 | N49: =MAX(0,C49-Inputs!$C$49) -> 12026.471 | O49: =D49+M49 -> 6602.8235
A50: TOTAL | C50: =SUM(C30:C49) -> 502588.24 | D50: =SUM(D30:D49) -> 75388.235 | E50: =SUM(E30:E49) -> 1266994.7 | F50: =SUM(F30:F49) -> 146442.56 | G50: =SUM(G30:G49) -> 21966.384 | H50: =H49 -> 1541470.9 | I50: =SUM(I30:I49) -> 65780.471 | J50: =SUM(J30:J49) -> 361419.53 | K50: =SUM(K30:K49) -> -1419.5294 | M50: =SUM(M30:M49) -> 54840.706 | N50: =SUM(N30:N49) -> 228502.94 | O50: =SUM(O30:O49) -> 130228.94
A52: SCENARIO C: OFFSET ACCOUNT
A53: Year | B53: Offset Balance (Start) | C53: Annual Deposit | D53: Offset Balance (End) | E53: Loan Balance (Start) | F53: Effective Balance (Loan - Offset) | G53: Interest Paid (With Offset) | H53: Principal Repaid | I53: Loan Balance (End) | J53: Interest Without Offset | K53: Interest Saved This Year | L53: Cumulative Interest Saved
A54: 1 | B54: =Inputs!$C$76 -> 50000 | C54: =Inputs!$C$83 -> 18000 | D54: =B54+C54 -> 68000 | E54: =Inputs!$C$68 -> 1000000 | F54: =MAX(0,E54-B54) -> 950000 | G54: =F54*Inputs!$C$69 -> 58900 | H54: =Inputs!$C$73*12-G54 -> 19889.852 | I54: =MAX(0,E54-H54) -> 980110.15 | J54: =E54*Inputs!$C$69 -> 62000 | K54: =J54-G54 -> 3100 | L54: =K54 -> 3100
A55: 2 | B55: =D54 -> 68000 | C55: =Inputs!$C$83 -> 18000 | D55: =B55+C55 -> 86000 | E55: =I54 -> 980110.15 | F55: =MAX(0,E55-B55) -> 912110.15 | G55: =F55*Inputs!$C$69 -> 56550.829 | H55: =IF(E55>0,Inputs!$C$73*12-G55,0) -> 22239.022 | I55: =MAX(0,E55-H55) -> 957871.13 | J55: =IF(E55>0,E55*Inputs!$C$69,0) -> 60766.829 | K55: =J55-G55 -> 4216 | L55: =L54+K55 -> 7316
A56: 3 | B56: =D55 -> 86000 | C56: =Inputs!$C$83 -> 18000 | D56: =B56+C56 -> 104000 | E56: =I55 -> 957871.13 | F56: =MAX(0,E56-B56) -> 871871.13 | G56: =F56*Inputs!$C$69 -> 54056.01 | H56: =IF(E56>0,Inputs!$C$73*12-G56,0) -> 24733.842 | I56: =MAX(0,E56-H56) -> 933137.28 | J56: =IF(E56>0,E56*Inputs!$C$69,0) -> 59388.01 | K56: =J56-G56 -> 5332 | L56: =L55+K56 -> 12648
A57: 4 | B57: =D56 -> 104000 | C57: =Inputs!$C$83 -> 18000 | D57: =B57+C57 -> 122000 | E57: =I56 -> 933137.28 | F57: =MAX(0,E57-B57) -> 829137.28 | G57: =F57*Inputs!$C$69 -> 51406.512 | H57: =IF(E57>0,Inputs!$C$73*12-G57,0) -> 27383.34 | I57: =MAX(0,E57-H57) -> 905753.94 | J57: =IF(E57>0,E57*Inputs!$C$69,0) -> 57854.512 | K57: =J57-G57 -> 6448 | L57: =L56+K57 -> 19096
A58: 5 | B58: =D57 -> 122000 | C58: =Inputs!$C$83 -> 18000 | D58: =B58+C58 -> 140000 | E58: =I57 -> 905753.94 | F58: =MAX(0,E58-B58) -> 783753.94 | G58: =F58*Inputs!$C$69 -> 48592.745 | H58: =IF(E58>0,Inputs!$C$73*12-G58,0) -> 30197.107 | I58: =MAX(0,E58-H58) -> 875556.84 | J58: =IF(E58>0,E58*Inputs!$C$69,0) -> 56156.745 | K58: =J58-G58 -> 7564 | L58: =L57+K58 -> 26660
A59: 6 | B59: =D58 -> 140000 | C59: =Inputs!$C$83 -> 18000 | D59: =B59+C59 -> 158000 | E59: =I58 -> 875556.84 | F59: =MAX(0,E59-B59) -> 735556.84 | G59: =F59*Inputs!$C$69 -> 45604.524 | H59: =IF(E59>0,Inputs!$C$73*12-G59,0) -> 33185.328 | I59: =MAX(0,E59-H59) -> 842371.51 | J59: =IF(E59>0,E59*Inputs!$C$69,0) -> 54284.524 | K59: =J59-G59 -> 8680 | L59: =L58+K59 -> 35340
A60: 7 | B60: =D59 -> 158000 | C60: =Inputs!$C$83 -> 18000 | D60: =B60+C60 -> 176000 | E60: =I59 -> 842371.51 | F60: =MAX(0,E60-B60) -> 684371.51 | G60: =F60*Inputs!$C$69 -> 42431.034 | H60: =IF(E60>0,Inputs!$C$73*12-G60,0) -> 36358.818 | I60: =MAX(0,E60-H60) -> 806012.69 | J60: =IF(E60>0,E60*Inputs!$C$69,0) -> 52227.034 | K60: =J60-G60 -> 9796 | L60: =L59+K60 -> 45136
A61: 8 | B61: =D60 -> 176000 | C61: =Inputs!$C$83 -> 18000 | D61: =B61+C61 -> 194000 | E61: =I60 -> 806012.69 | F61: =MAX(0,E61-B61) -> 630012.69 | G61: =F61*Inputs!$C$69 -> 39060.787 | H61: =IF(E61>0,Inputs!$C$73*12-G61,0) -> 39729.065 | I61: =MAX(0,E61-H61) -> 766283.63 | J61: =IF(E61>0,E61*Inputs!$C$69,0) -> 49972.787 | K61: =J61-G61 -> 10912 | L61: =L60+K61 -> 56048
A62: 9 | B62: =D61 -> 194000 | C62: =Inputs!$C$83 -> 18000 | D62: =B62+C62 -> 212000 | E62: =I61 -> 766283.63 | F62: =MAX(0,E62-B62) -> 572283.63 | G62: =F62*Inputs!$C$69 -> 35481.585 | H62: =IF(E62>0,Inputs!$C$73*12-G62,0) -> 43308.267 | I62: =MAX(0,E62-H62) -> 722975.36 | J62: =IF(E62>0,E62*Inputs!$C$69,0) -> 47509.585 | K62: =J62-G62 -> 12028 | L62: =L61+K62 -> 68076
A63: 10 | B63: =D62 -> 212000 | C63: =Inputs!$C$83 -> 18000 | D63: =B63+C63 -> 230000 | E63: =I62 -> 722975.36 | F63: =MAX(0,E63-B63) -> 510975.36 | G63: =F63*Inputs!$C$69 -> 31680.472 | H63: =IF(E63>0,Inputs!$C$73*12-G63,0) -> 47109.379 | I63: =MAX(0,E63-H63) -> 675865.98 | J63: =IF(E63>0,E63*Inputs!$C$69,0) -> 44824.472 | K63: =J63-G63 -> 13144 | L63: =L62+K63 -> 81220
A64: 11 | B64: =D63 -> 230000 | C64: =Inputs!$C$83 -> 18000 | D64: =B64+C64 -> 248000 | E64: =I63 -> 675865.98 | F64: =MAX(0,E64-B64) -> 445865.98 | G64: =F64*Inputs!$C$69 -> 27643.691 | H64: =IF(E64>0,Inputs!$C$73*12-G64,0) -> 51146.161 | I64: =MAX(0,E64-H64) -> 624719.82 | J64: =IF(E64>0,E64*Inputs!$C$69,0) -> 41903.691 | K64: =J64-G64 -> 14260 | L64: =L63+K64 -> 95480
A65: 12 | B65: =D64 -> 248000 | C65: =Inputs!$C$83 -> 18000 | D65: =B65+C65 -> 266000 | E65: =I64 -> 624719.82 | F65: =MAX(0,E65-B65) -> 376719.82 | G65: =F65*Inputs!$C$69 -> 23356.629 | H65: =IF(E65>0,Inputs!$C$73*12-G65,0) -> 55433.223 | I65: =MAX(0,E65-H65) -> 569286.6 | J65: =IF(E65>0,E65*Inputs!$C$69,0) -> 38732.629 | K65: =J65-G65 -> 15376 | L65: =L64+K65 -> 110856
A66: 13 | B66: =D65 -> 266000 | C66: =Inputs!$C$83 -> 18000 | D66: =B66+C66 -> 284000 | E66: =I65 -> 569286.6 | F66: =MAX(0,E66-B66) -> 303286.6 | G66: =F66*Inputs!$C$69 -> 18803.769 | H66: =IF(E66>0,Inputs!$C$73*12-G66,0) -> 59986.082 | I66: =MAX(0,E66-H66) -> 509300.52 | J66: =IF(E66>0,E66*Inputs!$C$69,0) -> 35295.769 | K66: =J66-G66 -> 16492 | L66: =L65+K66 -> 127348
... A73: 20 | B73: =D72 -> 392000 | C73: =Inputs!$C$83 -> 18000 | D73: =B73+C73 -> 410000 | E73: =I72 -> 62744.191 | F73: =MAX(0,E73-B73) -> 0 | G73: =F73*Inputs!$C$69 -> 0 | H73: =IF(E73>0,Inputs!$C$73*12-G73,0) -> 78789.852 | I73: =MAX(0,E73-H73) -> 0 | J73: =IF(E73>0,E73*Inputs!$C$69,0) -> 3890.1398 | K73: =J73-G73 -> 3890.1398 | L73: =L72+K73 -> 228390.38
A74: TOTAL | C74: =SUM(C54:C73) -> 360000 | G74: =SUM(G54:G73) -> 559751.37 | J74: =SUM(J54:J73) -> 788141.75 | L74: =L73 -> 228390.38
A76: NET WEALTH COMPARISON — INCREMENTAL BENEFIT OF DEPLOYING $18k/yr
A77: Year | B77: Baseline Super (SG Only) | C77: Baseline Loan (Min Repay) | D77: A: Cum. Interest Saved | E77: B: Extra Super (vs Baseline) | F77: B: Loan Savings (vs Baseline) | G77: B: Total Benefit | H77: C: Cum. Interest Saved | I77: A: Net Wealth Gain | J77: B: Net Wealth Gain | K77: C: Net Wealth Gain | L77: Best Scenario | M77: B vs A Difference | N77: C vs A Difference
A78: 1 | B78: =Inputs!$C$35*(1+Inputs!$C$53)+Inputs!$C$6*(1+Inputs!$C$8)^(A78-1)*Inputs!$C$36*(1-Inputs!$C$56) -> 165937.5 | C78: =L6 -> 1000000 | D78: =K6 -> 0 | E78: =H30-B78 -> 27414.641 | F78: =C78-L30 -> 15370.322 | G78: =E78+F78 -> 42784.963 | H78: =L54 -> 3100 | I78: =D78 -> 0 | J78: =G78 -> 42784.963 | K78: =H78 -> 3100 | L78: =IF(AND(I78>=J78,I78>=K78),"A",IF(AND(J78>=I78,J78>=K78),"B","C")) -> B | M78: =J78-I78 -> 42784.963 | N78: =K78-I78 -> 3100
A79: 2 | B79: =B78*(1+Inputs!$C$53)+Inputs!$C$6*(1+Inputs!$C$8)^(A79-1)*Inputs!$C$36*(1-Inputs!$C$56) -> 183476.72 | C79: =L7 -> 983210.15 | D79: =K7 -> 1116 | E79: =H31-B79 -> 49023.77 | F79: =C79-L31 -> 16323.282 | G79: =E79+F79 -> 65347.052 | H79: =L55 -> 7316 | I79: =D79 -> 1116 | J79: =G79 -> 65347.052 | K79: =H79 -> 7316 | L79: =IF(AND(I79>=J79,I79>=K79),"A",IF(AND(J79>=I79,J79>=K79),"B","C")) -> B | M79: =J79-I79 -> 64231.052 | N79: =K79-I79 -> 6200
A80: 3 | B80: =B79*(1+Inputs!$C$53)+Inputs!$C$6*(1+Inputs!$C$8)^(A80-1)*Inputs!$C$36*(1-Inputs!$C$56) -> 202777.9 | C80: =L8 -> 965379.33 | D80: =K8 -> 3417.192 | E80: =H32-B80 -> 70830.286 | F80: =C80-L32 -> 17335.326 | G80: =E80+F80 -> 88165.612 | H80: =L56 -> 12648 | I80: =D80 -> 3417.192 | J80: =G80 -> 88165.612 | K80: =H80 -> 12648 | L80: =IF(AND(I80>=J80,I80>=K80),"A",IF(AND(J80>=I80,J80>=K80),"B","C")) -> B | M80: =J80-I80 -> 84748.42 | N80: =K80-I80 -> 9230.808
A81: 4 | B81: =B80*(1+Inputs!$C$53)+Inputs!$C$6*(1+Inputs!$C$8)^(A81-1)*Inputs!$C$36*(1-Inputs!$C$56) -> 224017.3 | C81: =L9 -> 946442.99 | D81: =K9 -> 6977.0579 | E81: =H33-B81 -> 92837.238 | F81: =C81-L33 -> 18410.116 | G81: =E81+F81 -> 111247.35 | H81: =L57 -> 19096 | I81: =D81 -> 6977.0579 | J81: =G81 -> 111247.35 | K81: =H81 -> 19096 | L81: =IF(AND(I81>=J81,I81>=K81),"A",IF(AND(J81>=I81,J81>=K81),"B","C")) -> B | M81: =J81-I81 -> 104270.3 | N81: =K81-I81 -> 12118.942
A82: 5 | B82: =B81*(1+Inputs!$C$53)+Inputs!$C$6*(1+Inputs!$C$8)^(A82-1)*Inputs!$C$36*(1-Inputs!$C$56) -> 247388.81 | C82: =L10 -> 926332.61 | D82: =K10 -> 11873.635 | E82: =H34-B82 -> 115047.84 | F82: =C82-L34 -> 19551.543 | G82: =E82+F82 -> 134599.38 | H82: =L58 -> 26660 | I82: =D82 -> 11873.635 | J82: =G82 -> 134599.38 | K82: =H82 -> 26660 | L82: =IF(AND(I82>=J82,I82>=K82),"A",IF(AND(J82>=I82,J82>=K82),"B","C")) -> B | M82: =J82-I82 -> 122725.74 | N82: =K82-I82 -> 14786.365
A83: 6 | B83: =B82*(1+Inputs!$C$53)+Inputs!$C$6*(1+Inputs!$C$8)^(A83-1)*Inputs!$C$36*(1-Inputs!$C$56) -> 273105.72 | C83: =L11 -> 904975.38 | D83: =K11 -> 18189.801 | E83: =H35-B83 -> 137465.47 | F83: =C83-L35 -> 20763.739 | G83: =E83+F83 -> 158229.21 | H83: =L59 -> 35340 | I83: =D83 -> 18189.801 | J83: =G83 -> 158229.21 | K83: =H83 -> 35340 | L83: =IF(AND(I83>=J83,I83>=K83),"A",IF(AND(J83>=I83,J83>=K83),"B","C")) -> B | M83: =J83-I83 -> 140039.41 | N83: =K83-I83 -> 17150.199
A84: 7 | B84: =B83*(1+Inputs!$C$53)+Inputs!$C$6*(1+Inputs!$C$8)^(A84-1)*Inputs!$C$36*(1-Inputs!$C$56) -> 301402.63 | C84: =L12 -> 882294 | D84: =K12 -> 26013.569 | E84: =H36-B84 -> 160093.73 | F84: =C84-L36 -> 22051.09 | G84: =E84+F84 -> 182144.82 | H84: =L60 -> 45136 | I84: =D84 -> 26013.569 | J84: =G84 -> 182144.82 | K84: =H84 -> 45136 | L84: =IF(AND(I84>=J84,I84>=K84),"A",IF(AND(J84>=I84,J84>=K84),"B","C")) -> B | M84: =J84-I84 -> 156131.25 | N84: =K84-I84 -> 19122.431
A85: 8 | B85: =B84*(1+Inputs!$C$53)+Inputs!$C$6*(1+Inputs!$C$8)^(A85-1)*Inputs!$C$36*(1-Inputs!$C$56) -> 332537.62 | C85: =L13 -> 858206.38 | D85: =K13 -> 35438.41 | E85: =H37-B85 -> 182936.41 | F85: =C85-L37 -> 23418.258 | G85: =E85+F85 -> 206354.67 | H85: =L61 -> 56048 | I85: =D85 -> 35438.41 | J85: =G85 -> 206354.67 | K85: =H85 -> 56048 | L85: =IF(AND(I85>=J85,I85>=K85),"A",IF(AND(J85>=I85,J85>=K85),"B","C")) -> B | M85: =J85-I85 -> 170916.26 | N85: =K85-I85 -> 20609.59
A86: 9 | B86: =B85*(1+Inputs!$C$53)+Inputs!$C$6*(1+Inputs!$C$8)^(A86-1)*Inputs!$C$36*(1-Inputs!$C$56) -> 366794.56 | C86: =L14 -> 832625.32 | D86: =K14 -> 46563.591 | E86: =H38-B86 -> 205997.54 | F86: =C86-L38 -> 24870.19 | G86: =E86+F86 -> 230867.73 | H86: =L62 -> 68076 | I86: =D86 -> 46563.591 | J86: =G86 -> 230867.73 | K86: =H86 -> 68076 | L86: =IF(AND(I86>=J86,I86>=K86),"A",IF(AND(J86>=I86,J86>=K86),"B","C")) -> B | M86: =J86-I86 -> 184304.14 | N86: =K86-I86 -> 21512.409
A87: 10 | B87: =B86*(1+Inputs!$C$53)+Inputs!$C$6*(1+Inputs!$C$8)^(A87-1)*Inputs!$C$36*(1-Inputs!$C$56) -> 404485.72 | C87: =L15 -> 805458.24 | D87: =K15 -> 59494.534 | E87: =H39-B87 -> 229281.4 | F87: =C87-L39 -> 26412.142 | G87: =E87+F87 -> 255693.54 | H87: =L63 -> 81220 | I87: =D87 -> 59494.534 | J87: =G87 -> 255693.54 | K87: =H87 -> 81220 | L87: =IF(AND(I87>=J87,I87>=K87),"A",IF(AND(J87>=I87,J87>=K87),"B","C")) -> B | M87: =J87-I87 -> 196199.01 | N87: =K87-I87 -> 21725.466
A88: 11 | B88: =B87*(1+Inputs!$C$53)+Inputs!$C$6*(1+Inputs!$C$8)^(A88-1)*Inputs!$C$36*(1-Inputs!$C$56) -> 445954.59 | C88: =L16 -> 776606.8 | D88: =K16 -> 74343.195 | E88: =H40-B88 -> 252792.56 | F88: =C88-L40 -> 28049.695 | G88: =E88+F88 -> 280842.26 | H88: =L64 -> 95480 | I88: =D88 -> 74343.195 | J88: =G88 -> 280842.26 | K88: =H88 -> 95480 | L88: =IF(AND(I88>=J88,I88>=K88),"A",IF(AND(J88>=I88,J88>=K88),"B","C")) -> B | M88: =J88-I88 -> 206499.06 | N88: =K88-I88 -> 21136.805
A89: 12 | B89: =B88*(1+Inputs!$C$53)+Inputs!$C$6*(1+Inputs!$C$8)^(A89-1)*Inputs!$C$36*(1-Inputs!$C$56) -> 491579.03 | C89: =L17 -> 745966.57 | D89: =K17 -> 91228.473 | E89: =H41-B89 -> 276535.9 | F89: =C89-L41 -> 29788.776 | G89: =E89+F89 -> 306324.67 | H89: =L65 -> 110856 | I89: =D89 -> 91228.473 | J89: =G89 -> 306324.67 | K89: =H89 -> 110856 | L89: =IF(AND(I89>=J89,I89>=K89),"A",IF(AND(J89>=I89,J89>=K89),"B","C")) -> B | M89: =J89-I89 -> 215096.2 | N89: =K89-I89 -> 19627.527
A90: 13 | B90: =B89*(1+Inputs!$C$53)+Inputs!$C$6*(1+Inputs!$C$8)^(A90-1)*Inputs!$C$36*(1-Inputs!$C$56) -> 541774.66 | C90: =L18 -> 713426.64 | D90: =K18 -> 110276.64 | E90: =H42-B90 -> 300516.61 | F90: =C90-L42 -> 31635.68 | G90: =E90+F90 -> 332152.29 | H90: =L66 -> 127348 | I90: =D90 -> 110276.64 | J90: =G90 -> 332152.29 | K90: =H90 -> 127348 | L90: =IF(AND(I90>=J90,I90>=K90),"A",IF(AND(J90>=I90,J90>=K90),"B","C")) -> B | M90: =J90-I90 -> 221875.65 | N90: =K90-I90 -> 17071.362
... A97: 20 | B97: =B96*(1+Inputs!$C$53)+Inputs!$C$6*(1+Inputs!$C$8)^(A97-1)*Inputs!$C$36*(1-Inputs!$C$56) -> 1065918.5 | C97: =L25 -> 421582.55 | D97: =K25 -> 298306.35 | E97: =H49-B97 -> 475552.35 | F97: =C97-L49 -> 48200.194 | G97: =E97+F97 -> 523752.55 | H97: =L73 -> 228390.38 | I97: =D97 -> 298306.35 | J97: =G97 -> 523752.55 | K97: =H97 -> 228390.38 | L97: =IF(AND(I97>=J97,I97>=K97),"A",IF(AND(J97>=I97,J97>=K97),"B","C")) -> B | M97: =J97-I97 -> 225446.2 | N97: =K97-I97 -> -69915.967
A98: SUMMARY | E98: =E97 -> 475552.35 | F98: =F97 -> 48200.194 | G98: =E98+F98 -> 523752.55 | I98: =I97 -> 298306.35 | J98: =J97 -> 523752.55 | K98: =K97 -> 228390.38 | L98: =L97 -> B | M98: =M97 -> 225446.2 | N98: =N97 -> -69915.967
A100: BREAK-EVEN & SENSITIVITY ANALYSIS
A101: Key Finding | C101: Value | E101: Notes
A102: Scenario B wins at all horizons? | C102: =IF(AND(J82>=I82,J87>=I87,J97>=I97),"YES","NO") -> YES | E102: B consistently outperforms A due to super compounding + SG contributions
A103: B vs A advantage at 5 years | C103: =M82 -> 122725.74 | E103: Extra net wealth from choosing super over loan repayment
A104: B vs A advantage at 10 years | C104: =M87 -> 196199.01 | E104: Compounding widens the gap over time
A105: B vs A advantage at 20 years | C105: =M97 -> 225446.2 | E105: Note: Scenario B sacrifices all $18k/yr (excess concessional, taxed at marginal rate)
A106: C vs A advantage at 20 years | C106: =N97 -> -69915.967 | E106: Negative = A outperforms C at this horizon
A108: Loan Payoff Year (Scenario A) | C108: {=MATCH(TRUE,INDEX(H6:H25<=0,0),0)} -> 18 | E108: Year the loan reaches $0 with extra repayments
A109: Loan Payoff Year (Scenario B) | C109: {=IFERROR(MATCH(TRUE,INDEX(L30:L49<=0,0),0),">20")} -> >20 | E109: Loan never pays off early — $0 extra repayments (all cash to super)
A111: SENSITIVITY: Super Return Rate Impact on B vs A (20-Year Horizon)
A112: Super Return (Gross) | B112: Super Return (After Tax) | C112: Extra Super Value (B) | D112: B Total Benefit | E112: A Total Benefit | F112: B vs A Difference | G112: Winner
A113: 0.03 | B113: =A113*(1-Inputs!$C$52) -> 0.0255 | C113: =($C$30-$D$30)*(1+B113)^19+($C$31-$D$31)*IF(B113=0,19,((1+B113)^19-1)/B113) -> 550367.58 | D113: =C113+F97 -> 598567.77 | E113: =$I$97 -> 298306.35 | F113: =D113-E113 -> 300261.42 | G113: =IF(F113>0,"B","A") -> B
A114: 0.04 | B114: =A114*(1-Inputs!$C$52) -> 0.034 | C114: =($C$30-$D$30)*(1+B114)^19+($C$31-$D$31)*IF(B114=0,19,((1+B114)^19-1)/B114) -> 600812.9 | D114: =C114+F97 -> 649013.09 | E114: =$I$97 -> 298306.35 | F114: =D114-E114 -> 350706.74 | G114: =IF(F114>0,"B","A") -> B
A115: 0.05 | B115: =A115*(1-Inputs!$C$52) -> 0.0425 | C115: =($C$30-$D$30)*(1+B115)^19+($C$31-$D$31)*IF(B115=0,19,((1+B115)^19-1)/B115) -> 656877.4 | D115: =C115+F97 -> 705077.59 | E115: =$I$97 -> 298306.35 | F115: =D115-E115 -> 406771.24 | G115: =IF(F115>0,"B","A") -> B
A116: 0.06 | B116: =A116*(1-Inputs!$C$52) -> 0.051 | C116: =($C$30-$D$30)*(1+B116)^19+($C$31-$D$31)*IF(B116=0,19,((1+B116)^19-1)/B116) -> 719212.66 | D116: =C116+F97 -> 767412.85 | E116: =$I$97 -> 298306.35 | F116: =D116-E116 -> 469106.5 | G116: =IF(F116>0,"B","A") -> B
A117: 0.07 | B117: =A117*(1-Inputs!$C$52) -> 0.0595 | C117: =($C$30-$D$30)*(1+B117)^19+($C$31-$D$31)*IF(B117=0,19,((1+B117)^19-1)/B117) -> 788545.02 | D117: =C117+F97 -> 836745.21 | E117: =$I$97 -> 298306.35 | F117: =D117-E117 -> 538438.86 | G117: =IF(F117>0,"B","A") -> B
A118: 0.08 | B118: =A118*(1-Inputs!$C$52) -> 0.068 | C118: =($C$30-$D$30)*(1+B118)^19+($C$31-$D$31)*IF(B118=0,19,((1+B118)^19-1)/B118) -> 865683.84 | D118: =C118+F97 -> 913884.03 | E118: =$I$97 -> 298306.35 | F118: =D118-E118 -> 615577.68 | G118: =IF(F118>0,"B","A") -> B
A119: 0.1 | B119: =A119*(1-Inputs!$C$52) -> 0.085 | C119: =($C$30-$D$30)*(1+B119)^19+($C$31-$D$31)*IF(B119=0,19,((1+B119)^19-1)/B119) -> 1047089.3 | D119: =C119+F97 -> 1095289.5 | E119: =$I$97 -> 298306.35 | F119: =D119-E119 -> 796983.12 | G119: =IF(F119>0,"B","A") -> B
A121: IMPORTANT CAVEATS
A122: 1. Super funds are LOCKED until preservation age (60). Scenario B's benefit is inaccessible until then.
A123: 2. Salary sacrifice uses carry-forward in Year 1, then ongoing cap space (Cap − SG) each year. If SG exceeds cap, ongoing SS = $0 unless cap is increased.
A124: 3. All scenarios assume constant interest rates, returns, and contribution rules. Real outcomes will vary.
A126: DIVISION 293 TAX IMPACT ON SCENARIO B
A127: Component | B127: Without Div 293 | C127: With Div 293 | D127: Difference | E127: Notes
A128: Gross Salary Sacrifice (Year 1) | B128: =C30 -> 31835.294 | C128: =C30 -> 31835.294 | D128: - | E128: Same sacrifice amount either way
A129: Standard Contributions Tax (15%) | B129: =C30*0.15 -> 4775.2941 | C129: =C30*0.15 -> 4775.2941 | D129: - | E129: Base 15% concessional contributions tax
A130: Division 293 Extra Tax (15%) | B130: 0 | C130: =C30*0.15 -> 4775.2941 | D130: =C130-B130 -> 4775.2941 | E130: Extra 15% because income + SG > $250,000
A131: Total Contributions Tax | B131: =B129+B130 -> 4775.2941 | C131: =C129+C130 -> 9550.5882 | D131: =C131-B131 -> 4775.2941 | E131: Total tax on salary sacrifice
A132: Net into Super | B132: =B128-B131 -> 27060 | C132: =C128-C131 -> 22284.706 | D132: =C132-B132 -> -4775.2941 | E132: Amount actually entering your super fund
A133: Tax Saved vs Marginal Rate | B133: =B128*Inputs!$C$29-B131 -> 7640.4706 | C133: =C128*Inputs!$C$29-C131 -> 2865.1765 | D133: =C133-B133 -> -4775.2941 | E133: Net benefit of salary sacrifice vs taking as salary
...
