Workbook

Sheet Input
A1: Input
A2: Change blue cells to compare current CGT treatment with the Budget 2026-27 proposal
A4: Global assumptions
A5: Assumption | B5: Input | C5: Notes | E5: Transition value: if you know or estimate the market value at 1 July 2027, enter it in the asset table. If left blank, the workbook apportions gains by days held before and after 1 July 2027. The calculator is a planning model only and excludes main residence, small business CGT concessions, foreign resident CGT, companies, superannuation funds and detailed trust streaming.
A6: Marginal tax rate for CGT | B6: 0.45 | C6: Your marginal tax rate before Medicare levy.
A7: Medicare levy / other levy | B7: 0.02 | C7: Set to 0 if not applicable.
A8: Combined tax rate | B8: =B6+B7 -> 0.47 | C8: Used for current-law tax and standard new-regime tax.
A9: Current CGT discount | B9: 0.5 | C9: Existing discount for eligible assets held more than 12 months.
A10: New-regime minimum tax | B10: ='Static Data'!F19 -> 0.3 | C10: Budget Paper No. 2 minimum tax on net capital gains.
A11: Default annual CPI/indexation rate | B11: ='Static Data'!F20 -> 0.025 | C11: Used where an asset-specific CPI override is blank.
A12: Reform commencement date | B12: ='Static Data'!F18 -> 1-Jul-2027 | C12: Budget Paper No. 2 start date.
A13: Capital losses available | B13: 0 | C13: Applied equally against each regime at portfolio level.
A14: Default tax residency | B14: Australian resident | C14: Foreign resident rules are not modelled.
A15: Model version | B15: Budget Paper No. 2, 2026-27 | C15: Simplified calculator, not tax advice.
A18: Asset inputs
A19: Asset name | B19: Asset type | C19: Pre-1985 asset? | D19: New residential property? | E19: Income support recipient? | F19: Acquisition date | G19: Sale date | H19: Sale proceeds | I19: Purchase price / original cost | J19: Acquisition costs | K19: Improvement costs | L19: Selling costs | M19: Value at 1 Jul 2027 | N19: Manual indexation factor | O19: Annual CPI override | P19: Eligible for 12m discount? | Q19: Comments
A20: Investment property example | B20: Residential property | C20: No | D20: No | E20: No | F20: 1-Jul-2018 | G20: 30-Jun-2030 | H20: 1250000 | I20: 760000 | J20: 35000 | K20: 40000 | L20: 25000 | M20: 1100000 | P20: =IF(AND(F20<>"",G20-F20>365),"Yes","No") -> Yes | Q20: Replace with your own details
A21: Share portfolio example | B21: Listed shares | C21: No | D21: No | E21: No | F21: 15-Mar-2021 | G21: 30-Jun-2029 | H21: 310000 | I21: 180000 | J21: 2500 | K21: 0 | L21: 1200 | P21: =IF(AND(F21<>"",G21-F21>365),"Yes","No") -> Yes | Q21: Uses time apportionment because transition value is blank
A22: Pre-CGT asset example | B22: Other asset | C22: Yes | D22: No | E22: No | F22: 1-Jan-1984 | G22: 30-Jun-2031 | H22: 900000 | I22: 120000 | J22: 5000 | K22: 20000 | L22: 15000 | M22: 700000 | P22: =IF(AND(F22<>"",G22-F22>365),"Yes","No") -> Yes | Q22: Shows post-reform gain exposure
C23: No | D23: No | E23: No | P23: =IF(AND(F23<>"",G23-F23>365),"Yes","No") -> No
C24: No | D24: No | E24: No | P24: =IF(AND(F24<>"",G24-F24>365),"Yes","No") -> No
C25: No | D25: No | E25: No | P25: =IF(AND(F25<>"",G25-F25>365),"Yes","No") -> No
C26: No | D26: No | E26: No | P26: =IF(AND(F26<>"",G26-F26>365),"Yes","No") -> No
C27: No | D27: No | E27: No | P27: =IF(AND(F27<>"",G27-F27>365),"Yes","No") -> No
C28: No | D28: No | E28: No | P28: =IF(AND(F28<>"",G28-F28>365),"Yes","No") -> No
C29: No | D29: No | E29: No | P29: =IF(AND(F29<>"",G29-F29>365),"Yes","No") -> No
C30: No | D30: No | E30: No | P30: =IF(AND(F30<>"",G30-F30>365),"Yes","No") -> No
C31: No | D31: No | E31: No | P31: =IF(AND(F31<>"",G31-F31>365),"Yes","No") -> No
C32: No | D32: No | E32: No | P32: =IF(AND(F32<>"",G32-F32>365),"Yes","No") -> No
C33: No | D33: No | E33: No | P33: =IF(AND(F33<>"",G33-F33>365),"Yes","No") -> No
C34: No | D34: No | E34: No | P34: =IF(AND(F34<>"",G34-F34>365),"Yes","No") -> No
... C49: No | D49: No | E49: No | P49: =IF(AND(F49<>"",G49-F49>365),"Yes","No") -> No

Sheet Calculator
A1: Calculator
A2: Side-by-side comparison of current and Budget 2026-27 CGT treatment
A4: Summary
A5: Metric | B5: Current regime | C5: New Budget regime | D5: Difference | E5: Direction | F5: Notes
A6: Gross nominal capital gains | B6: =SUM(I20:I49) -> 1256300 | C6: =SUM(I20:I49) -> 1256300 | D6: =C6-B6 -> 0 | E6: =IF(D6=0,"No change",IF(D6>0,"Higher","Lower")) -> No change | F6: Before losses and concessions
A7: Taxable capital gains after concessions | B7: =SUM(J20:J49) -> 258150 | C7: =SUM(R20:R49) -> 132500 | D7: =C7-B7 -> -125650 | E7: =IF(D7=0,"No change",IF(D7>0,"Higher","Lower")) -> Lower | F7: After current discount or new indexation treatment
A8: Capital losses applied | B8: =MIN(Input!$B$14,B7) -> 258150 | C8: =MIN(Input!$B$14,C7) -> 132500 | D8: =C8-B8 -> -125650 | E8: =IF(D8=0,"No change",IF(D8>0,"Higher","Lower")) -> Lower | F8: Losses from Input tab
A9: Net taxable capital gains | B9: =MAX(0,B7-B8) -> 0 | C9: =MAX(0,C7-C8) -> 0 | D9: =C9-B9 -> 0 | E9: =IF(D9=0,"No change",IF(D9>0,"Higher","Lower")) -> No change | F9: After portfolio-level capital losses
A10: Estimated CGT tax | B10: =B9*Input!$B$8 -> 0 | C10: =SUM(S20:S49) -> 454015 | D10: =C10-B10 -> 454015 | E10: =IF(D10=0,"No change",IF(D10>0,"Higher tax","Lower tax")) -> Higher tax | F10: Current uses combined marginal rate. New uses higher of standard tax and minimum tax where applicable.
A11: Net proceeds after CGT | B11: =SUM(Input!H20:H49)-SUM(Input!L20:L49)-B10 -> 2418800 | C11: =SUM(Input!H20:H49)-SUM(Input!L20:L49)-C10 -> 1964785 | D11: =C11-B11 -> -454015 | E11: =IF(D11=0,"No change",IF(D11>0,"Higher cash","Lower cash")) -> Lower cash | F11: Sale proceeds less selling costs and estimated CGT tax
A12: Effective tax rate on gross gains | B12: =IFERROR(B10/B6,0) -> 0 | C12: =IFERROR(C10/C6,0) -> 0.36139059 | D12: =C12-B12 -> 0.36139059 | E12: =IF(D12=0,"No change",IF(D12>0,"Higher rate","Lower rate")) -> Higher rate | F12: Estimated CGT tax divided by gross nominal gains
A16: Asset-by-asset calculation
A17: Asset name | B17: Asset type | C17: Pre-1985? | D17: New residential? | E17: Income support? | F17: Acq date | G17: Sale date | H17: Net sale proceeds | I17: Gross gain | J17: Current taxable gain | K17: Current tax | L17: Pre-reform gain | M17: Post-reform nominal gain | N17: Indexation factor | O17: Indexation allowance | P17: Post-reform indexed gain | Q17: Minimum-tax base | R17: New taxable gain | S17: New tax | T17: Tax difference | U17: Lower option used? | V17: Transition method
A20: =Input!A20 -> Investment property example | B20: =Input!B20 -> Residential property | C20: =Input!C20 -> No | D20: =Input!D20 -> No | E20: =Input!E20 -> No | F20: =Input!F20 -> 1-Jul-2018 | G20: =Input!G20 -> 30-Jun-2030 | H20: =IF(Input!A20="","",MAX(0,Input!H20-Input!L20)) -> 1225000 | I20: =IF(A20="","",MAX(0,H20-(Input!I20+Input!J20+Input!K20))) -> 390000 | J20: =IF(A20="","",IF(C20="Yes",0,I20*(1-IF(Input!P20="Yes",Input!$B$9,0)))) -> 195000 | K20: =IF(A20="","",J20*Input!$B$8) -> 91650 | L20: =IF(A20="","",IF(Input!G20<=Input!$B$12,I20,IF(Input!F20>=Input!$B$12,0,IF(Input!M20<>"",MAX(0,Input!M20-(Input!I20+Input!J20+Input!K20)),I20*MAX(0,MIN(Input!G20,Input!$B$12)-Input!F20)/MAX(1,Input!G20-Input!F20))))) -> 265000 | M20: =IF(A20="","",MAX(0,I20-L20)) -> 125000 | N20: =IF(A20="","",IF(Input!N20<>"",Input!N20,POWER(1+IF(Input!O20<>"",Input!O20,Input!$B$11),MAX(0,Input!G20-MAX(Input!F20,Input!$B$12))/365))) -> 25.141427 | O20: =IF(A20="","",MAX(0,IF(Input!F20>=Input!$B$12,Input!I20+Input!J20+Input!K20,IF(Input!M20<>"",Input!M20,Input!I20+Input!J20+Input!K20+L20))*(N20-1))) -> 26555569 | P20: =IF(A20="","",MAX(0,M20-O20)) -> 0 | Q20: =IF(A20="","",M20) -> 125000 | R20: =IF(A20="","",IF(C20="Yes",P20,L20*(1-IF(Input!P20="Yes",Input!$B$9,0))+P20)) -> 132500 | S20: =IF(A20="","",IF(D20="Yes",MIN(R20*Input!$B$8,I20*(1-Input!$B$9)*Input!$B$8),L20*(1-IF(OR(C20="Yes",Input!P20<>"Yes"),0,Input!$B$9))*Input!$B$8+MAX(P20*Input!$B$8,IF(E20="Yes",0,Q20*Input!$B$10)))) -> 99775 | T20: =IF(A20="","",S20-K20) -> 8125 | U20: =IF(A20="","",IF(D20="Yes","Best of discount/indexation","Indexation/min tax")) -> Indexation/min tax | V20: =IF(A20="","",IF(Input!M20<>"","1 Jul 2027 value","Time apportionment")) -> 1 Jul 2027 value
A21: =Input!A21 -> Share portfolio example | B21: =Input!B21 -> Listed shares | C21: =Input!C21 -> No | D21: =Input!D21 -> No | E21: =Input!E21 -> No | F21: =Input!F21 -> 15-Mar-2021 | G21: =Input!G21 -> 30-Jun-2029 | H21: =IF(Input!A21="","",MAX(0,Input!H21-Input!L21)) -> 308800 | I21: =IF(A21="","",MAX(0,H21-(Input!I21+Input!J21+Input!K21))) -> 126300 | J21: =IF(A21="","",IF(C21="Yes",0,I21*(1-IF(Input!P21="Yes",Input!$B$9,0)))) -> 63150 | K21: =IF(A21="","",J21*Input!$B$8) -> 29680.5 | L21: =IF(A21="","",IF(Input!G21<=Input!$B$12,I21,IF(Input!F21>=Input!$B$12,0,IF(Input!M21<>"",MAX(0,Input!M21-(Input!I21+Input!J21+Input!K21)),I21*MAX(0,MIN(Input!G21,Input!$B$12)-Input!F21)/MAX(1,Input!G21-Input!F21))))) -> 0 | M21: =IF(A21="","",MAX(0,I21-L21)) -> 126300 | N21: =IF(A21="","",IF(Input!N21<>"",Input!N21,POWER(1+IF(Input!O21<>"",Input!O21,Input!$B$11),MAX(0,Input!G21-MAX(Input!F21,Input!$B$12))/365))) -> 24.528221 | O21: =IF(A21="","",MAX(0,IF(Input!F21>=Input!$B$12,Input!I21+Input!J21+Input!K21,IF(Input!M21<>"",Input!M21,Input!I21+Input!J21+Input!K21+L21))*(N21-1))) -> 4293900.4 | P21: =IF(A21="","",MAX(0,M21-O21)) -> 0 | Q21: =IF(A21="","",M21) -> 126300 | R21: =IF(A21="","",IF(C21="Yes",P21,L21*(1-IF(Input!P21="Yes",Input!$B$9,0))+P21)) -> 0 | S21: =IF(A21="","",IF(D21="Yes",MIN(R21*Input!$B$8,I21*(1-Input!$B$9)*Input!$B$8),L21*(1-IF(OR(C21="Yes",Input!P21<>"Yes"),0,Input!$B$9))*Input!$B$8+MAX(P21*Input!$B$8,IF(E21="Yes",0,Q21*Input!$B$10)))) -> 37890 | T21: =IF(A21="","",S21-K21) -> 8209.5 | U21: =IF(A21="","",IF(D21="Yes","Best of discount/indexation","Indexation/min tax")) -> Indexation/min tax | V21: =IF(A21="","",IF(Input!M21<>"","1 Jul 2027 value","Time apportionment")) -> Time apportionment
A22: =Input!A22 -> Pre-CGT asset example | B22: =Input!B22 -> Other asset | C22: =Input!C22 -> Yes | D22: =Input!D22 -> No | E22: =Input!E22 -> No | F22: =Input!F22 -> 1-Jan-1984 | G22: =Input!G22 -> 30-Jun-2031 | H22: =IF(Input!A22="","",MAX(0,Input!H22-Input!L22)) -> 885000 | I22: =IF(A22="","",MAX(0,H22-(Input!I22+Input!J22+Input!K22))) -> 740000 | J22: =IF(A22="","",IF(C22="Yes",0,I22*(1-IF(Input!P22="Yes",Input!$B$9,0)))) -> 0 | K22: =IF(A22="","",J22*Input!$B$8) -> 0 | L22: =IF(A22="","",IF(Input!G22<=Input!$B$12,I22,IF(Input!F22>=Input!$B$12,0,IF(Input!M22<>"",MAX(0,Input!M22-(Input!I22+Input!J22+Input!K22)),I22*MAX(0,MIN(Input!G22,Input!$B$12)-Input!F22)/MAX(1,Input!G22-Input!F22))))) -> 555000 | M22: =IF(A22="","",MAX(0,I22-L22)) -> 185000 | N22: =IF(A22="","",IF(Input!N22<>"",Input!N22,POWER(1+IF(Input!O22<>"",Input!O22,Input!$B$11),MAX(0,Input!G22-MAX(Input!F22,Input!$B$12))/365))) -> 25.769962 | O22: =IF(A22="","",MAX(0,IF(Input!F22>=Input!$B$12,Input!I22+Input!J22+Input!K22,IF(Input!M22<>"",Input!M22,Input!I22+Input!J22+Input!K22+L22))*(N22-1))) -> 17338974 | P22: =IF(A22="","",MAX(0,M22-O22)) -> 0 | Q22: =IF(A22="","",M22) -> 185000 | R22: =IF(A22="","",IF(C22="Yes",P22,L22*(1-IF(Input!P22="Yes",Input!$B$9,0))+P22)) -> 0 | S22: =IF(A22="","",IF(D22="Yes",MIN(R22*Input!$B$8,I22*(1-Input!$B$9)*Input!$B$8),L22*(1-IF(OR(C22="Yes",Input!P22<>"Yes"),0,Input!$B$9))*Input!$B$8+MAX(P22*Input!$B$8,IF(E22="Yes",0,Q22*Input!$B$10)))) -> 316350 | T22: =IF(A22="","",S22-K22) -> 316350 | U22: =IF(A22="","",IF(D22="Yes","Best of discount/indexation","Indexation/min tax")) -> Indexation/min tax | V22: =IF(A22="","",IF(Input!M22<>"","1 Jul 2027 value","Time apportionment")) -> 1 Jul 2027 value

Sheet Taxpayer Types
A1: Taxpayer Type Comparison
A2: Compares the current 50% CGT discount regime with the Budget 2026-27 indexation/minimum-tax regime using the portfolio from the Input tab.
A4: Portfolio values imported from Calculator
A5: Metric | B5: Linked value | C5: Notes | E5: How to read this tab: each row applies a taxpayer profile to the same asset portfolio. It is a scenario comparison, not a full tax return model. Marginal rates are editable assumptions. Foreign-resident CGT, company taxpayers, superannuation funds, detailed trust streaming, main residence exemptions and small business CGT concessions are not modelled.
A6: Gross nominal capital gains | B6: =Calculator!B6 -> 1256300 | C6: Before concessions and losses.
A7: Current-regime taxable gain | B7: =Calculator!B7 -> 258150 | C7: Uses current 50% discount where eligible.
A8: New-regime taxable gain before losses | B8: =Calculator!C7 -> 132500 | C8: Uses indexation / transition model from Calculator.
A9: New-regime minimum-tax base | B9: =SUM(Calculator!Q20:Q49) -> 436300 | C9: Post-reform nominal gain base used for 30% minimum-tax testing.
A10: Capital losses available | B10: =Input!B14 -> Australian resident | C10: From Input tab.
A11: Budget minimum tax rate | B11: =Input!B10 -> 0.3 | C11: 30% default from Budget Paper No. 2.
A14: Taxpayer type comparison
A15: Taxpayer type | B15: Marginal tax rate | C15: Medicare / levy | D15: Combined tax rate | E15: Minimum tax applies? | F15: Special treatment | G15: Current taxable gain | H15: Current tax | I15: New taxable gain | J15: New standard tax | K15: Minimum tax amount | L15: New regime tax | M15: Tax difference | N15: Comment
A16: Resident individual - low bracket | B16: 0.19 | C16: 0.02 | D16: =B16+C16 -> 0.21 | E16: Yes | F16: Standard | G16: =MAX(0,$B$7-MIN($B$10,$B$7)) -> 0 | H16: =G16*D16 -> 0 | I16: =MAX(0,$B$8-MIN($B$10,$B$8)) -> 0 | J16: =I16*D16 -> 0 | K16: =IF(E16="Yes",MAX(0,$B$9-MIN($B$10,$B$9))*$B$11,0) -> 0 | L16: =IF(A16="Foreign resident investor","Not modelled",IF(F16="Best of discount/indexation",MIN(H16,MAX(J16,K16)),MAX(J16,K16))) -> 0 | M16: =IF(A16="Foreign resident investor","Not modelled",L16-H16) -> 0 | N16: Shows the minimum tax can bind where marginal rate is below 30%.
A17: Resident individual - middle bracket | B17: 0.325 | C17: 0.02 | D17: =B17+C17 -> 0.345 | E17: Yes | F17: Standard | G17: =MAX(0,$B$7-MIN($B$10,$B$7)) -> 0 | H17: =G17*D17 -> 0 | I17: =MAX(0,$B$8-MIN($B$10,$B$8)) -> 0 | J17: =I17*D17 -> 0 | K17: =IF(E17="Yes",MAX(0,$B$9-MIN($B$10,$B$9))*$B$11,0) -> 0 | L17: =IF(A17="Foreign resident investor","Not modelled",IF(F17="Best of discount/indexation",MIN(H17,MAX(J17,K17)),MAX(J17,K17))) -> 0 | M17: =IF(A17="Foreign resident investor","Not modelled",L17-H17) -> 0 | N17: Illustrative mid-rate taxpayer.
A18: Resident individual - top bracket | B18: 0.45 | C18: 0.02 | D18: =B18+C18 -> 0.47 | E18: Yes | F18: Standard | G18: =MAX(0,$B$7-MIN($B$10,$B$7)) -> 0 | H18: =G18*D18 -> 0 | I18: =MAX(0,$B$8-MIN($B$10,$B$8)) -> 0 | J18: =I18*D18 -> 0 | K18: =IF(E18="Yes",MAX(0,$B$9-MIN($B$10,$B$9))*$B$11,0) -> 0 | L18: =IF(A18="Foreign resident investor","Not modelled",IF(F18="Best of discount/indexation",MIN(H18,MAX(J18,K18)),MAX(J18,K18))) -> 0 | M18: =IF(A18="Foreign resident investor","Not modelled",L18-H18) -> 0 | N18: Broad proxy for high-income resident individual.
A19: Income support / Age Pension recipient | B19: 0.19 | C19: 0.02 | D19: =B19+C19 -> 0.21 | E19: No | F19: Minimum tax exempt | G19: =MAX(0,$B$7-MIN($B$10,$B$7)) -> 0 | H19: =G19*D19 -> 0 | I19: =MAX(0,$B$8-MIN($B$10,$B$8)) -> 0 | J19: =I19*D19 -> 0 | K19: =IF(E19="Yes",MAX(0,$B$9-MIN($B$10,$B$9))*$B$11,0) -> 0 | L19: =IF(A19="Foreign resident investor","Not modelled",IF(F19="Best of discount/indexation",MIN(H19,MAX(J19,K19)),MAX(J19,K19))) -> 0 | M19: =IF(A19="Foreign resident investor","Not modelled",L19-H19) -> 0 | N19: Budget measure exempts income support recipients from the 30% minimum tax.
A20: New residential property investor | B20: 0.45 | C20: 0.02 | D20: =B20+C20 -> 0.47 | E20: Yes | F20: Best of discount/indexation | G20: =MAX(0,$B$7-MIN($B$10,$B$7)) -> 0 | H20: =G20*D20 -> 0 | I20: =MAX(0,$B$8-MIN($B$10,$B$8)) -> 0 | J20: =I20*D20 -> 0 | K20: =IF(E20="Yes",MAX(0,$B$9-MIN($B$10,$B$9))*$B$11,0) -> 0 | L20: =IF(A20="Foreign resident investor","Not modelled",IF(F20="Best of discount/indexation",MIN(H20,MAX(J20,K20)),MAX(J20,K20))) -> 0 | M20: =IF(A20="Foreign resident investor","Not modelled",L20-H20) -> 0 | N20: Budget measure allows choice between 50% discount and indexation/minimum-tax treatment for new residential property.
A21: Discretionary trust beneficiary | B21: 0.45 | C21: 0.02 | D21: =B21+C21 -> 0.47 | E21: Yes | F21: Beneficiary rate proxy | G21: =MAX(0,$B$7-MIN($B$10,$B$7)) -> 0 | H21: =G21*D21 -> 0 | I21: =MAX(0,$B$8-MIN($B$10,$B$8)) -> 0 | J21: =I21*D21 -> 0 | K21: =IF(E21="Yes",MAX(0,$B$9-MIN($B$10,$B$9))*$B$11,0) -> 0 | L21: =IF(A21="Foreign resident investor","Not modelled",IF(F21="Best of discount/indexation",MIN(H21,MAX(J21,K21)),MAX(J21,K21))) -> 0 | M21: =IF(A21="Foreign resident investor","Not modelled",L21-H21) -> 0 | N21: Simplified proxy only; does not model trust streaming or the separate discretionary trust minimum tax.
A22: Partnership individual partner | B22: 0.325 | C22: 0.02 | D22: =B22+C22 -> 0.345 | E22: Yes | F22: Partner rate proxy | G22: =MAX(0,$B$7-MIN($B$10,$B$7)) -> 0 | H22: =G22*D22 -> 0 | I22: =MAX(0,$B$8-MIN($B$10,$B$8)) -> 0 | J22: =I22*D22 -> 0 | K22: =IF(E22="Yes",MAX(0,$B$9-MIN($B$10,$B$9))*$B$11,0) -> 0 | L22: =IF(A22="Foreign resident investor","Not modelled",IF(F22="Best of discount/indexation",MIN(H22,MAX(J22,K22)),MAX(J22,K22))) -> 0 | M22: =IF(A22="Foreign resident investor","Not modelled",L22-H22) -> 0 | N22: Simplified proxy: applies partner tax rate to partnership-attributed gain.
A23: Foreign resident investor | B23: 0.325 | C23: 0 | D23: =B23+C23 -> 0.325 | E23: Not modelled | F23: Out of scope | G23: =MAX(0,$B$7-MIN($B$10,$B$7)) -> 0 | H23: =G23*D23 -> 0 | I23: =MAX(0,$B$8-MIN($B$10,$B$8)) -> 0 | J23: =I23*D23 -> 0 | K23: =IF(E23="Yes",MAX(0,$B$9-MIN($B$10,$B$9))*$B$11,0) -> 0 | L23: =IF(A23="Foreign resident investor","Not modelled",IF(F23="Best of discount/indexation",MIN(H23,MAX(J23,K23)),MAX(J23,K23))) -> Not modelled | M23: =IF(A23="Foreign resident investor","Not modelled",L23-H23) -> Not modelled | N23: Foreign-resident CGT rules and transitional arrangements are separate and not modelled here.

Sheet Static Data
A1: Static Data
A2: Budget Paper No. 2 policy settings and modelling assumptions used by the calculator
A4: Regime assumptions
A5: Item | B5: Current regime | C5: New Budget 2026-27 regime | D5: Effective date | E5: Rate / value | F5: Applies to | G5: Workbook treatment | H5: Source note
A6: CGT concession | B6: 50% CGT discount for eligible assets held >12 months | C6: Cost base indexation replaces 50% discount for post-reform gains | D6: 1-Jul-2027 | E6: 0.5 | F6: Individuals, trusts, partnerships | G6: Current-law taxable gain uses 50% discount. New regime splits pre/post reform gains. | H6: Budget Paper No. 2
A7: Minimum tax | B7: No separate CGT minimum tax | C7: 30% minimum tax on net capital gains | D7: 1-Jul-2027 | E7: 0.3 | F7: Net capital gains under new regime | G7: New regime tax is higher of marginal-rate tax on indexed gain and 30% of post-reform nominal gain. | H7: Budget Paper No. 2
A8: Transition | B8: Existing law applies | C8: New rules apply only to gains arising on or after 1 July 2027 | D8: 1-Jul-2027 | F8: Existing assets | G8: Uses supplied 1 July 2027 value or time-apportioned gain split. | H8: Budget Paper No. 2
A9: Pre-1985 assets | B9: Generally exempt from CGT | C9: Post-1 July 2027 gains included in new regime | D9: 1-Jul-2027 | F9: Pre-CGT assets | G9: Exempts current-law and pre-reform gains, taxes post-reform gains under new regime. | H9: Budget Paper No. 2
A10: New residential property | B10: Generally eligible for 50% discount after 12 months | C10: Choice of 50% discount or indexation plus minimum tax | D10: 1-Jul-2027 | F10: New residential property investors | G10: Calculator selects lower tax option when marked Yes. | H10: Budget Paper No. 2
A11: Income support recipients | B11: No minimum-tax concept | C11: Exempt from 30% minimum tax | D11: 1-Jul-2027 | F11: Including Age Pension recipients | G11: Minimum tax disabled when marked Yes. | H11: Budget Paper No. 2
A12: Foreign resident CGT | B12: Separate regime | C12: Separate transitional arrangements | F12: Foreign residents | G12: Not modelled. | H12: Out of scope
A13: Main residence and small business concessions | B13: Specific concessions may apply | C13: Not modelled by this comparison | F13: Eligible taxpayers/assets | G13: Not modelled. | H13: Scope limitation
A16: Default CPI/indexation assumptions
A17: Financial year ending | B17: Default CPI / indexation rate | C17: Editable? | E17: Named assumption | F17: Cell / value | G17: Used by | H17: Note
A18: 2028 | B18: 0.025 | C18: Yes | E18: Reform commencement date | F18: 1-Jul-2027 | G18: Input + Calculator | H18: Budget Paper No. 2 start date.
A19: 2029 | B19: 0.025 | C19: Yes | E19: New-regime minimum tax | F19: 0.3 | G19: Calculator | H19: Budget Paper No. 2 minimum tax.
A20: 2030 | B20: 0.025 | C20: Yes | E20: Default annual CPI | F20: 0.025 | G20: Input | H20: Override on Input tab or asset row.
A21: 2031 | B21: 0.025 | C21: Yes
A22: 2032 | B22: 0.025 | C22: Yes
A23: 2033 | B23: 0.025 | C23: Yes
A24: 2034 | B24: 0.025 | C24: Yes
A25: 2035 | B25: 0.025 | C25: Yes
A26: 2036 | B26: 0.025 | C26: Yes
A27: 2037 | B27: 0.025 | C27: Yes
A28: 2038 | B28: 0.025 | C28: Yes
A29: 2039 | B29: 0.025 | C29: Yes
